Workbook

Sheet Setup_Macro
B1: ⚙️ SETUP MACRO — CONFIGURAZIONE
B3: ⚠ IMPORTANTE: scrivi il percorso del file storico DIRETTAMENTE nella cella D4 (es: C:\Users\Mario\Desktop\Riepilogo_Energia_STORICO.xlsx) e salva il file. Non basta selezionarlo dalla finestra di dialogo — devi digitarlo nella cella.
B4: Percorso file storico: | D4: C:\Users\TuoNome\Desktop\Riepilogo_Energia_STORICO.xlsx
B5: Anno PVGIS (2005-2020): | D5: 2020 | E5: ⚠ Max 2020 — oltre questa data PVGIS non ha dati
B6: Percorso detailed-history.xlsx: | D6: C:\Users\TuoNome\Desktop\detailed-history.xlsx
B7: ISTRUZIONI: 1) Alt+F11 → Inserisci Modulo → incolla codice → Ctrl+S → .xlsm | 2) Crea pulsanti in Dashboard: verde=AggiornaDaStorico | viola=AggiornaPVGIS | blu=AggiornaCompleto
B8: CODICE VBA — copia tutto il testo verde sotto e incollalo nel Modulo VBA
B9: ' D4 = percorso Riepilogo_Energia_STORICO.xlsx
B10: ' D5 = Anno (PVGIS max 2020 | Open-Meteo storico da 1940)
B11: ' D6 = percorso detailed-history.xlsx (incentivi)
B13: Sub TestPVGIS_Debug()
B14: Dim http As Object, sUrl As String, sResp As String
B15: sUrl = "https://re.jrc.ec.europa.eu/api/v5_2/PVcalc"
B16: sUrl = sUrl & "?lat=37.236750&lon=13.742667&peakpower=1&loss=0"
B17: sUrl = sUrl & "&angle=30&aspect=0&startyear=2020&endyear=2020&outputformat=json"
B18: Set http = CreateObject("WinHttp.WinHttpRequest.5.1")
B19: http.Open "GET", sUrl, False
... B407: End Function

Sheet Fonte_Dati
B1: 📥 FONTE DATI — STORICO ENERGIA & FATTURATO
B4: Importato da: Riepilogo_Energia_STORICO.xlsx | Periodo: Q1 2026 | 16 Impianti | Aggiornato: 16/03/2026
B5: ⚠ Questo foglio è la fonte centralizzata. Gli altri fogli leggono da qui via SUMIF. Non modificare la struttura.
B7: Anno | C7: Mese | D7: Impianto | E7: Energia Mis. (kWh) | F7: Energia Magg. (kWh) | G7: Fatturato Lordo (€) | H7: Fee (€) | I7: Fatturato Netto (€) | J7: EUR/MWh | K7: Tipo
B8: 2026 | C8: Gennaio | D8: FV-Batia S. Francesco | E8: 425760.24 | F8: 424057.2 | G8: 47434.025 | H8: -84.81144 | I8: 47349.213 | J8: 0 | K8: Fotovoltaico
B9: 2026 | C9: Gennaio | D9: FV-Campofranco Tetto | E9: 24295.24 | F9: 24854.031 | G9: 3025.1312 | H9: -4.9708061 | I9: 3020.1604 | J9: 0 | K9: Fotovoltaico
B10: 2026 | C10: Gennaio | D10: FV-Fauma Tetto | E10: 652486.4 | F10: 667493.59 | G10: 79168.413 | H10: -133.49872 | I10: 79034.914 | J10: 0 | K10: Fotovoltaico
B11: 2026 | C11: Gennaio | D11: FV-Favara Grande | E11: 629425.76 | F11: 643902.55 | G11: 76759.684 | H11: -128.78051 | I11: 76630.904 | J11: 0 | K11: Fotovoltaico
B12: 2026 | C12: Gennaio | D12: FV-Malvizzo Piccolo | E12: 111376.12 | F12: 110930.62 | G12: 12280.38 | H12: -22.186124 | I12: 12258.194 | J12: 0 | K12: Fotovoltaico
B13: 2026 | C13: Gennaio | D13: FV-Malvizzo a Terra | E13: 112069.2 | F13: 111620.92 | G13: 12199.659 | H13: -22.324185 | I13: 12177.335 | J13: 0 | K13: Fotovoltaico
B14: 2026 | C14: Gennaio | D14: FV-Narbone Piccolo | E14: 33209.7 | F14: 33076.861 | G14: 3870.2981 | H14: -6.6153722 | I14: 3863.6828 | J14: 0 | K14: Fotovoltaico
B15: 2026 | C15: Gennaio | D15: FV-Narbone a Terra Grande | E15: 76190.16 | F15: 75885.399 | G15: 8742.4718 | H15: -15.17708 | I15: 8727.2947 | J15: 0 | K15: Fotovoltaico
B16: 2026 | C16: Gennaio | D16: FV-Perniciara | E16: 209754.75 | F16: 214579.11 | G16: 25631.128 | H16: -42.915822 | I16: 25588.212 | J16: 0 | K16: Fotovoltaico
B17: 2026 | C17: Gennaio | D17: FV-Serre Gela | E17: 199294.56 | F17: 203878.33 | G17: 24021.424 | H17: -40.775667 | I17: 23980.648 | J17: 0 | K17: Fotovoltaico
B18: 2026 | C18: Gennaio | D18: FV-Serre Narbone | E18: 353361.6 | F18: 351948.15 | G18: 41581.31 | H18: -70.389631 | I18: 41510.92 | J18: 0 | K18: Fotovoltaico
B19: 2026 | C19: Gennaio | D19: FV-Serre S.Angelo Muxaro | E19: 356199.6 | F19: 364392.19 | G19: 43280.191 | H19: -72.878438 | I19: 43207.313 | J19: 0 | K19: Fotovoltaico
... B55: 2026 | C55: Marzo | D55: Wind - Monte Narbone | E55: 348.54082 | F55: 356.55726 | G55: 43.314576 | H55: -0.071311452 | I55: 43.243264 | J55: 0 | K55: Eolico
B56: TOTALE Q1 2026 | E56: =SUM(F8:F55) -> 28924178 | F56: =SUM(G8:G55) -> 3133013.1 | G56: =SUM(H8:H55) -> -5784.8357 | H56: =SUM(I8:I55) -> 3127228.3 | I56: =SUM(J8:J55) -> 0

Sheet DB_Impianti
B1: 🗄️ DATABASE PORTFOLIO — DATI REALI Q1 2026
B4: 16 Impianti (13 FV + 3 Eolici) | Q1 2026 | Celle gialle = dati tecnici da completare
B6: ANAGRAFICA IMPIANTI | K6: DATI TECNICI (da compilare) | U6: PR — Formula IEC 61724-1
B7: ID | C7: Impianto | D7: Tipo | E7: Trader | F7: Ragione Sociale | G7: PVI | H7: Fee (€/MWh) | I7: Regione | J7: Anno Ins. | K7: kWp DC ⚠ | L7: kW AC ⚠ | M7: Vita Resid.⚠ | N7: En. Mis. Q1 (MWh) | O7: En. Magg. Q1 (MWh) | P7: Fatturato Lordo Q1 (€) | Q7: Fee Q1 (€) | R7: Fatturato Netto Q1 (€) | S7: EUR/MWh medio | T7: OPEX est. (€) | U7: Irr. Q1 (kWh/m²) | V7: PR Q1 (%) IEC
B8: 1 | C8: Wind - Monte Narbone | D8: Eolico | E8: DXT | F8: Moncada Energy Group Srl | G8: PVI_S19MNEN_001 | H8: -1.36 | I8: Sicilia | N8: =IFERROR(SUMIFS(Fonte_Dati!E:E,Fonte_Dati!D:D,C8)/1000,0) -> 9096.2236 | O8: =IFERROR(SUMIFS(Fonte_Dati!F:F,Fonte_Dati!D:D,C8)/1000,0) -> 9096.2316 | P8: =IFERROR(SUMIFS(Fonte_Dati!G:G,Fonte_Dati!D:D,C8),0) -> 1042617.3 | Q8: =IFERROR(SUMIFS(Fonte_Dati!H:H,Fonte_Dati!D:D,C8),0) -> -1819.2463 | R8: =IFERROR(SUMIFS(Fonte_Dati!I:I,Fonte_Dati!D:D,C8),0) -> 1040798.1 | S8: =IFERROR(R8/O8,0) -> 114.4208 | T8: =IFERROR(R8*0.08,0) -> 83263.847 | U8: =IFERROR(VLOOKUP(C8,Irraggiamento_PVGIS!C50:H65,6,0),"") | V8: =IFERROR((N8*1000)/(U8*K8),"")
B9: 2 | C9: Wind - Monte Durrà | D9: Eolico | E9: BANCO ENERGIA | F9: Moncada Energy Group Srl | G9: PVI_S19MDEN_001 | H9: -1.86 | I9: Sicilia | N9: =IFERROR(SUMIFS(Fonte_Dati!E:E,Fonte_Dati!D:D,C9)/1000,0) -> 8107.3148 | O9: =IFERROR(SUMIFS(Fonte_Dati!F:F,Fonte_Dati!D:D,C9)/1000,0) -> 8107.3148 | P9: =IFERROR(SUMIFS(Fonte_Dati!G:G,Fonte_Dati!D:D,C9),0) -> 908432.26 | Q9: =IFERROR(SUMIFS(Fonte_Dati!H:H,Fonte_Dati!D:D,C9),0) -> -1621.463 | R9: =IFERROR(SUMIFS(Fonte_Dati!I:I,Fonte_Dati!D:D,C9),0) -> 906810.8 | S9: =IFERROR(R9/O9,0) -> 111.85094 | T9: =IFERROR(R9*0.08,0) -> 72544.864 | U9: =IFERROR(VLOOKUP(C9,Irraggiamento_PVGIS!C50:H65,6,0),"") | V9: =IFERROR((N9*1000)/(U9*K9),"")
B10: 3 | C10: Wind - Monte Malvizzo | D10: Eolico | E10: DXT | F10: Moncada Energy Group Srl | G10: PVI_S19MMEN_001 | H10: -1.36 | I10: Sicilia | N10: =IFERROR(SUMIFS(Fonte_Dati!E:E,Fonte_Dati!D:D,C10)/1000,0) -> 3945.0563 | O10: =IFERROR(SUMIFS(Fonte_Dati!F:F,Fonte_Dati!D:D,C10)/1000,0) -> 3945.0775 | P10: =IFERROR(SUMIFS(Fonte_Dati!G:G,Fonte_Dati!D:D,C10),0) -> 445055.51 | Q10: =IFERROR(SUMIFS(Fonte_Dati!H:H,Fonte_Dati!D:D,C10),0) -> -789.0155 | R10: =IFERROR(SUMIFS(Fonte_Dati!I:I,Fonte_Dati!D:D,C10),0) -> 444266.5 | S10: =IFERROR(R10/O10,0) -> 112.61287 | T10: =IFERROR(R10*0.08,0) -> 35541.32 | U10: =IFERROR(VLOOKUP(C10,Irraggiamento_PVGIS!C50:H65,6,0),"") | V10: =IFERROR((N10*1000)/(U10*K10),"")
B11: 4 | C11: FV-Favara Grande | D11: Fotovoltaico | E11: AXPO | F11: Biopower 2 Srl | H11: -0.2 | I11: Sicilia | N11: =IFERROR(SUMIFS(Fonte_Dati!E:E,Fonte_Dati!D:D,C11)/1000,0) -> 1544.2125 | O11: =IFERROR(SUMIFS(Fonte_Dati!F:F,Fonte_Dati!D:D,C11)/1000,0) -> 1579.7294 | P11: =IFERROR(SUMIFS(Fonte_Dati!G:G,Fonte_Dati!D:D,C11),0) -> 150406.67 | Q11: =IFERROR(SUMIFS(Fonte_Dati!H:H,Fonte_Dati!D:D,C11),0) -> -315.94587 | R11: =IFERROR(SUMIFS(Fonte_Dati!I:I,Fonte_Dati!D:D,C11),0) -> 150090.73 | S11: =IFERROR(R11/O11,0) -> 95.010406 | T11: =IFERROR(R11*0.08,0) -> 12007.258 | U11: =IFERROR(VLOOKUP(C11,Irraggiamento_PVGIS!C50:H65,6,0),"") -> 0 | V11: =IFERROR((N11*1000)/(U11*K11),"")
B12: 5 | C12: FV-Fauma Tetto | D12: Fotovoltaico | E12: AXPO | F12: Biopower 3 Srl | H12: -0.2 | I12: Sicilia | N12: =IFERROR(SUMIFS(Fonte_Dati!E:E,Fonte_Dati!D:D,C12)/1000,0) -> 1503.9636 | O12: =IFERROR(SUMIFS(Fonte_Dati!F:F,Fonte_Dati!D:D,C12)/1000,0) -> 1538.5548 | P12: =IFERROR(SUMIFS(Fonte_Dati!G:G,Fonte_Dati!D:D,C12),0) -> 148356.71 | Q12: =IFERROR(SUMIFS(Fonte_Dati!H:H,Fonte_Dati!D:D,C12),0) -> -307.71095 | R12: =IFERROR(SUMIFS(Fonte_Dati!I:I,Fonte_Dati!D:D,C12),0) -> 148049 | S12: =IFERROR(R12/O12,0) -> 96.226018 | T12: =IFERROR(R12*0.08,0) -> 11843.92 | U12: =IFERROR(VLOOKUP(C12,Irraggiamento_PVGIS!C50:H65,6,0),"") -> 0 | V12: =IFERROR((N12*1000)/(U12*K12),"")
B13: 6 | C13: FV-Batia S. Francesco | D13: Fotovoltaico | E13: DXT | F13: Energie Innovative Srl | G13: PVI_0435789_001 | H13: -0.2 | I13: Sicilia | N13: =IFERROR(SUMIFS(Fonte_Dati!E:E,Fonte_Dati!D:D,C13)/1000,0) -> 1146.8885 | O13: =IFERROR(SUMIFS(Fonte_Dati!F:F,Fonte_Dati!D:D,C13)/1000,0) -> 1142.3009 | P13: =IFERROR(SUMIFS(Fonte_Dati!G:G,Fonte_Dati!D:D,C13),0) -> 103510.6 | Q13: =IFERROR(SUMIFS(Fonte_Dati!H:H,Fonte_Dati!D:D,C13),0) -> -228.46019 | R13: =IFERROR(SUMIFS(Fonte_Dati!I:I,Fonte_Dati!D:D,C13),0) -> 103282.14 | S13: =IFERROR(R13/O13,0) -> 90.415876 | T13: =IFERROR(R13*0.08,0) -> 8262.5711 | U13: =IFERROR(VLOOKUP(C13,Irraggiamento_PVGIS!C50:H65,6,0),"") -> 0 | V13: =IFERROR((N13*1000)/(U13*K13),"")
B14: 7 | C14: FV-Serre S.Angelo Muxaro | D14: Fotovoltaico | E14: DXT | F14: Società Agricola Solar Farm 3 Srl | G14: PVI_0363736_001 | H14: -0.2 | I14: Sicilia | N14: =IFERROR(SUMIFS(Fonte_Dati!E:E,Fonte_Dati!D:D,C14)/1000,0) -> 787.1292 | O14: =IFERROR(SUMIFS(Fonte_Dati!F:F,Fonte_Dati!D:D,C14)/1000,0) -> 805.23317 | P14: =IFERROR(SUMIFS(Fonte_Dati!G:G,Fonte_Dati!D:D,C14),0) -> 77680.731 | Q14: =IFERROR(SUMIFS(Fonte_Dati!H:H,Fonte_Dati!D:D,C14),0) -> -161.04663 | R14: =IFERROR(SUMIFS(Fonte_Dati!I:I,Fonte_Dati!D:D,C14),0) -> 77519.685 | S14: =IFERROR(R14/O14,0) -> 96.26986 | T14: =IFERROR(R14*0.08,0) -> 6201.5748 | U14: =IFERROR(VLOOKUP(C14,Irraggiamento_PVGIS!C50:H65,6,0),"") -> 0 | V14: =IFERROR((N14*1000)/(U14*K14),"")
B15: 8 | C15: FV-Serre Narbone | D15: Fotovoltaico | E15: DXT | F15: Società Agricola Solar Farm Srl | G15: PVI_S19SNRR_001 | H15: -0.2 | I15: Sicilia | N15: =IFERROR(SUMIFS(Fonte_Dati!E:E,Fonte_Dati!D:D,C15)/1000,0) -> 801.5076 | O15: =IFERROR(SUMIFS(Fonte_Dati!F:F,Fonte_Dati!D:D,C15)/1000,0) -> 798.30157 | P15: =IFERROR(SUMIFS(Fonte_Dati!G:G,Fonte_Dati!D:D,C15),0) -> 76124.436 | Q15: =IFERROR(SUMIFS(Fonte_Dati!H:H,Fonte_Dati!D:D,C15),0) -> -159.66031 | R15: =IFERROR(SUMIFS(Fonte_Dati!I:I,Fonte_Dati!D:D,C15),0) -> 75964.775 | S15: =IFERROR(R15/O15,0) -> 95.157993 | T15: =IFERROR(R15*0.08,0) -> 6077.182 | U15: =IFERROR(VLOOKUP(C15,Irraggiamento_PVGIS!C50:H65,6,0),"") -> 0 | V15: =IFERROR((N15*1000)/(U15*K15),"")
B16: 9 | C16: FV-Perniciara | D16: Fotovoltaico | E16: AXPO | F16: Biopower 2 Srl | H16: -0.2 | I16: Sicilia | N16: =IFERROR(SUMIFS(Fonte_Dati!E:E,Fonte_Dati!D:D,C16)/1000,0) -> 521.4165 | O16: =IFERROR(SUMIFS(Fonte_Dati!F:F,Fonte_Dati!D:D,C16)/1000,0) -> 533.40908 | P16: =IFERROR(SUMIFS(Fonte_Dati!G:G,Fonte_Dati!D:D,C16),0) -> 50858.787 | Q16: =IFERROR(SUMIFS(Fonte_Dati!H:H,Fonte_Dati!D:D,C16),0) -> -106.68182 | R16: =IFERROR(SUMIFS(Fonte_Dati!I:I,Fonte_Dati!D:D,C16),0) -> 50752.105 | S16: =IFERROR(R16/O16,0) -> 95.146684 | T16: =IFERROR(R16*0.08,0) -> 4060.1684 | U16: =IFERROR(VLOOKUP(C16,Irraggiamento_PVGIS!C50:H65,6,0),"") -> 0 | V16: =IFERROR((N16*1000)/(U16*K16),"")
B17: 10 | C17: FV-Serre Gela | D17: Fotovoltaico | E17: DXT | F17: Società Agricola Solar Farm 5 Srl | G17: PVI_0384558_001 | H17: -0.2 | I17: Sicilia | N17: =IFERROR(SUMIFS(Fonte_Dati!E:E,Fonte_Dati!D:D,C17)/1000,0) -> 476.96608 | O17: =IFERROR(SUMIFS(Fonte_Dati!F:F,Fonte_Dati!D:D,C17)/1000,0) -> 487.9363 | P17: =IFERROR(SUMIFS(Fonte_Dati!G:G,Fonte_Dati!D:D,C17),0) -> 46577.793 | Q17: =IFERROR(SUMIFS(Fonte_Dati!H:H,Fonte_Dati!D:D,C17),0) -> -97.58726 | R17: =IFERROR(SUMIFS(Fonte_Dati!I:I,Fonte_Dati!D:D,C17),0) -> 46480.205 | S17: =IFERROR(R17/O17,0) -> 95.258757 | T17: =IFERROR(R17*0.08,0) -> 3718.4164 | U17: =IFERROR(VLOOKUP(C17,Irraggiamento_PVGIS!C50:H65,6,0),"") -> 0 | V17: =IFERROR((N17*1000)/(U17*K17),"")
B18: 11 | C18: FV-Malvizzo Piccolo | D18: Fotovoltaico | E18: AXPO | F18: ERM Srl | H18: -0.2 | I18: Sicilia | N18: =IFERROR(SUMIFS(Fonte_Dati!E:E,Fonte_Dati!D:D,C18)/1000,0) -> 326.17582 | O18: =IFERROR(SUMIFS(Fonte_Dati!F:F,Fonte_Dati!D:D,C18)/1000,0) -> 324.87112 | P18: =IFERROR(SUMIFS(Fonte_Dati!G:G,Fonte_Dati!D:D,C18),0) -> 29734.277 | Q18: =IFERROR(SUMIFS(Fonte_Dati!H:H,Fonte_Dati!D:D,C18),0) -> -64.974224 | R18: =IFERROR(SUMIFS(Fonte_Dati!I:I,Fonte_Dati!D:D,C18),0) -> 29669.302 | S18: =IFERROR(R18/O18,0) -> 91.326377 | T18: =IFERROR(R18*0.08,0) -> 2373.5442 | U18: =IFERROR(VLOOKUP(C18,Irraggiamento_PVGIS!C50:H65,6,0),"") -> 0 | V18: =IFERROR((N18*1000)/(U18*K18),"")
B19: 12 | C19: FV-Malvizzo a Terra | D19: Fotovoltaico | E19: DXT | F19: Moncada Energy Solar Srl | G19: PVI_0397946_001 | H19: -0.2 | I19: Sicilia | N19: =IFERROR(SUMIFS(Fonte_Dati!E:E,Fonte_Dati!D:D,C19)/1000,0) -> 320.47704 | O19: =IFERROR(SUMIFS(Fonte_Dati!F:F,Fonte_Dati!D:D,C19)/1000,0) -> 319.19513 | P19: =IFERROR(SUMIFS(Fonte_Dati!G:G,Fonte_Dati!D:D,C19),0) -> 29047.258 | Q19: =IFERROR(SUMIFS(Fonte_Dati!H:H,Fonte_Dati!D:D,C19),0) -> -63.839026 | R19: =IFERROR(SUMIFS(Fonte_Dati!I:I,Fonte_Dati!D:D,C19),0) -> 28983.419 | S19: =IFERROR(R19/O19,0) -> 90.80157 | T19: =IFERROR(R19*0.08,0) -> 2318.6735 | U19: =IFERROR(VLOOKUP(C19,Irraggiamento_PVGIS!C50:H65,6,0),"") -> 0 | V19: =IFERROR((N19*1000)/(U19*K19),"")
B20: 13 | C20: FV-Narbone a Terra Grande | D20: Fotovoltaico | E20: DXT | F20: Moncada Energy Solar Srl | G20: PVI_0397937_001 | H20: -0.2 | I20: Sicilia | N20: =IFERROR(SUMIFS(Fonte_Dati!E:E,Fonte_Dati!D:D,C20)/1000,0) -> 76.19016 | O20: =IFERROR(SUMIFS(Fonte_Dati!F:F,Fonte_Dati!D:D,C20)/1000,0) -> 75.885399 | P20: =IFERROR(SUMIFS(Fonte_Dati!G:G,Fonte_Dati!D:D,C20),0) -> 8742.4718 | Q20: =IFERROR(SUMIFS(Fonte_Dati!H:H,Fonte_Dati!D:D,C20),0) -> -15.17708 | R20: =IFERROR(SUMIFS(Fonte_Dati!I:I,Fonte_Dati!D:D,C20),0) -> 8727.2947 | S20: =IFERROR(R20/O20,0) -> 115.00624 | T20: =IFERROR(R20*0.08,0) -> 698.18358 | U20: =IFERROR(VLOOKUP(C20,Irraggiamento_PVGIS!C50:H65,6,0),"") -> 0 | V20: =IFERROR((N20*1000)/(U20*K20),"")
B21: 14 | C21: FV-Narbone Piccolo | D21: Fotovoltaico | E21: AXPO | F21: ERM Srl | H21: -0.2 | I21: Sicilia | N21: =IFERROR(SUMIFS(Fonte_Dati!E:E,Fonte_Dati!D:D,C21)/1000,0) -> 78.51654 | O21: =IFERROR(SUMIFS(Fonte_Dati!F:F,Fonte_Dati!D:D,C21)/1000,0) -> 78.202474 | P21: =IFERROR(SUMIFS(Fonte_Dati!G:G,Fonte_Dati!D:D,C21),0) -> 7402.499 | Q21: =IFERROR(SUMIFS(Fonte_Dati!H:H,Fonte_Dati!D:D,C21),0) -> -15.640495 | R21: =IFERROR(SUMIFS(Fonte_Dati!I:I,Fonte_Dati!D:D,C21),0) -> 7386.8585 | S21: =IFERROR(R21/O21,0) -> 94.458118 | T21: =IFERROR(R21*0.08,0) -> 590.94868 | U21: =IFERROR(VLOOKUP(C21,Irraggiamento_PVGIS!C50:H65,6,0),"") -> 0 | V21: =IFERROR((N21*1000)/(U21*K21),"")
B22: 15 | C22: FV-Campofranco Tetto | D22: Fotovoltaico | E22: DXT | F22: Moncada Energy Group Srl | G22: PVI_0130620_001 | H22: -0.2 | I22: Sicilia | N22: =IFERROR(SUMIFS(Fonte_Dati!E:E,Fonte_Dati!D:D,C22)/1000,0) -> 70.70192 | O22: =IFERROR(SUMIFS(Fonte_Dati!F:F,Fonte_Dati!D:D,C22)/1000,0) -> 72.328064 | P22: =IFERROR(SUMIFS(Fonte_Dati!G:G,Fonte_Dati!D:D,C22),0) -> 6636.8041 | Q22: =IFERROR(SUMIFS(Fonte_Dati!H:H,Fonte_Dati!D:D,C22),0) -> -14.465613 | R22: =IFERROR(SUMIFS(Fonte_Dati!I:I,Fonte_Dati!D:D,C22),0) -> 6622.3385 | S22: =IFERROR(R22/O22,0) -> 91.559736 | T22: =IFERROR(R22*0.08,0) -> 529.78708 | U22: =IFERROR(VLOOKUP(C22,Irraggiamento_PVGIS!C50:H65,6,0),"") -> 0 | V22: =IFERROR((N22*1000)/(U22*K22),"")
B23: 16 | C23: FV-Tumarrano MEG | D23: Fotovoltaico | E23: DXT | F23: Moncada Energy Group Srl | G23: PVI_0558896_001 | H23: -0.2 | I23: Sicilia | N23: =IFERROR(SUMIFS(Fonte_Dati!E:E,Fonte_Dati!D:D,C23)/1000,0) -> 19.16622 | O23: =IFERROR(SUMIFS(Fonte_Dati!F:F,Fonte_Dati!D:D,C23)/1000,0) -> 19.607043 | P23: =IFERROR(SUMIFS(Fonte_Dati!G:G,Fonte_Dati!D:D,C23),0) -> 1828.9881 | Q23: =IFERROR(SUMIFS(Fonte_Dati!H:H,Fonte_Dati!D:D,C23),0) -> -3.9214086 | R23: =IFERROR(SUMIFS(Fonte_Dati!I:I,Fonte_Dati!D:D,C23),0) -> 1825.0667 | S23: =IFERROR(R23/O23,0) -> 93.082199 | T23: =IFERROR(R23*0.08,0) -> 146.00533 | U23: =IFERROR(VLOOKUP(C23,Irraggiamento_PVGIS!C50:H65,6,0),"") -> 0 | V23: =IFERROR((N23*1000)/(U23*K23),"")
B24: TOTALE PORTFOLIO Q1 2026 | N24: =SUM(O8:O23) -> 28924.178 | O24: =SUM(P8:P23) -> 3133013.1 | P24: =SUM(Q8:Q23) -> -5784.8357 | Q24: =SUM(R8:R23) -> 3127228.3 | R24: =IFERROR(SUM(R8:R23),0) -> 3127228.3 | S24: =IFERROR(R24/O24,"") -> 0.99815359 | T24: =IFERROR(SUM(T8:T23),0) -> 250178.26 | U24: =IFERROR(AVERAGE(V8:V23),"") | V24: =IFERROR(AVERAGE(V8:V23),"")

Sheet Dashboard
B1: ☀ PORTFOLIO AM — DASHBOARD ESECUTIVO ☀
B4: Q1 2026 | 16 Impianti (13 FV + 3 Eolici) | Elaborato: 16/03/2026
B5: ▶ AGGIORNA DATI | E5: 🌞 AGGIORNA PVGIS | I5: ▶▶ AGGIORNA TUTTO (storico + PVGIS) | L5: ← Assegna macro: verde=AggiornaDaStorico | viola=AggiornaPVGIS | blu=AggiornaCompleto
C6: ⚡ ENERGIA MISURATA Q1 | F6: 💰 FATTURATO NETTO Q1 | I6: 📈 PREZZO MEDIO EUR/MWh | L6: 🔋 IMPIANTI ATTIVI
C7: 28,822 MWh | F7: € 3.127 M | I7: € 108.12/MWh | L7: 16 / 16
C8: ▲ Gennaio + Febbraio + Marzo | F8: ▲ Fee contrattuale applicata | I8: ▲ Media ponderata per MWh | L8: ✅ Portfolio 100% operativo
C10: ☀ IMPIANTI FOTOVOLTAICI | F10: 💨 IMPIANTI EOLICI | I10: 💹 FATTURATO LORDO Q1 | L10: 🏦 EBITDA STIMATO Q1
C11: 13 impianti | F11: 3 impianti | I11: € 3.133 M | L11: € 2.877 M
C12: Fat. Netto: € 0.735 M | F12: Fat. Netto: € 2.392 M | I12: Fee totale: € 5,785 | L12: ▲ Margin ~92% (OPEX ~8%)
B13: 💹 INCENTIVI GSE — ACCONTO Q1 2026 (ADVANCE-GSE × TARIFF)
C14: 💹 ACCONTO INCENTIVI Q1 | F14: ✅ CONSUNTIVO INCENTIVI Q1 | I14: 📐 DELTA Cons. − Acc. | L14: 🏦 EBITDA + INCENTIVI
C15: =IFERROR(TEXT('💹 Incentivi'!R24,"€ #,##0"),"—") -> € 2,826,099 | F15: =IFERROR(TEXT('💹 Incentivi'!R44,"€ #,##0"),"—") -> € 1,123,198 | I15: =IFERROR(TEXT('💹 Incentivi'!R64,"+€ #,##0;-€ #,##0;€ 0"),"—") -> -€ 1,702,901 | L15: =IFERROR(TEXT(Finanziario!N24,"€ #,##0"),"—") -> € 4,582,009
C16: ADVANCE-GSE × Tariffa | F16: OWNER × Tariffa | I16: Aggiustamento consuntivo | L16: EBITDA mercato + cons. inc.
C17: RIEPILOGO IMPIANTI — STATUS Q1 2026
C18: ID | D18: Impianto | E18: Tipo | F18: Trader | G18: Ragione Sociale | H18: En. Mis. Q1 (MWh) | I18: En. Magg. Q1 (MWh) | J18: Fat. Lordo (€) | K18: Fee (€) | L18: Fat. Netto (€) | M18: EUR/MWh | N18: OPEX est. (€)
C19: 1 | D19: Wind - Monte Narbone | E19: Eolico | F19: =IFERROR(SUMIFS(Fonte_Dati!E:E,Fonte_Dati!D:D,D16)/1000,0) -> 0 | G19: =IFERROR(SUMIFS(Fonte_Dati!F:F,Fonte_Dati!D:D,D16)/1000,0) -> 0 | H19: =IFERROR(SUMIFS(Fonte_Dati!G:G,Fonte_Dati!D:D,D16),0) -> 0 | I19: =IFERROR(SUMIFS(Fonte_Dati!H:H,Fonte_Dati!D:D,D16),0) -> 0 | J19: =IFERROR(SUMIFS(Fonte_Dati!I:I,Fonte_Dati!D:D,D16),0) -> 0 | K19: =IFERROR(J16/G16,0) -> 0 | L19: =IFERROR(J16*0.08,0) -> 0 | M19: 114.4208 | N19: 83264
C20: 2 | D20: Wind - Monte Durrà | E20: Eolico | F20: =IFERROR(SUMIFS(Fonte_Dati!E:E,Fonte_Dati!D:D,D17)/1000,0) -> 0 | G20: =IFERROR(SUMIFS(Fonte_Dati!F:F,Fonte_Dati!D:D,D17)/1000,0) -> 0 | H20: =IFERROR(SUMIFS(Fonte_Dati!G:G,Fonte_Dati!D:D,D17),0) -> 0 | I20: =IFERROR(SUMIFS(Fonte_Dati!H:H,Fonte_Dati!D:D,D17),0) -> 0 | J20: =IFERROR(SUMIFS(Fonte_Dati!I:I,Fonte_Dati!D:D,D17),0) -> 0 | K20: =IFERROR(J17/G17,0) -> 0 | L20: =IFERROR(J17*0.08,0) -> 0 | M20: 111.85094 | N20: 72545
C21: 3 | D21: Wind - Monte Malvizzo | E21: Eolico | F21: =IFERROR(SUMIFS(Fonte_Dati!E:E,Fonte_Dati!D:D,D18)/1000,0) -> 0 | G21: =IFERROR(SUMIFS(Fonte_Dati!F:F,Fonte_Dati!D:D,D18)/1000,0) -> 0 | H21: =IFERROR(SUMIFS(Fonte_Dati!G:G,Fonte_Dati!D:D,D18),0) -> 0 | I21: =IFERROR(SUMIFS(Fonte_Dati!H:H,Fonte_Dati!D:D,D18),0) -> 0 | J21: =IFERROR(SUMIFS(Fonte_Dati!I:I,Fonte_Dati!D:D,D18),0) -> 0 | K21: =IFERROR(J18/G18,0) -> 0 | L21: =IFERROR(J18*0.08,0) -> 0 | M21: 112.61287 | N21: 35541
C22: 4 | D22: FV-Favara Grande | E22: Fotovoltaico | F22: =IFERROR(SUMIFS(Fonte_Dati!E:E,Fonte_Dati!D:D,D19)/1000,0) -> 9096.2236 | G22: =IFERROR(SUMIFS(Fonte_Dati!F:F,Fonte_Dati!D:D,D19)/1000,0) -> 9096.2316 | H22: =IFERROR(SUMIFS(Fonte_Dati!G:G,Fonte_Dati!D:D,D19),0) -> 1042617.3 | I22: =IFERROR(SUMIFS(Fonte_Dati!H:H,Fonte_Dati!D:D,D19),0) -> -1819.2463 | J22: =IFERROR(SUMIFS(Fonte_Dati!I:I,Fonte_Dati!D:D,D19),0) -> 1040798.1 | K22: =IFERROR(J19/G19,0) -> 0 | L22: =IFERROR(J19*0.08,0) -> 0 | M22: 95.010406 | N22: 12007
C23: 5 | D23: FV-Fauma Tetto | E23: Fotovoltaico | F23: =IFERROR(SUMIFS(Fonte_Dati!E:E,Fonte_Dati!D:D,D20)/1000,0) -> 8107.3148 | G23: =IFERROR(SUMIFS(Fonte_Dati!F:F,Fonte_Dati!D:D,D20)/1000,0) -> 8107.3148 | H23: =IFERROR(SUMIFS(Fonte_Dati!G:G,Fonte_Dati!D:D,D20),0) -> 908432.26 | I23: =IFERROR(SUMIFS(Fonte_Dati!H:H,Fonte_Dati!D:D,D20),0) -> -1621.463 | J23: =IFERROR(SUMIFS(Fonte_Dati!I:I,Fonte_Dati!D:D,D20),0) -> 906810.8 | K23: =IFERROR(J20/G20,0) -> 0 | L23: =IFERROR(J20*0.08,0) -> 0 | M23: 96.226018 | N23: 11844
C24: 6 | D24: FV-Batia S. Francesco | E24: Fotovoltaico | F24: =IFERROR(SUMIFS(Fonte_Dati!E:E,Fonte_Dati!D:D,D21)/1000,0) -> 3945.0563 | G24: =IFERROR(SUMIFS(Fonte_Dati!F:F,Fonte_Dati!D:D,D21)/1000,0) -> 3945.0775 | H24: =IFERROR(SUMIFS(Fonte_Dati!G:G,Fonte_Dati!D:D,D21),0) -> 445055.51 | I24: =IFERROR(SUMIFS(Fonte_Dati!H:H,Fonte_Dati!D:D,D21),0) -> -789.0155 | J24: =IFERROR(SUMIFS(Fonte_Dati!I:I,Fonte_Dati!D:D,D21),0) -> 444266.5 | K24: =IFERROR(J21/G21,0) -> 0 | L24: =IFERROR(J21*0.08,0) -> 0 | M24: 90.415876 | N24: 8263
C25: 7 | D25: FV-Serre S.Angelo Muxaro | E25: Fotovoltaico | F25: =IFERROR(SUMIFS(Fonte_Dati!E:E,Fonte_Dati!D:D,D22)/1000,0) -> 1544.2125 | G25: =IFERROR(SUMIFS(Fonte_Dati!F:F,Fonte_Dati!D:D,D22)/1000,0) -> 1579.7294 | H25: =IFERROR(SUMIFS(Fonte_Dati!G:G,Fonte_Dati!D:D,D22),0) -> 150406.67 | I25: =IFERROR(SUMIFS(Fonte_Dati!H:H,Fonte_Dati!D:D,D22),0) -> -315.94587 | J25: =IFERROR(SUMIFS(Fonte_Dati!I:I,Fonte_Dati!D:D,D22),0) -> 150090.73 | K25: =IFERROR(J22/G22,0) -> 114.4208 | L25: =IFERROR(J22*0.08,0) -> 83263.847 | M25: 96.26986 | N25: 6202
C26: 8 | D26: FV-Serre Narbone | E26: Fotovoltaico | F26: =IFERROR(SUMIFS(Fonte_Dati!E:E,Fonte_Dati!D:D,D23)/1000,0) -> 1503.9636 | G26: =IFERROR(SUMIFS(Fonte_Dati!F:F,Fonte_Dati!D:D,D23)/1000,0) -> 1538.5548 | H26: =IFERROR(SUMIFS(Fonte_Dati!G:G,Fonte_Dati!D:D,D23),0) -> 148356.71 | I26: =IFERROR(SUMIFS(Fonte_Dati!H:H,Fonte_Dati!D:D,D23),0) -> -307.71095 | J26: =IFERROR(SUMIFS(Fonte_Dati!I:I,Fonte_Dati!D:D,D23),0) -> 148049 | K26: =IFERROR(J23/G23,0) -> 111.85094 | L26: =IFERROR(J23*0.08,0) -> 72544.864 | M26: 95.157993 | N26: 6077
C27: 9 | D27: FV-Perniciara | E27: Fotovoltaico | F27: =IFERROR(SUMIFS(Fonte_Dati!E:E,Fonte_Dati!D:D,D24)/1000,0) -> 1146.8885 | G27: =IFERROR(SUMIFS(Fonte_Dati!F:F,Fonte_Dati!D:D,D24)/1000,0) -> 1142.3009 | H27: =IFERROR(SUMIFS(Fonte_Dati!G:G,Fonte_Dati!D:D,D24),0) -> 103510.6 | I27: =IFERROR(SUMIFS(Fonte_Dati!H:H,Fonte_Dati!D:D,D24),0) -> -228.46019 | J27: =IFERROR(SUMIFS(Fonte_Dati!I:I,Fonte_Dati!D:D,D24),0) -> 103282.14 | K27: =IFERROR(J24/G24,0) -> 112.61287 | L27: =IFERROR(J24*0.08,0) -> 35541.32 | M27: 95.146684 | N27: 4060
C28: 10 | D28: FV-Serre Gela | E28: Fotovoltaico | F28: =IFERROR(SUMIFS(Fonte_Dati!E:E,Fonte_Dati!D:D,D25)/1000,0) -> 787.1292 | G28: =IFERROR(SUMIFS(Fonte_Dati!F:F,Fonte_Dati!D:D,D25)/1000,0) -> 805.23317 | H28: =IFERROR(SUMIFS(Fonte_Dati!G:G,Fonte_Dati!D:D,D25),0) -> 77680.731 | I28: =IFERROR(SUMIFS(Fonte_Dati!H:H,Fonte_Dati!D:D,D25),0) -> -161.04663 | J28: =IFERROR(SUMIFS(Fonte_Dati!I:I,Fonte_Dati!D:D,D25),0) -> 77519.685 | K28: =IFERROR(J25/G25,0) -> 95.010406 | L28: =IFERROR(J25*0.08,0) -> 12007.258 | M28: 95.258757 | N28: 3718
C29: 11 | D29: FV-Malvizzo Piccolo | E29: Fotovoltaico | F29: =IFERROR(SUMIFS(Fonte_Dati!E:E,Fonte_Dati!D:D,D26)/1000,0) -> 801.5076 | G29: =IFERROR(SUMIFS(Fonte_Dati!F:F,Fonte_Dati!D:D,D26)/1000,0) -> 798.30157 | H29: =IFERROR(SUMIFS(Fonte_Dati!G:G,Fonte_Dati!D:D,D26),0) -> 76124.436 | I29: =IFERROR(SUMIFS(Fonte_Dati!H:H,Fonte_Dati!D:D,D26),0) -> -159.66031 | J29: =IFERROR(SUMIFS(Fonte_Dati!I:I,Fonte_Dati!D:D,D26),0) -> 75964.775 | K29: =IFERROR(J26/G26,0) -> 96.226018 | L29: =IFERROR(J26*0.08,0) -> 11843.92 | M29: 91.326377 | N29: 2374
C30: 12 | D30: FV-Malvizzo a Terra | E30: Fotovoltaico | F30: =IFERROR(SUMIFS(Fonte_Dati!E:E,Fonte_Dati!D:D,D27)/1000,0) -> 521.4165 | G30: =IFERROR(SUMIFS(Fonte_Dati!F:F,Fonte_Dati!D:D,D27)/1000,0) -> 533.40908 | H30: =IFERROR(SUMIFS(Fonte_Dati!G:G,Fonte_Dati!D:D,D27),0) -> 50858.787 | I30: =IFERROR(SUMIFS(Fonte_Dati!H:H,Fonte_Dati!D:D,D27),0) -> -106.68182 | J30: =IFERROR(SUMIFS(Fonte_Dati!I:I,Fonte_Dati!D:D,D27),0) -> 50752.105 | K30: =IFERROR(J27/G27,0) -> 90.415876 | L30: =IFERROR(J27*0.08,0) -> 8262.5711 | M30: 90.80157 | N30: 2319
C31: 13 | D31: FV-Narbone a Terra Grande | E31: Fotovoltaico | F31: =IFERROR(SUMIFS(Fonte_Dati!E:E,Fonte_Dati!D:D,D28)/1000,0) -> 476.96608 | G31: =IFERROR(SUMIFS(Fonte_Dati!F:F,Fonte_Dati!D:D,D28)/1000,0) -> 487.9363 | H31: =IFERROR(SUMIFS(Fonte_Dati!G:G,Fonte_Dati!D:D,D28),0) -> 46577.793 | I31: =IFERROR(SUMIFS(Fonte_Dati!H:H,Fonte_Dati!D:D,D28),0) -> -97.58726 | J31: =IFERROR(SUMIFS(Fonte_Dati!I:I,Fonte_Dati!D:D,D28),0) -> 46480.205 | K31: =IFERROR(J28/G28,0) -> 96.26986 | L31: =IFERROR(J28*0.08,0) -> 6201.5748 | M31: 115.00624 | N31: 698
C32: 14 | F32: =IFERROR(SUMIFS(Fonte_Dati!E:E,Fonte_Dati!D:D,D29)/1000,0) -> 326.17582 | G32: =IFERROR(SUMIFS(Fonte_Dati!F:F,Fonte_Dati!D:D,D29)/1000,0) -> 324.87112 | H32: =IFERROR(SUMIFS(Fonte_Dati!G:G,Fonte_Dati!D:D,D29),0) -> 29734.277 | I32: =IFERROR(SUMIFS(Fonte_Dati!H:H,Fonte_Dati!D:D,D29),0) -> -64.974224 | J32: =IFERROR(SUMIFS(Fonte_Dati!I:I,Fonte_Dati!D:D,D29),0) -> 29669.302 | K32: =IFERROR(J29/G29,0) -> 95.157993 | L32: =IFERROR(J29*0.08,0) -> 6077.182 | M32: 94.458118 | N32: 591
C33: 15 | D33: FV-Campofranco Tetto | E33: Fotovoltaico | F33: =IFERROR(SUMIFS(Fonte_Dati!E:E,Fonte_Dati!D:D,D30)/1000,0) -> 320.47704 | G33: =IFERROR(SUMIFS(Fonte_Dati!F:F,Fonte_Dati!D:D,D30)/1000,0) -> 319.19513 | H33: =IFERROR(SUMIFS(Fonte_Dati!G:G,Fonte_Dati!D:D,D30),0) -> 29047.258 | I33: =IFERROR(SUMIFS(Fonte_Dati!H:H,Fonte_Dati!D:D,D30),0) -> -63.839026 | J33: =IFERROR(SUMIFS(Fonte_Dati!I:I,Fonte_Dati!D:D,D30),0) -> 28983.419 | K33: =IFERROR(J30/G30,0) -> 95.146684 | L33: =IFERROR(J30*0.08,0) -> 4060.1684 | M33: 91.559736 | N33: 530
C34: 16 | D34: FV-Tumarrano MEG | E34: Fotovoltaico | F34: =IFERROR(SUMIFS(Fonte_Dati!E:E,Fonte_Dati!D:D,D31)/1000,0) -> 76.19016 | G34: =IFERROR(SUMIFS(Fonte_Dati!F:F,Fonte_Dati!D:D,D31)/1000,0) -> 75.885399 | H34: =IFERROR(SUMIFS(Fonte_Dati!G:G,Fonte_Dati!D:D,D31),0) -> 8742.4718 | I34: =IFERROR(SUMIFS(Fonte_Dati!H:H,Fonte_Dati!D:D,D31),0) -> -15.17708 | J34: =IFERROR(SUMIFS(Fonte_Dati!I:I,Fonte_Dati!D:D,D31),0) -> 8727.2947 | K34: =IFERROR(J31/G31,0) -> 95.258757 | L34: =IFERROR(J31*0.08,0) -> 3718.4164 | M34: 93.082199 | N34: 146
C35: TOTALE PORTFOLIO | F35: =SUM(F16:F31) -> 27930.679 | G35: =SUM(G16:G31) -> 28034.089 | H35: =SUM(H16:H31) -> 3049620.8 | I35: =SUM(I16:I31) -> -5606.8178 | J35: =SUM(J16:J31) -> 3044014 | K35: =IFERROR(J32/G32,0) -> 91.326377 | L35: =SUM(L16:L31) -> 229665.35

Sheet Produzione
B1: ⚡ PRODUZIONE ENERGETICA MENSILE — PORTFOLIO Q1 2026
B4: Energia Misurata (kWh→MWh) e Maggiorata per Impianto | Fonte: _Storico_Dati_
B6: ENERGIA MISURATA (MWh) — BREAKDOWN MENSILE | O6: PERFORMANCE RATIO (IEC 61724-1) — PR = E_real [kWh] / (H(i) [kWh/m²] × kWp DC)
B7: ID | C7: Impianto | D7: Tipo | E7: Gen 2026 (MWh) | F7: Feb 2026 (MWh) | G7: Mar 2026 (MWh) | H7: Totale Q1 (MWh) | I7: Gen/Tot % | J7: Gen vs Feb | K7: Feb vs Gen | L7: EUR/MWh Gen | M7: EUR/MWh Feb | N7: EUR/MWh Q1 | O7: kWp DC | P7: Irr. Gen (kWh/m²) | Q7: Irr. Feb (kWh/m²) | R7: Irr. Mar (kWh/m²) | S7: PR Gen (%) | T7: PR Feb (%) | U7: PR Mar (%) | V7: PR Q1 (%)
B8: 1 | C8: Wind - Monte Narbone | D8: Eolico | E8: =IFERROR(SUMIFS(Fonte_Dati!E:E,Fonte_Dati!D:D,C8,Fonte_Dati!C:C,"Gennaio")/1000,0) -> 4716.6952 | F8: =IFERROR(SUMIFS(Fonte_Dati!E:E,Fonte_Dati!D:D,C8,Fonte_Dati!C:C,"Febbraio")/1000,0) -> 4379.1799 | G8: =IFERROR(SUMIFS(Fonte_Dati!E:E,Fonte_Dati!D:D,C8,Fonte_Dati!C:C,"Marzo")/1000,0) -> 0.34854082 | H8: =SUM(E8:G8) -> 9096.2236 | I8: =IFERROR(E8/H8,0) -> 0.51853334 | J8: =IFERROR(F8-E8,0) -> -337.51536 | K8: =IFERROR((F8-E8)/E8,"-") -> -0.071557594 | L8: =IFERROR(SUMIFS(Fonte_Dati!I:I,Fonte_Dati!D:D,C8,Fonte_Dati!C:C,"Gennaio")/(SUMIFS(Fonte_Dati!F:F,Fonte_Dati!D:D,C8,Fonte_Dati!C:C,"Gennaio")/1000),0) -> 124.75426 | M8: =IFERROR(SUMIFS(Fonte_Dati!I:I,Fonte_Dati!D:D,C8,Fonte_Dati!C:C,"Febbraio")/(SUMIFS(Fonte_Dati!F:F,Fonte_Dati!D:D,C8,Fonte_Dati!C:C,"Febbraio")/1000),0) -> 103.29036 | N8: =IFERROR(SUMIFS(Fonte_Dati!I:I,Fonte_Dati!D:D,C8)/(SUMIFS(Fonte_Dati!F:F,Fonte_Dati!D:D,C8)/1000),0) -> 114.4208 | O8: =IFERROR(VLOOKUP(C8,DB_Impianti!C:K,9,0),"") -> 0 | P8: =IFERROR(VLOOKUP(C8,Irraggiamento_PVGIS!C50:H65,3,0),"") | Q8: =IFERROR(VLOOKUP(C8,Irraggiamento_PVGIS!C50:H65,4,0),"") | R8: =IFERROR(VLOOKUP(C8,Irraggiamento_PVGIS!C50:H65,5,0),"") | S8: =IFERROR((E8*1000)/(P8*O8),"") | T8: =IFERROR((F8*1000)/(Q8*O8),"") | U8: =IFERROR((G8*1000)/(R8*O8),"") | V8: =IFERROR((H8*1000)/(VLOOKUP(C8,Irraggiamento_PVGIS!C50:H65,6,0)*O8),"")
B9: 2 | C9: Wind - Monte Durrà | D9: Eolico | E9: =IFERROR(SUMIFS(Fonte_Dati!E:E,Fonte_Dati!D:D,C9,Fonte_Dati!C:C,"Gennaio")/1000,0) -> 3977.1227 | F9: =IFERROR(SUMIFS(Fonte_Dati!E:E,Fonte_Dati!D:D,C9,Fonte_Dati!C:C,"Febbraio")/1000,0) -> 4130.1921 | G9: =IFERROR(SUMIFS(Fonte_Dati!E:E,Fonte_Dati!D:D,C9,Fonte_Dati!C:C,"Marzo")/1000,0) -> 0 | H9: =SUM(E9:G9) -> 8107.3148 | I9: =IFERROR(E9/H9,0) -> 0.4905598 | J9: =IFERROR(F9-E9,0) -> 153.0694 | K9: =IFERROR((F9-E9)/E9,"-") -> 0.038487471 | L9: =IFERROR(SUMIFS(Fonte_Dati!I:I,Fonte_Dati!D:D,C9,Fonte_Dati!C:C,"Gennaio")/(SUMIFS(Fonte_Dati!F:F,Fonte_Dati!D:D,C9,Fonte_Dati!C:C,"Gennaio")/1000),0) -> 120.79263 | M9: =IFERROR(SUMIFS(Fonte_Dati!I:I,Fonte_Dati!D:D,C9,Fonte_Dati!C:C,"Febbraio")/(SUMIFS(Fonte_Dati!F:F,Fonte_Dati!D:D,C9,Fonte_Dati!C:C,"Febbraio")/1000),0) -> 103.24065 | N9: =IFERROR(SUMIFS(Fonte_Dati!I:I,Fonte_Dati!D:D,C9)/(SUMIFS(Fonte_Dati!F:F,Fonte_Dati!D:D,C9)/1000),0) -> 111.85094 | O9: =IFERROR(VLOOKUP(C9,DB_Impianti!C:K,9,0),"") -> 0 | P9: =IFERROR(VLOOKUP(C9,Irraggiamento_PVGIS!C50:H65,3,0),"") | Q9: =IFERROR(VLOOKUP(C9,Irraggiamento_PVGIS!C50:H65,4,0),"") | R9: =IFERROR(VLOOKUP(C9,Irraggiamento_PVGIS!C50:H65,5,0),"") | S9: =IFERROR((E9*1000)/(P9*O9),"") | T9: =IFERROR((F9*1000)/(Q9*O9),"") | U9: =IFERROR((G9*1000)/(R9*O9),"") | V9: =IFERROR((H9*1000)/(VLOOKUP(C9,Irraggiamento_PVGIS!C50:H65,6,0)*O9),"")
B10: 3 | C10: Wind - Monte Malvizzo | D10: Eolico | E10: =IFERROR(SUMIFS(Fonte_Dati!E:E,Fonte_Dati!D:D,C10,Fonte_Dati!C:C,"Gennaio")/1000,0) -> 1906.8542 | F10: =IFERROR(SUMIFS(Fonte_Dati!E:E,Fonte_Dati!D:D,C10,Fonte_Dati!C:C,"Febbraio")/1000,0) -> 2037.2792 | G10: =IFERROR(SUMIFS(Fonte_Dati!E:E,Fonte_Dati!D:D,C10,Fonte_Dati!C:C,"Marzo")/1000,0) -> 0.9229494 | H10: =SUM(E10:G10) -> 3945.0563 | I10: =IFERROR(E10/H10,0) -> 0.48335284 | J10: =IFERROR(F10-E10,0) -> 130.425 | K10: =IFERROR((F10-E10)/E10,"-") -> 0.068397996 | L10: =IFERROR(SUMIFS(Fonte_Dati!I:I,Fonte_Dati!D:D,C10,Fonte_Dati!C:C,"Gennaio")/(SUMIFS(Fonte_Dati!F:F,Fonte_Dati!D:D,C10,Fonte_Dati!C:C,"Gennaio")/1000),0) -> 119.02333 | M10: =IFERROR(SUMIFS(Fonte_Dati!I:I,Fonte_Dati!D:D,C10,Fonte_Dati!C:C,"Febbraio")/(SUMIFS(Fonte_Dati!F:F,Fonte_Dati!D:D,C10,Fonte_Dati!C:C,"Febbraio")/1000),0) -> 106.60879 | N10: =IFERROR(SUMIFS(Fonte_Dati!I:I,Fonte_Dati!D:D,C10)/(SUMIFS(Fonte_Dati!F:F,Fonte_Dati!D:D,C10)/1000),0) -> 112.61287 | O10: =IFERROR(VLOOKUP(C10,DB_Impianti!C:K,9,0),"") -> 0 | P10: =IFERROR(VLOOKUP(C10,Irraggiamento_PVGIS!C50:H65,3,0),"") | Q10: =IFERROR(VLOOKUP(C10,Irraggiamento_PVGIS!C50:H65,4,0),"") | R10: =IFERROR(VLOOKUP(C10,Irraggiamento_PVGIS!C50:H65,5,0),"") | S10: =IFERROR((E10*1000)/(P10*O10),"") | T10: =IFERROR((F10*1000)/(Q10*O10),"") | U10: =IFERROR((G10*1000)/(R10*O10),"") | V10: =IFERROR((H10*1000)/(VLOOKUP(C10,Irraggiamento_PVGIS!C50:H65,6,0)*O10),"")
B11: 4 | C11: FV-Favara Grande | D11: Fotovoltaico | E11: =IFERROR(SUMIFS(Fonte_Dati!E:E,Fonte_Dati!D:D,C11,Fonte_Dati!C:C,"Gennaio")/1000,0) -> 629.42576 | F11: =IFERROR(SUMIFS(Fonte_Dati!E:E,Fonte_Dati!D:D,C11,Fonte_Dati!C:C,"Febbraio")/1000,0) -> 914.78672 | G11: =IFERROR(SUMIFS(Fonte_Dati!E:E,Fonte_Dati!D:D,C11,Fonte_Dati!C:C,"Marzo")/1000,0) -> 0 | H11: =SUM(E11:G11) -> 1544.2125 | I11: =IFERROR(E11/H11,0) -> 0.40760308 | J11: =IFERROR(F11-E11,0) -> 285.36096 | K11: =IFERROR((F11-E11)/E11,"-") -> 0.45336715 | L11: =IFERROR(SUMIFS(Fonte_Dati!I:I,Fonte_Dati!D:D,C11,Fonte_Dati!C:C,"Gennaio")/(SUMIFS(Fonte_Dati!F:F,Fonte_Dati!D:D,C11,Fonte_Dati!C:C,"Gennaio")/1000),0) -> 119.01009 | M11: =IFERROR(SUMIFS(Fonte_Dati!I:I,Fonte_Dati!D:D,C11,Fonte_Dati!C:C,"Febbraio")/(SUMIFS(Fonte_Dati!F:F,Fonte_Dati!D:D,C11,Fonte_Dati!C:C,"Febbraio")/1000),0) -> 78.497243 | N11: =IFERROR(SUMIFS(Fonte_Dati!I:I,Fonte_Dati!D:D,C11)/(SUMIFS(Fonte_Dati!F:F,Fonte_Dati!D:D,C11)/1000),0) -> 95.010406 | O11: =IFERROR(VLOOKUP(C11,DB_Impianti!C:K,9,0),"") -> 0 | P11: =IFERROR(VLOOKUP(C11,Irraggiamento_PVGIS!C50:H65,3,0),"") -> 0 | Q11: =IFERROR(VLOOKUP(C11,Irraggiamento_PVGIS!C50:H65,4,0),"") -> 0 | R11: =IFERROR(VLOOKUP(C11,Irraggiamento_PVGIS!C50:H65,5,0),"") -> 0 | S11: =IFERROR((E11*1000)/(P11*O11),"") | T11: =IFERROR((F11*1000)/(Q11*O11),"") | U11: =IFERROR((G11*1000)/(R11*O11),"") | V11: =IFERROR((H11*1000)/(VLOOKUP(C11,Irraggiamento_PVGIS!C50:H65,6,0)*O11),"")
B12: 5 | C12: FV-Fauma Tetto | D12: Fotovoltaico | E12: =IFERROR(SUMIFS(Fonte_Dati!E:E,Fonte_Dati!D:D,C12,Fonte_Dati!C:C,"Gennaio")/1000,0) -> 652.4864 | F12: =IFERROR(SUMIFS(Fonte_Dati!E:E,Fonte_Dati!D:D,C12,Fonte_Dati!C:C,"Febbraio")/1000,0) -> 851.4772 | G12: =IFERROR(SUMIFS(Fonte_Dati!E:E,Fonte_Dati!D:D,C12,Fonte_Dati!C:C,"Marzo")/1000,0) -> 0 | H12: =SUM(E12:G12) -> 1503.9636 | I12: =IFERROR(E12/H12,0) -> 0.43384454 | J12: =IFERROR(F12-E12,0) -> 198.9908 | K12: =IFERROR((F12-E12)/E12,"-") -> 0.3049731 | L12: =IFERROR(SUMIFS(Fonte_Dati!I:I,Fonte_Dati!D:D,C12,Fonte_Dati!C:C,"Gennaio")/(SUMIFS(Fonte_Dati!F:F,Fonte_Dati!D:D,C12,Fonte_Dati!C:C,"Gennaio")/1000),0) -> 118.4055 | M12: =IFERROR(SUMIFS(Fonte_Dati!I:I,Fonte_Dati!D:D,C12,Fonte_Dati!C:C,"Febbraio")/(SUMIFS(Fonte_Dati!F:F,Fonte_Dati!D:D,C12,Fonte_Dati!C:C,"Febbraio")/1000),0) -> 79.229894 | N12: =IFERROR(SUMIFS(Fonte_Dati!I:I,Fonte_Dati!D:D,C12)/(SUMIFS(Fonte_Dati!F:F,Fonte_Dati!D:D,C12)/1000),0) -> 96.226018 | O12: =IFERROR(VLOOKUP(C12,DB_Impianti!C:K,9,0),"") -> 0 | P12: =IFERROR(VLOOKUP(C12,Irraggiamento_PVGIS!C50:H65,3,0),"") -> 0 | Q12: =IFERROR(VLOOKUP(C12,Irraggiamento_PVGIS!C50:H65,4,0),"") -> 0 | R12: =IFERROR(VLOOKUP(C12,Irraggiamento_PVGIS!C50:H65,5,0),"") -> 0 | S12: =IFERROR((E12*1000)/(P12*O12),"") | T12: =IFERROR((F12*1000)/(Q12*O12),"") | U12: =IFERROR((G12*1000)/(R12*O12),"") | V12: =IFERROR((H12*1000)/(VLOOKUP(C12,Irraggiamento_PVGIS!C50:H65,6,0)*O12),"")
B13: 6 | C13: FV-Batia S. Francesco | D13: Fotovoltaico | E13: =IFERROR(SUMIFS(Fonte_Dati!E:E,Fonte_Dati!D:D,C13,Fonte_Dati!C:C,"Gennaio")/1000,0) -> 425.76024 | F13: =IFERROR(SUMIFS(Fonte_Dati!E:E,Fonte_Dati!D:D,C13,Fonte_Dati!C:C,"Febbraio")/1000,0) -> 721.12824 | G13: =IFERROR(SUMIFS(Fonte_Dati!E:E,Fonte_Dati!D:D,C13,Fonte_Dati!C:C,"Marzo")/1000,0) -> 0 | H13: =SUM(E13:G13) -> 1146.8885 | I13: =IFERROR(E13/H13,0) -> 0.37123072 | J13: =IFERROR(F13-E13,0) -> 295.368 | K13: =IFERROR((F13-E13)/E13,"-") -> 0.69374256 | L13: =IFERROR(SUMIFS(Fonte_Dati!I:I,Fonte_Dati!D:D,C13,Fonte_Dati!C:C,"Gennaio")/(SUMIFS(Fonte_Dati!F:F,Fonte_Dati!D:D,C13,Fonte_Dati!C:C,"Gennaio")/1000),0) -> 111.65761 | M13: =IFERROR(SUMIFS(Fonte_Dati!I:I,Fonte_Dati!D:D,C13,Fonte_Dati!C:C,"Febbraio")/(SUMIFS(Fonte_Dati!F:F,Fonte_Dati!D:D,C13,Fonte_Dati!C:C,"Febbraio")/1000),0) -> 77.874575 | N13: =IFERROR(SUMIFS(Fonte_Dati!I:I,Fonte_Dati!D:D,C13)/(SUMIFS(Fonte_Dati!F:F,Fonte_Dati!D:D,C13)/1000),0) -> 90.415876 | O13: =IFERROR(VLOOKUP(C13,DB_Impianti!C:K,9,0),"") -> 0 | P13: =IFERROR(VLOOKUP(C13,Irraggiamento_PVGIS!C50:H65,3,0),"") -> 0 | Q13: =IFERROR(VLOOKUP(C13,Irraggiamento_PVGIS!C50:H65,4,0),"") -> 0 | R13: =IFERROR(VLOOKUP(C13,Irraggiamento_PVGIS!C50:H65,5,0),"") -> 0 | S13: =IFERROR((E13*1000)/(P13*O13),"") | T13: =IFERROR((F13*1000)/(Q13*O13),"") | U13: =IFERROR((G13*1000)/(R13*O13),"") | V13: =IFERROR((H13*1000)/(VLOOKUP(C13,Irraggiamento_PVGIS!C50:H65,6,0)*O13),"")
B14: 7 | C14: FV-Serre S.Angelo Muxaro | D14: Fotovoltaico | E14: =IFERROR(SUMIFS(Fonte_Dati!E:E,Fonte_Dati!D:D,C14,Fonte_Dati!C:C,"Gennaio")/1000,0) -> 356.1996 | F14: =IFERROR(SUMIFS(Fonte_Dati!E:E,Fonte_Dati!D:D,C14,Fonte_Dati!C:C,"Febbraio")/1000,0) -> 430.9296 | G14: =IFERROR(SUMIFS(Fonte_Dati!E:E,Fonte_Dati!D:D,C14,Fonte_Dati!C:C,"Marzo")/1000,0) -> 0 | H14: =SUM(E14:G14) -> 787.1292 | I14: =IFERROR(E14/H14,0) -> 0.45253003 | J14: =IFERROR(F14-E14,0) -> 74.73 | K14: =IFERROR((F14-E14)/E14,"-") -> 0.2097981 | L14: =IFERROR(SUMIFS(Fonte_Dati!I:I,Fonte_Dati!D:D,C14,Fonte_Dati!C:C,"Gennaio")/(SUMIFS(Fonte_Dati!F:F,Fonte_Dati!D:D,C14,Fonte_Dati!C:C,"Gennaio")/1000),0) -> 118.57365 | M14: =IFERROR(SUMIFS(Fonte_Dati!I:I,Fonte_Dati!D:D,C14,Fonte_Dati!C:C,"Febbraio")/(SUMIFS(Fonte_Dati!F:F,Fonte_Dati!D:D,C14,Fonte_Dati!C:C,"Febbraio")/1000),0) -> 77.833898 | N14: =IFERROR(SUMIFS(Fonte_Dati!I:I,Fonte_Dati!D:D,C14)/(SUMIFS(Fonte_Dati!F:F,Fonte_Dati!D:D,C14)/1000),0) -> 96.26986 | O14: =IFERROR(VLOOKUP(C14,DB_Impianti!C:K,9,0),"") -> 0 | P14: =IFERROR(VLOOKUP(C14,Irraggiamento_PVGIS!C50:H65,3,0),"") -> 0 | Q14: =IFERROR(VLOOKUP(C14,Irraggiamento_PVGIS!C50:H65,4,0),"") -> 0 | R14: =IFERROR(VLOOKUP(C14,Irraggiamento_PVGIS!C50:H65,5,0),"") -> 0 | S14: =IFERROR((E14*1000)/(P14*O14),"") | T14: =IFERROR((F14*1000)/(Q14*O14),"") | U14: =IFERROR((G14*1000)/(R14*O14),"") | V14: =IFERROR((H14*1000)/(VLOOKUP(C14,Irraggiamento_PVGIS!C50:H65,6,0)*O14),"")
B15: 8 | C15: FV-Serre Narbone | D15: Fotovoltaico | E15: =IFERROR(SUMIFS(Fonte_Dati!E:E,Fonte_Dati!D:D,C15,Fonte_Dati!C:C,"Gennaio")/1000,0) -> 353.3616 | F15: =IFERROR(SUMIFS(Fonte_Dati!E:E,Fonte_Dati!D:D,C15,Fonte_Dati!C:C,"Febbraio")/1000,0) -> 448.146 | G15: =IFERROR(SUMIFS(Fonte_Dati!E:E,Fonte_Dati!D:D,C15,Fonte_Dati!C:C,"Marzo")/1000,0) -> 0 | H15: =SUM(E15:G15) -> 801.5076 | I15: =IFERROR(E15/H15,0) -> 0.44087118 | J15: =IFERROR(F15-E15,0) -> 94.7844 | K15: =IFERROR((F15-E15)/E15,"-") -> 0.26823628 | L15: =IFERROR(SUMIFS(Fonte_Dati!I:I,Fonte_Dati!D:D,C15,Fonte_Dati!C:C,"Gennaio")/(SUMIFS(Fonte_Dati!F:F,Fonte_Dati!D:D,C15,Fonte_Dati!C:C,"Gennaio")/1000),0) -> 117.94612 | M15: =IFERROR(SUMIFS(Fonte_Dati!I:I,Fonte_Dati!D:D,C15,Fonte_Dati!C:C,"Febbraio")/(SUMIFS(Fonte_Dati!F:F,Fonte_Dati!D:D,C15,Fonte_Dati!C:C,"Febbraio")/1000),0) -> 77.189631 | N15: =IFERROR(SUMIFS(Fonte_Dati!I:I,Fonte_Dati!D:D,C15)/(SUMIFS(Fonte_Dati!F:F,Fonte_Dati!D:D,C15)/1000),0) -> 95.157993 | O15: =IFERROR(VLOOKUP(C15,DB_Impianti!C:K,9,0),"") -> 0 | P15: =IFERROR(VLOOKUP(C15,Irraggiamento_PVGIS!C50:H65,3,0),"") -> 0 | Q15: =IFERROR(VLOOKUP(C15,Irraggiamento_PVGIS!C50:H65,4,0),"") -> 0 | R15: =IFERROR(VLOOKUP(C15,Irraggiamento_PVGIS!C50:H65,5,0),"") -> 0 | S15: =IFERROR((E15*1000)/(P15*O15),"") | T15: =IFERROR((F15*1000)/(Q15*O15),"") | U15: =IFERROR((G15*1000)/(R15*O15),"") | V15: =IFERROR((H15*1000)/(VLOOKUP(C15,Irraggiamento_PVGIS!C50:H65,6,0)*O15),"")
B16: 9 | C16: FV-Perniciara | D16: Fotovoltaico | E16: =IFERROR(SUMIFS(Fonte_Dati!E:E,Fonte_Dati!D:D,C16,Fonte_Dati!C:C,"Gennaio")/1000,0) -> 209.75475 | F16: =IFERROR(SUMIFS(Fonte_Dati!E:E,Fonte_Dati!D:D,C16,Fonte_Dati!C:C,"Febbraio")/1000,0) -> 311.66175 | G16: =IFERROR(SUMIFS(Fonte_Dati!E:E,Fonte_Dati!D:D,C16,Fonte_Dati!C:C,"Marzo")/1000,0) -> 0 | H16: =SUM(E16:G16) -> 521.4165 | I16: =IFERROR(E16/H16,0) -> 0.4022787 | J16: =IFERROR(F16-E16,0) -> 101.907 | K16: =IFERROR((F16-E16)/E16,"-") -> 0.48583882 | L16: =IFERROR(SUMIFS(Fonte_Dati!I:I,Fonte_Dati!D:D,C16,Fonte_Dati!C:C,"Gennaio")/(SUMIFS(Fonte_Dati!F:F,Fonte_Dati!D:D,C16,Fonte_Dati!C:C,"Gennaio")/1000),0) -> 119.24838 | M16: =IFERROR(SUMIFS(Fonte_Dati!I:I,Fonte_Dati!D:D,C16,Fonte_Dati!C:C,"Febbraio")/(SUMIFS(Fonte_Dati!F:F,Fonte_Dati!D:D,C16,Fonte_Dati!C:C,"Febbraio")/1000),0) -> 78.925747 | N16: =IFERROR(SUMIFS(Fonte_Dati!I:I,Fonte_Dati!D:D,C16)/(SUMIFS(Fonte_Dati!F:F,Fonte_Dati!D:D,C16)/1000),0) -> 95.146684 | O16: =IFERROR(VLOOKUP(C16,DB_Impianti!C:K,9,0),"") -> 0 | P16: =IFERROR(VLOOKUP(C16,Irraggiamento_PVGIS!C50:H65,3,0),"") -> 0 | Q16: =IFERROR(VLOOKUP(C16,Irraggiamento_PVGIS!C50:H65,4,0),"") -> 0 | R16: =IFERROR(VLOOKUP(C16,Irraggiamento_PVGIS!C50:H65,5,0),"") -> 0 | S16: =IFERROR((E16*1000)/(P16*O16),"") | T16: =IFERROR((F16*1000)/(Q16*O16),"") | U16: =IFERROR((G16*1000)/(R16*O16),"") | V16: =IFERROR((H16*1000)/(VLOOKUP(C16,Irraggiamento_PVGIS!C50:H65,6,0)*O16),"")
B17: 10 | C17: FV-Serre Gela | D17: Fotovoltaico | E17: =IFERROR(SUMIFS(Fonte_Dati!E:E,Fonte_Dati!D:D,C17,Fonte_Dati!C:C,"Gennaio")/1000,0) -> 199.29456 | F17: =IFERROR(SUMIFS(Fonte_Dati!E:E,Fonte_Dati!D:D,C17,Fonte_Dati!C:C,"Febbraio")/1000,0) -> 277.67152 | G17: =IFERROR(SUMIFS(Fonte_Dati!E:E,Fonte_Dati!D:D,C17,Fonte_Dati!C:C,"Marzo")/1000,0) -> 0 | H17: =SUM(E17:G17) -> 476.96608 | I17: =IFERROR(E17/H17,0) -> 0.41783801 | J17: =IFERROR(F17-E17,0) -> 78.37696 | K17: =IFERROR((F17-E17)/E17,"-") -> 0.39327195 | L17: =IFERROR(SUMIFS(Fonte_Dati!I:I,Fonte_Dati!D:D,C17,Fonte_Dati!C:C,"Gennaio")/(SUMIFS(Fonte_Dati!F:F,Fonte_Dati!D:D,C17,Fonte_Dati!C:C,"Gennaio")/1000),0) -> 117.62235 | M17: =IFERROR(SUMIFS(Fonte_Dati!I:I,Fonte_Dati!D:D,C17,Fonte_Dati!C:C,"Febbraio")/(SUMIFS(Fonte_Dati!F:F,Fonte_Dati!D:D,C17,Fonte_Dati!C:C,"Febbraio")/1000),0) -> 79.207626 | N17: =IFERROR(SUMIFS(Fonte_Dati!I:I,Fonte_Dati!D:D,C17)/(SUMIFS(Fonte_Dati!F:F,Fonte_Dati!D:D,C17)/1000),0) -> 95.258757 | O17: =IFERROR(VLOOKUP(C17,DB_Impianti!C:K,9,0),"") -> 0 | P17: =IFERROR(VLOOKUP(C17,Irraggiamento_PVGIS!C50:H65,3,0),"") -> 0 | Q17: =IFERROR(VLOOKUP(C17,Irraggiamento_PVGIS!C50:H65,4,0),"") -> 0 | R17: =IFERROR(VLOOKUP(C17,Irraggiamento_PVGIS!C50:H65,5,0),"") -> 0 | S17: =IFERROR((E17*1000)/(P17*O17),"") | T17: =IFERROR((F17*1000)/(Q17*O17),"") | U17: =IFERROR((G17*1000)/(R17*O17),"") | V17: =IFERROR((H17*1000)/(VLOOKUP(C17,Irraggiamento_PVGIS!C50:H65,6,0)*O17),"")
B18: 11 | C18: FV-Malvizzo Piccolo | D18: Fotovoltaico | E18: =IFERROR(SUMIFS(Fonte_Dati!E:E,Fonte_Dati!D:D,C18,Fonte_Dati!C:C,"Gennaio")/1000,0) -> 111.37613 | F18: =IFERROR(SUMIFS(Fonte_Dati!E:E,Fonte_Dati!D:D,C18,Fonte_Dati!C:C,"Febbraio")/1000,0) -> 214.7997 | G18: =IFERROR(SUMIFS(Fonte_Dati!E:E,Fonte_Dati!D:D,C18,Fonte_Dati!C:C,"Marzo")/1000,0) -> 0 | H18: =SUM(E18:G18) -> 326.17582 | I18: =IFERROR(E18/H18,0) -> 0.34146039 | J18: =IFERROR(F18-E18,0) -> 103.42357 | K18: =IFERROR((F18-E18)/E18,"-") -> 0.92859735 | L18: =IFERROR(SUMIFS(Fonte_Dati!I:I,Fonte_Dati!D:D,C18,Fonte_Dati!C:C,"Gennaio")/(SUMIFS(Fonte_Dati!F:F,Fonte_Dati!D:D,C18,Fonte_Dati!C:C,"Gennaio")/1000),0) -> 110.50325 | M18: =IFERROR(SUMIFS(Fonte_Dati!I:I,Fonte_Dati!D:D,C18,Fonte_Dati!C:C,"Febbraio")/(SUMIFS(Fonte_Dati!F:F,Fonte_Dati!D:D,C18,Fonte_Dati!C:C,"Febbraio")/1000),0) -> 81.382945 | N18: =IFERROR(SUMIFS(Fonte_Dati!I:I,Fonte_Dati!D:D,C18)/(SUMIFS(Fonte_Dati!F:F,Fonte_Dati!D:D,C18)/1000),0) -> 91.326377 | O18: =IFERROR(VLOOKUP(C18,DB_Impianti!C:K,9,0),"") -> 0 | P18: =IFERROR(VLOOKUP(C18,Irraggiamento_PVGIS!C50:H65,3,0),"") -> 0 | Q18: =IFERROR(VLOOKUP(C18,Irraggiamento_PVGIS!C50:H65,4,0),"") -> 0 | R18: =IFERROR(VLOOKUP(C18,Irraggiamento_PVGIS!C50:H65,5,0),"") -> 0 | S18: =IFERROR((E18*1000)/(P18*O18),"") | T18: =IFERROR((F18*1000)/(Q18*O18),"") | U18: =IFERROR((G18*1000)/(R18*O18),"") | V18: =IFERROR((H18*1000)/(VLOOKUP(C18,Irraggiamento_PVGIS!C50:H65,6,0)*O18),"")
B19: 12 | C19: FV-Malvizzo a Terra | D19: Fotovoltaico | E19: =IFERROR(SUMIFS(Fonte_Dati!E:E,Fonte_Dati!D:D,C19,Fonte_Dati!C:C,"Gennaio")/1000,0) -> 112.0692 | F19: =IFERROR(SUMIFS(Fonte_Dati!E:E,Fonte_Dati!D:D,C19,Fonte_Dati!C:C,"Febbraio")/1000,0) -> 208.40784 | G19: =IFERROR(SUMIFS(Fonte_Dati!E:E,Fonte_Dati!D:D,C19,Fonte_Dati!C:C,"Marzo")/1000,0) -> 0 | H19: =SUM(E19:G19) -> 320.47704 | I19: =IFERROR(E19/H19,0) -> 0.34969494 | J19: =IFERROR(F19-E19,0) -> 96.33864 | K19: =IFERROR((F19-E19)/E19,"-") -> 0.8596353 | L19: =IFERROR(SUMIFS(Fonte_Dati!I:I,Fonte_Dati!D:D,C19,Fonte_Dati!C:C,"Gennaio")/(SUMIFS(Fonte_Dati!F:F,Fonte_Dati!D:D,C19,Fonte_Dati!C:C,"Gennaio")/1000),0) -> 109.09545 | M19: =IFERROR(SUMIFS(Fonte_Dati!I:I,Fonte_Dati!D:D,C19,Fonte_Dati!C:C,"Febbraio")/(SUMIFS(Fonte_Dati!F:F,Fonte_Dati!D:D,C19,Fonte_Dati!C:C,"Febbraio")/1000),0) -> 80.96422 | N19: =IFERROR(SUMIFS(Fonte_Dati!I:I,Fonte_Dati!D:D,C19)/(SUMIFS(Fonte_Dati!F:F,Fonte_Dati!D:D,C19)/1000),0) -> 90.80157 | O19: =IFERROR(VLOOKUP(C19,DB_Impianti!C:K,9,0),"") -> 0 | P19: =IFERROR(VLOOKUP(C19,Irraggiamento_PVGIS!C50:H65,3,0),"") -> 0 | Q19: =IFERROR(VLOOKUP(C19,Irraggiamento_PVGIS!C50:H65,4,0),"") -> 0 | R19: =IFERROR(VLOOKUP(C19,Irraggiamento_PVGIS!C50:H65,5,0),"") -> 0 | S19: =IFERROR((E19*1000)/(P19*O19),"") | T19: =IFERROR((F19*1000)/(Q19*O19),"") | U19: =IFERROR((G19*1000)/(R19*O19),"") | V19: =IFERROR((H19*1000)/(VLOOKUP(C19,Irraggiamento_PVGIS!C50:H65,6,0)*O19),"")
B20: 13 | C20: FV-Narbone a Terra Grande | D20: Fotovoltaico | E20: =IFERROR(SUMIFS(Fonte_Dati!E:E,Fonte_Dati!D:D,C20,Fonte_Dati!C:C,"Gennaio")/1000,0) -> 76.19016 | F20: =IFERROR(SUMIFS(Fonte_Dati!E:E,Fonte_Dati!D:D,C20,Fonte_Dati!C:C,"Febbraio")/1000,0) -> 0 | G20: =IFERROR(SUMIFS(Fonte_Dati!E:E,Fonte_Dati!D:D,C20,Fonte_Dati!C:C,"Marzo")/1000,0) -> 0 | H20: =SUM(E20:G20) -> 76.19016 | I20: =IFERROR(E20/H20,0) -> 1 | J20: =IFERROR(F20-E20,0) -> -76.19016 | K20: =IFERROR((F20-E20)/E20,"-") -> -1 | L20: =IFERROR(SUMIFS(Fonte_Dati!I:I,Fonte_Dati!D:D,C20,Fonte_Dati!C:C,"Gennaio")/(SUMIFS(Fonte_Dati!F:F,Fonte_Dati!D:D,C20,Fonte_Dati!C:C,"Gennaio")/1000),0) -> 115.00624 | M20: =IFERROR(SUMIFS(Fonte_Dati!I:I,Fonte_Dati!D:D,C20,Fonte_Dati!C:C,"Febbraio")/(SUMIFS(Fonte_Dati!F:F,Fonte_Dati!D:D,C20,Fonte_Dati!C:C,"Febbraio")/1000),0) -> 0 | N20: =IFERROR(SUMIFS(Fonte_Dati!I:I,Fonte_Dati!D:D,C20)/(SUMIFS(Fonte_Dati!F:F,Fonte_Dati!D:D,C20)/1000),0) -> 115.00624 | O20: =IFERROR(VLOOKUP(C20,DB_Impianti!C:K,9,0),"") -> 0 | P20: =IFERROR(VLOOKUP(C20,Irraggiamento_PVGIS!C50:H65,3,0),"") -> 0 | Q20: =IFERROR(VLOOKUP(C20,Irraggiamento_PVGIS!C50:H65,4,0),"") -> 0 | R20: =IFERROR(VLOOKUP(C20,Irraggiamento_PVGIS!C50:H65,5,0),"") -> 0 | S20: =IFERROR((E20*1000)/(P20*O20),"") | T20: =IFERROR((F20*1000)/(Q20*O20),"") | U20: =IFERROR((G20*1000)/(R20*O20),"") | V20: =IFERROR((H20*1000)/(VLOOKUP(C20,Irraggiamento_PVGIS!C50:H65,6,0)*O20),"")
B21: 14 | C21: FV-Narbone Piccolo | D21: Fotovoltaico | E21: =IFERROR(SUMIFS(Fonte_Dati!E:E,Fonte_Dati!D:D,C21,Fonte_Dati!C:C,"Gennaio")/1000,0) -> 33.2097 | F21: =IFERROR(SUMIFS(Fonte_Dati!E:E,Fonte_Dati!D:D,C21,Fonte_Dati!C:C,"Febbraio")/1000,0) -> 45.30684 | G21: =IFERROR(SUMIFS(Fonte_Dati!E:E,Fonte_Dati!D:D,C21,Fonte_Dati!C:C,"Marzo")/1000,0) -> 0 | H21: =SUM(E21:G21) -> 78.51654 | I21: =IFERROR(E21/H21,0) -> 0.42296438 | J21: =IFERROR(F21-E21,0) -> 12.09714 | K21: =IFERROR((F21-E21)/E21,"-") -> 0.36426526 | L21: =IFERROR(SUMIFS(Fonte_Dati!I:I,Fonte_Dati!D:D,C21,Fonte_Dati!C:C,"Gennaio")/(SUMIFS(Fonte_Dati!F:F,Fonte_Dati!D:D,C21,Fonte_Dati!C:C,"Gennaio")/1000),0) -> 116.80923 | M21: =IFERROR(SUMIFS(Fonte_Dati!I:I,Fonte_Dati!D:D,C21,Fonte_Dati!C:C,"Febbraio")/(SUMIFS(Fonte_Dati!F:F,Fonte_Dati!D:D,C21,Fonte_Dati!C:C,"Febbraio")/1000),0) -> 78.074857 | N21: =IFERROR(SUMIFS(Fonte_Dati!I:I,Fonte_Dati!D:D,C21)/(SUMIFS(Fonte_Dati!F:F,Fonte_Dati!D:D,C21)/1000),0) -> 94.458118 | O21: =IFERROR(VLOOKUP(C21,DB_Impianti!C:K,9,0),"") -> 0 | P21: =IFERROR(VLOOKUP(C21,Irraggiamento_PVGIS!C50:H65,3,0),"") -> 0 | Q21: =IFERROR(VLOOKUP(C21,Irraggiamento_PVGIS!C50:H65,4,0),"") -> 0 | R21: =IFERROR(VLOOKUP(C21,Irraggiamento_PVGIS!C50:H65,5,0),"") -> 0 | S21: =IFERROR((E21*1000)/(P21*O21),"") | T21: =IFERROR((F21*1000)/(Q21*O21),"") | U21: =IFERROR((G21*1000)/(R21*O21),"") | V21: =IFERROR((H21*1000)/(VLOOKUP(C21,Irraggiamento_PVGIS!C50:H65,6,0)*O21),"")
B22: 15 | C22: FV-Campofranco Tetto | D22: Fotovoltaico | E22: =IFERROR(SUMIFS(Fonte_Dati!E:E,Fonte_Dati!D:D,C22,Fonte_Dati!C:C,"Gennaio")/1000,0) -> 24.29524 | F22: =IFERROR(SUMIFS(Fonte_Dati!E:E,Fonte_Dati!D:D,C22,Fonte_Dati!C:C,"Febbraio")/1000,0) -> 46.40668 | G22: =IFERROR(SUMIFS(Fonte_Dati!E:E,Fonte_Dati!D:D,C22,Fonte_Dati!C:C,"Marzo")/1000,0) -> 0 | H22: =SUM(E22:G22) -> 70.70192 | I22: =IFERROR(E22/H22,0) -> 0.34362914 | J22: =IFERROR(F22-E22,0) -> 22.11144 | K22: =IFERROR((F22-E22)/E22,"-") -> 0.91011408 | L22: =IFERROR(SUMIFS(Fonte_Dati!I:I,Fonte_Dati!D:D,C22,Fonte_Dati!C:C,"Gennaio")/(SUMIFS(Fonte_Dati!F:F,Fonte_Dati!D:D,C22,Fonte_Dati!C:C,"Gennaio")/1000),0) -> 121.51592 | M22: =IFERROR(SUMIFS(Fonte_Dati!I:I,Fonte_Dati!D:D,C22,Fonte_Dati!C:C,"Febbraio")/(SUMIFS(Fonte_Dati!F:F,Fonte_Dati!D:D,C22,Fonte_Dati!C:C,"Febbraio")/1000),0) -> 75.876805 | N22: =IFERROR(SUMIFS(Fonte_Dati!I:I,Fonte_Dati!D:D,C22)/(SUMIFS(Fonte_Dati!F:F,Fonte_Dati!D:D,C22)/1000),0) -> 91.559736 | O22: =IFERROR(VLOOKUP(C22,DB_Impianti!C:K,9,0),"") -> 0 | P22: =IFERROR(VLOOKUP(C22,Irraggiamento_PVGIS!C50:H65,3,0),"") -> 0 | Q22: =IFERROR(VLOOKUP(C22,Irraggiamento_PVGIS!C50:H65,4,0),"") -> 0 | R22: =IFERROR(VLOOKUP(C22,Irraggiamento_PVGIS!C50:H65,5,0),"") -> 0 | S22: =IFERROR((E22*1000)/(P22*O22),"") | T22: =IFERROR((F22*1000)/(Q22*O22),"") | U22: =IFERROR((G22*1000)/(R22*O22),"") | V22: =IFERROR((H22*1000)/(VLOOKUP(C22,Irraggiamento_PVGIS!C50:H65,6,0)*O22),"")
B23: 16 | C23: FV-Tumarrano MEG | D23: Fotovoltaico | E23: =IFERROR(SUMIFS(Fonte_Dati!E:E,Fonte_Dati!D:D,C23,Fonte_Dati!C:C,"Gennaio")/1000,0) -> 7.469178 | F23: =IFERROR(SUMIFS(Fonte_Dati!E:E,Fonte_Dati!D:D,C23,Fonte_Dati!C:C,"Febbraio")/1000,0) -> 11.697042 | G23: =IFERROR(SUMIFS(Fonte_Dati!E:E,Fonte_Dati!D:D,C23,Fonte_Dati!C:C,"Marzo")/1000,0) -> 0 | H23: =SUM(E23:G23) -> 19.16622 | I23: =IFERROR(E23/H23,0) -> 0.38970533 | J23: =IFERROR(F23-E23,0) -> 4.227864 | K23: =IFERROR((F23-E23)/E23,"-") -> 0.5660414 | L23: =IFERROR(SUMIFS(Fonte_Dati!I:I,Fonte_Dati!D:D,C23,Fonte_Dati!C:C,"Gennaio")/(SUMIFS(Fonte_Dati!F:F,Fonte_Dati!D:D,C23,Fonte_Dati!C:C,"Gennaio")/1000),0) -> 117.67705 | M23: =IFERROR(SUMIFS(Fonte_Dati!I:I,Fonte_Dati!D:D,C23,Fonte_Dati!C:C,"Febbraio")/(SUMIFS(Fonte_Dati!F:F,Fonte_Dati!D:D,C23,Fonte_Dati!C:C,"Febbraio")/1000),0) -> 77.377091 | N23: =IFERROR(SUMIFS(Fonte_Dati!I:I,Fonte_Dati!D:D,C23)/(SUMIFS(Fonte_Dati!F:F,Fonte_Dati!D:D,C23)/1000),0) -> 93.082199 | O23: =IFERROR(VLOOKUP(C23,DB_Impianti!C:K,9,0),"") -> 0 | P23: =IFERROR(VLOOKUP(C23,Irraggiamento_PVGIS!C50:H65,3,0),"") -> 0 | Q23: =IFERROR(VLOOKUP(C23,Irraggiamento_PVGIS!C50:H65,4,0),"") -> 0 | R23: =IFERROR(VLOOKUP(C23,Irraggiamento_PVGIS!C50:H65,5,0),"") -> 0 | S23: =IFERROR((E23*1000)/(P23*O23),"") | T23: =IFERROR((F23*1000)/(Q23*O23),"") | U23: =IFERROR((G23*1000)/(R23*O23),"") | V23: =IFERROR((H23*1000)/(VLOOKUP(C23,Irraggiamento_PVGIS!C50:H65,6,0)*O23),"")
B24: TOTALE Q1 2026 | E24: =SUM(E8:E23) -> 13791.565 | F24: =SUM(F8:F23) -> 15029.07 | G24: =SUM(G8:G23) -> 1.2714902 | H24: =SUM(H8:H23) -> 28821.906 | M24: =IFERROR(J24/G24,0) -> 0 | O24: =IFERROR(SUM(O8:O23),"") -> 0 | S24: =IFERROR(AVERAGE(S8:S23),"") | T24: =IFERROR(AVERAGE(T8:T23),"") | U24: =IFERROR(AVERAGE(U8:U23),"") | V24: =IFERROR(AVERAGE(V8:V23),"")
O25: ⚠ PR calcolato solo se kWp DC inserito in DB_Impianti col K
B26: BREAKDOWN FV vs EOLICO
B27: Fotovoltaico (13 imp.) | E27: =E11+E12+E13+E14+E15+E16+E17+E18+E19+E20+E21+E22+E23 -> 3190.8925 | F27: =F11+F12+F13+F14+F15+F16+F17+F18+F19+F20+F21+F22+F23 -> 4482.4191 | G27: =G11+G12+G13+G14+G15+G16+G17+G18+G19+G20+G21+G22+G23 -> 0 | H27: =H11+H12+H13+H14+H15+H16+H17+H18+H19+H20+H21+H22+H23 -> 7673.3116
B28: Eolico (3 imp.) | E28: =E8+E9+E10 -> 10600.672 | F28: =F8+F9+F10 -> 10546.651 | G28: =G8+G9+G10 -> 1.2714902 | H28: =H8+H9+H10 -> 21148.595
B29: Totale Portfolio | E29: =E27+E28 -> 13791.565 | F29: =F27+F28 -> 15029.07 | G29: =G27+G28 -> 1.2714902 | H29: =H27+H28 -> 28821.906

Sheet Fatturazione
B1: 💳 FATTURAZIONE DETTAGLIO — PER IMPIANTO E MESE
B4: Dettaglio mensile: Energia, Fee, Prezzo e Totale Fatturato | Q1 2026
B6: ID | C6: Impianto | D6: Tipo | E6: Trader | F6: Ragione Sociale | G6: PVI | H6: Fee (€/MWh) | I6: Mese | J6: MWh Mis. | K6: MWh Magg. | L6: Fat. Lordo (€) | M6: Fee App. (€) | N6: Fat. Netto (€) | O6: EUR/MWh Netto
B7: 1 | C7: Wind - Monte Narbone | D7: Eolico | E7: =IFERROR(VLOOKUP(C7,DB_Impianti!C:E,3,0),"") -> DXT | F7: =IFERROR(VLOOKUP(C7,DB_Impianti!C:F,4,0),"") -> Moncada Energy Group Srl | G7: =IFERROR(VLOOKUP(C7,DB_Impianti!C:G,5,0),"") -> PVI_S19MNEN_001 | H7: =IFERROR(VLOOKUP(C7,DB_Impianti!C:H,6,0),0) -> -1.36 | I7: Gennaio 2026 | J7: =IFERROR(SUMIFS(Fonte_Dati!E:E,Fonte_Dati!D:D,C7,Fonte_Dati!C:C,"Gennaio")/1000,0) -> 4716.6952 | K7: =IFERROR(SUMIFS(Fonte_Dati!F:F,Fonte_Dati!D:D,C7,Fonte_Dati!C:C,"Gennaio")/1000,0) -> 4716.6952 | L7: =IFERROR(SUMIFS(Fonte_Dati!G:G,Fonte_Dati!D:D,C7,Fonte_Dati!C:C,"Gennaio"),0) -> 589371.14 | M7: =IFERROR(SUMIFS(Fonte_Dati!H:H,Fonte_Dati!D:D,C7,Fonte_Dati!C:C,"Gennaio"),0) -> -943.33904 | N7: =IFERROR(SUMIFS(Fonte_Dati!I:I,Fonte_Dati!D:D,C7,Fonte_Dati!C:C,"Gennaio"),0) -> 588427.8 | O7: =IFERROR(N7/K7,0) -> 124.75426
B8: 1 | C8: Wind - Monte Narbone | D8: Eolico | E8: =IFERROR(VLOOKUP(C8,DB_Impianti!C:E,3,0),"") -> DXT | F8: =IFERROR(VLOOKUP(C8,DB_Impianti!C:F,4,0),"") -> Moncada Energy Group Srl | G8: =IFERROR(VLOOKUP(C8,DB_Impianti!C:G,5,0),"") -> PVI_S19MNEN_001 | H8: =IFERROR(VLOOKUP(C8,DB_Impianti!C:H,6,0),0) -> -1.36 | I8: Febbraio 2026 | J8: =IFERROR(SUMIFS(Fonte_Dati!E:E,Fonte_Dati!D:D,C8,Fonte_Dati!C:C,"Febbraio")/1000,0) -> 4379.1799 | K8: =IFERROR(SUMIFS(Fonte_Dati!F:F,Fonte_Dati!D:D,C8,Fonte_Dati!C:C,"Febbraio")/1000,0) -> 4379.1799 | L8: =IFERROR(SUMIFS(Fonte_Dati!G:G,Fonte_Dati!D:D,C8,Fonte_Dati!C:C,"Febbraio"),0) -> 453202.88 | M8: =IFERROR(SUMIFS(Fonte_Dati!H:H,Fonte_Dati!D:D,C8,Fonte_Dati!C:C,"Febbraio"),0) -> -875.83597 | N8: =IFERROR(SUMIFS(Fonte_Dati!I:I,Fonte_Dati!D:D,C8,Fonte_Dati!C:C,"Febbraio"),0) -> 452327.04 | O8: =IFERROR(N8/K8,0) -> 103.29036
B9: 1 | C9: Wind - Monte Narbone | D9: Eolico | E9: =IFERROR(VLOOKUP(C9,DB_Impianti!C:E,3,0),"") -> DXT | F9: =IFERROR(VLOOKUP(C9,DB_Impianti!C:F,4,0),"") -> Moncada Energy Group Srl | G9: =IFERROR(VLOOKUP(C9,DB_Impianti!C:G,5,0),"") -> PVI_S19MNEN_001 | H9: =IFERROR(VLOOKUP(C9,DB_Impianti!C:H,6,0),0) -> -1.36 | I9: Marzo 2026 | J9: =IFERROR(SUMIFS(Fonte_Dati!E:E,Fonte_Dati!D:D,C9,Fonte_Dati!C:C,"Marzo")/1000,0) -> 0.34854082 | K9: =IFERROR(SUMIFS(Fonte_Dati!F:F,Fonte_Dati!D:D,C9,Fonte_Dati!C:C,"Marzo")/1000,0) -> 0.35655726 | L9: =IFERROR(SUMIFS(Fonte_Dati!G:G,Fonte_Dati!D:D,C9,Fonte_Dati!C:C,"Marzo"),0) -> 43.314576 | M9: =IFERROR(SUMIFS(Fonte_Dati!H:H,Fonte_Dati!D:D,C9,Fonte_Dati!C:C,"Marzo"),0) -> -0.071311452 | N9: =IFERROR(SUMIFS(Fonte_Dati!I:I,Fonte_Dati!D:D,C9,Fonte_Dati!C:C,"Marzo"),0) -> 43.243264 | O9: =IFERROR(N9/K9,0) -> 121.28
B10: 2 | C10: Wind - Monte Durrà | D10: Eolico | E10: =IFERROR(VLOOKUP(C10,DB_Impianti!C:E,3,0),"") -> BANCO ENERGIA | F10: =IFERROR(VLOOKUP(C10,DB_Impianti!C:F,4,0),"") -> Moncada Energy Group Srl | G10: =IFERROR(VLOOKUP(C10,DB_Impianti!C:G,5,0),"") -> PVI_S19MDEN_001 | H10: =IFERROR(VLOOKUP(C10,DB_Impianti!C:H,6,0),0) -> -1.86 | I10: Gennaio 2026 | J10: =IFERROR(SUMIFS(Fonte_Dati!E:E,Fonte_Dati!D:D,C10,Fonte_Dati!C:C,"Gennaio")/1000,0) -> 3977.1227 | K10: =IFERROR(SUMIFS(Fonte_Dati!F:F,Fonte_Dati!D:D,C10,Fonte_Dati!C:C,"Gennaio")/1000,0) -> 3977.1227 | L10: =IFERROR(SUMIFS(Fonte_Dati!G:G,Fonte_Dati!D:D,C10,Fonte_Dati!C:C,"Gennaio"),0) -> 481202.52 | M10: =IFERROR(SUMIFS(Fonte_Dati!H:H,Fonte_Dati!D:D,C10,Fonte_Dati!C:C,"Gennaio"),0) -> -795.42454 | N10: =IFERROR(SUMIFS(Fonte_Dati!I:I,Fonte_Dati!D:D,C10,Fonte_Dati!C:C,"Gennaio"),0) -> 480407.1 | O10: =IFERROR(N10/K10,0) -> 120.79263
B11: 2 | C11: Wind - Monte Durrà | D11: Eolico | E11: =IFERROR(VLOOKUP(C11,DB_Impianti!C:E,3,0),"") -> BANCO ENERGIA | F11: =IFERROR(VLOOKUP(C11,DB_Impianti!C:F,4,0),"") -> Moncada Energy Group Srl | G11: =IFERROR(VLOOKUP(C11,DB_Impianti!C:G,5,0),"") -> PVI_S19MDEN_001 | H11: =IFERROR(VLOOKUP(C11,DB_Impianti!C:H,6,0),0) -> -1.86 | I11: Febbraio 2026 | J11: =IFERROR(SUMIFS(Fonte_Dati!E:E,Fonte_Dati!D:D,C11,Fonte_Dati!C:C,"Febbraio")/1000,0) -> 4130.1921 | K11: =IFERROR(SUMIFS(Fonte_Dati!F:F,Fonte_Dati!D:D,C11,Fonte_Dati!C:C,"Febbraio")/1000,0) -> 4130.1921 | L11: =IFERROR(SUMIFS(Fonte_Dati!G:G,Fonte_Dati!D:D,C11,Fonte_Dati!C:C,"Febbraio"),0) -> 427229.74 | M11: =IFERROR(SUMIFS(Fonte_Dati!H:H,Fonte_Dati!D:D,C11,Fonte_Dati!C:C,"Febbraio"),0) -> -826.03842 | N11: =IFERROR(SUMIFS(Fonte_Dati!I:I,Fonte_Dati!D:D,C11,Fonte_Dati!C:C,"Febbraio"),0) -> 426403.7 | O11: =IFERROR(N11/K11,0) -> 103.24065
B12: 2 | C12: Wind - Monte Durrà | D12: Eolico | E12: =IFERROR(VLOOKUP(C12,DB_Impianti!C:E,3,0),"") -> BANCO ENERGIA | F12: =IFERROR(VLOOKUP(C12,DB_Impianti!C:F,4,0),"") -> Moncada Energy Group Srl | G12: =IFERROR(VLOOKUP(C12,DB_Impianti!C:G,5,0),"") -> PVI_S19MDEN_001 | H12: =IFERROR(VLOOKUP(C12,DB_Impianti!C:H,6,0),0) -> -1.86 | I12: Marzo 2026 | J12: =IFERROR(SUMIFS(Fonte_Dati!E:E,Fonte_Dati!D:D,C12,Fonte_Dati!C:C,"Marzo")/1000,0) -> 0 | K12: =IFERROR(SUMIFS(Fonte_Dati!F:F,Fonte_Dati!D:D,C12,Fonte_Dati!C:C,"Marzo")/1000,0) -> 0 | L12: =IFERROR(SUMIFS(Fonte_Dati!G:G,Fonte_Dati!D:D,C12,Fonte_Dati!C:C,"Marzo"),0) -> 0 | M12: =IFERROR(SUMIFS(Fonte_Dati!H:H,Fonte_Dati!D:D,C12,Fonte_Dati!C:C,"Marzo"),0) -> 0 | N12: =IFERROR(SUMIFS(Fonte_Dati!I:I,Fonte_Dati!D:D,C12,Fonte_Dati!C:C,"Marzo"),0) -> 0 | O12: =IFERROR(N12/K12,0) -> 0
B13: 3 | C13: Wind - Monte Malvizzo | D13: Eolico | E13: =IFERROR(VLOOKUP(C13,DB_Impianti!C:E,3,0),"") -> DXT | F13: =IFERROR(VLOOKUP(C13,DB_Impianti!C:F,4,0),"") -> Moncada Energy Group Srl | G13: =IFERROR(VLOOKUP(C13,DB_Impianti!C:G,5,0),"") -> PVI_S19MMEN_001 | H13: =IFERROR(VLOOKUP(C13,DB_Impianti!C:H,6,0),0) -> -1.36 | I13: Gennaio 2026 | J13: =IFERROR(SUMIFS(Fonte_Dati!E:E,Fonte_Dati!D:D,C13,Fonte_Dati!C:C,"Gennaio")/1000,0) -> 1906.8542 | K13: =IFERROR(SUMIFS(Fonte_Dati!F:F,Fonte_Dati!D:D,C13,Fonte_Dati!C:C,"Gennaio")/1000,0) -> 1906.8542 | L13: =IFERROR(SUMIFS(Fonte_Dati!G:G,Fonte_Dati!D:D,C13,Fonte_Dati!C:C,"Gennaio"),0) -> 227341.49 | M13: =IFERROR(SUMIFS(Fonte_Dati!H:H,Fonte_Dati!D:D,C13,Fonte_Dati!C:C,"Gennaio"),0) -> -381.37083 | N13: =IFERROR(SUMIFS(Fonte_Dati!I:I,Fonte_Dati!D:D,C13,Fonte_Dati!C:C,"Gennaio"),0) -> 226960.12 | O13: =IFERROR(N13/K13,0) -> 119.02333
B14: 3 | C14: Wind - Monte Malvizzo | D14: Eolico | E14: =IFERROR(VLOOKUP(C14,DB_Impianti!C:E,3,0),"") -> DXT | F14: =IFERROR(VLOOKUP(C14,DB_Impianti!C:F,4,0),"") -> Moncada Energy Group Srl | G14: =IFERROR(VLOOKUP(C14,DB_Impianti!C:G,5,0),"") -> PVI_S19MMEN_001 | H14: =IFERROR(VLOOKUP(C14,DB_Impianti!C:H,6,0),0) -> -1.36 | I14: Febbraio 2026 | J14: =IFERROR(SUMIFS(Fonte_Dati!E:E,Fonte_Dati!D:D,C14,Fonte_Dati!C:C,"Febbraio")/1000,0) -> 2037.2792 | K14: =IFERROR(SUMIFS(Fonte_Dati!F:F,Fonte_Dati!D:D,C14,Fonte_Dati!C:C,"Febbraio")/1000,0) -> 2037.2792 | L14: =IFERROR(SUMIFS(Fonte_Dati!G:G,Fonte_Dati!D:D,C14,Fonte_Dati!C:C,"Febbraio"),0) -> 217599.32 | M14: =IFERROR(SUMIFS(Fonte_Dati!H:H,Fonte_Dati!D:D,C14,Fonte_Dati!C:C,"Febbraio"),0) -> -407.45583 | N14: =IFERROR(SUMIFS(Fonte_Dati!I:I,Fonte_Dati!D:D,C14,Fonte_Dati!C:C,"Febbraio"),0) -> 217191.86 | O14: =IFERROR(N14/K14,0) -> 106.60879
B15: 3 | C15: Wind - Monte Malvizzo | D15: Eolico | E15: =IFERROR(VLOOKUP(C15,DB_Impianti!C:E,3,0),"") -> DXT | F15: =IFERROR(VLOOKUP(C15,DB_Impianti!C:F,4,0),"") -> Moncada Energy Group Srl | G15: =IFERROR(VLOOKUP(C15,DB_Impianti!C:G,5,0),"") -> PVI_S19MMEN_001 | H15: =IFERROR(VLOOKUP(C15,DB_Impianti!C:H,6,0),0) -> -1.36 | I15: Marzo 2026 | J15: =IFERROR(SUMIFS(Fonte_Dati!E:E,Fonte_Dati!D:D,C15,Fonte_Dati!C:C,"Marzo")/1000,0) -> 0.9229494 | K15: =IFERROR(SUMIFS(Fonte_Dati!F:F,Fonte_Dati!D:D,C15,Fonte_Dati!C:C,"Marzo")/1000,0) -> 0.94417723 | L15: =IFERROR(SUMIFS(Fonte_Dati!G:G,Fonte_Dati!D:D,C15,Fonte_Dati!C:C,"Marzo"),0) -> 114.69865 | M15: =IFERROR(SUMIFS(Fonte_Dati!H:H,Fonte_Dati!D:D,C15,Fonte_Dati!C:C,"Marzo"),0) -> -0.18883545 | N15: =IFERROR(SUMIFS(Fonte_Dati!I:I,Fonte_Dati!D:D,C15,Fonte_Dati!C:C,"Marzo"),0) -> 114.50981 | O15: =IFERROR(N15/K15,0) -> 121.28
B16: 4 | C16: FV-Favara Grande | D16: Fotovoltaico | E16: =IFERROR(VLOOKUP(C16,DB_Impianti!C:E,3,0),"") -> AXPO | F16: =IFERROR(VLOOKUP(C16,DB_Impianti!C:F,4,0),"") -> Biopower 2 Srl | G16: =IFERROR(VLOOKUP(C16,DB_Impianti!C:G,5,0),"") -> 0 | H16: =IFERROR(VLOOKUP(C16,DB_Impianti!C:H,6,0),0) -> -0.2 | I16: Gennaio 2026 | J16: =IFERROR(SUMIFS(Fonte_Dati!E:E,Fonte_Dati!D:D,C16,Fonte_Dati!C:C,"Gennaio")/1000,0) -> 629.42576 | K16: =IFERROR(SUMIFS(Fonte_Dati!F:F,Fonte_Dati!D:D,C16,Fonte_Dati!C:C,"Gennaio")/1000,0) -> 643.90255 | L16: =IFERROR(SUMIFS(Fonte_Dati!G:G,Fonte_Dati!D:D,C16,Fonte_Dati!C:C,"Gennaio"),0) -> 76759.684 | M16: =IFERROR(SUMIFS(Fonte_Dati!H:H,Fonte_Dati!D:D,C16,Fonte_Dati!C:C,"Gennaio"),0) -> -128.78051 | N16: =IFERROR(SUMIFS(Fonte_Dati!I:I,Fonte_Dati!D:D,C16,Fonte_Dati!C:C,"Gennaio"),0) -> 76630.904 | O16: =IFERROR(N16/K16,0) -> 119.01009
B17: 4 | C17: FV-Favara Grande | D17: Fotovoltaico | E17: =IFERROR(VLOOKUP(C17,DB_Impianti!C:E,3,0),"") -> AXPO | F17: =IFERROR(VLOOKUP(C17,DB_Impianti!C:F,4,0),"") -> Biopower 2 Srl | G17: =IFERROR(VLOOKUP(C17,DB_Impianti!C:G,5,0),"") -> 0 | H17: =IFERROR(VLOOKUP(C17,DB_Impianti!C:H,6,0),0) -> -0.2 | I17: Febbraio 2026 | J17: =IFERROR(SUMIFS(Fonte_Dati!E:E,Fonte_Dati!D:D,C17,Fonte_Dati!C:C,"Febbraio")/1000,0) -> 914.78672 | K17: =IFERROR(SUMIFS(Fonte_Dati!F:F,Fonte_Dati!D:D,C17,Fonte_Dati!C:C,"Febbraio")/1000,0) -> 935.82681 | L17: =IFERROR(SUMIFS(Fonte_Dati!G:G,Fonte_Dati!D:D,C17,Fonte_Dati!C:C,"Febbraio"),0) -> 73646.99 | M17: =IFERROR(SUMIFS(Fonte_Dati!H:H,Fonte_Dati!D:D,C17,Fonte_Dati!C:C,"Febbraio"),0) -> -187.16536 | N17: =IFERROR(SUMIFS(Fonte_Dati!I:I,Fonte_Dati!D:D,C17,Fonte_Dati!C:C,"Febbraio"),0) -> 73459.825 | O17: =IFERROR(N17/K17,0) -> 78.497243
B18: 4 | C18: FV-Favara Grande | D18: Fotovoltaico | E18: =IFERROR(VLOOKUP(C18,DB_Impianti!C:E,3,0),"") -> AXPO | F18: =IFERROR(VLOOKUP(C18,DB_Impianti!C:F,4,0),"") -> Biopower 2 Srl | G18: =IFERROR(VLOOKUP(C18,DB_Impianti!C:G,5,0),"") -> 0 | H18: =IFERROR(VLOOKUP(C18,DB_Impianti!C:H,6,0),0) -> -0.2 | I18: Marzo 2026 | J18: =IFERROR(SUMIFS(Fonte_Dati!E:E,Fonte_Dati!D:D,C18,Fonte_Dati!C:C,"Marzo")/1000,0) -> 0 | K18: =IFERROR(SUMIFS(Fonte_Dati!F:F,Fonte_Dati!D:D,C18,Fonte_Dati!C:C,"Marzo")/1000,0) -> 0 | L18: =IFERROR(SUMIFS(Fonte_Dati!G:G,Fonte_Dati!D:D,C18,Fonte_Dati!C:C,"Marzo"),0) -> 0 | M18: =IFERROR(SUMIFS(Fonte_Dati!H:H,Fonte_Dati!D:D,C18,Fonte_Dati!C:C,"Marzo"),0) -> 0 | N18: =IFERROR(SUMIFS(Fonte_Dati!I:I,Fonte_Dati!D:D,C18,Fonte_Dati!C:C,"Marzo"),0) -> 0 | O18: =IFERROR(N18/K18,0) -> 0
B19: 5 | C19: FV-Fauma Tetto | D19: Fotovoltaico | E19: =IFERROR(VLOOKUP(C19,DB_Impianti!C:E,3,0),"") -> AXPO | F19: =IFERROR(VLOOKUP(C19,DB_Impianti!C:F,4,0),"") -> Biopower 3 Srl | G19: =IFERROR(VLOOKUP(C19,DB_Impianti!C:G,5,0),"") -> 0 | H19: =IFERROR(VLOOKUP(C19,DB_Impianti!C:H,6,0),0) -> -0.2 | I19: Gennaio 2026 | J19: =IFERROR(SUMIFS(Fonte_Dati!E:E,Fonte_Dati!D:D,C19,Fonte_Dati!C:C,"Gennaio")/1000,0) -> 652.4864 | K19: =IFERROR(SUMIFS(Fonte_Dati!F:F,Fonte_Dati!D:D,C19,Fonte_Dati!C:C,"Gennaio")/1000,0) -> 667.49359 | L19: =IFERROR(SUMIFS(Fonte_Dati!G:G,Fonte_Dati!D:D,C19,Fonte_Dati!C:C,"Gennaio"),0) -> 79168.413 | M19: =IFERROR(SUMIFS(Fonte_Dati!H:H,Fonte_Dati!D:D,C19,Fonte_Dati!C:C,"Gennaio"),0) -> -133.49872 | N19: =IFERROR(SUMIFS(Fonte_Dati!I:I,Fonte_Dati!D:D,C19,Fonte_Dati!C:C,"Gennaio"),0) -> 79034.914 | O19: =IFERROR(N19/K19,0) -> 118.4055
B20: 5 | C20: FV-Fauma Tetto | D20: Fotovoltaico | E20: =IFERROR(VLOOKUP(C20,DB_Impianti!C:E,3,0),"") -> AXPO | F20: =IFERROR(VLOOKUP(C20,DB_Impianti!C:F,4,0),"") -> Biopower 3 Srl | G20: =IFERROR(VLOOKUP(C20,DB_Impianti!C:G,5,0),"") -> 0 | H20: =IFERROR(VLOOKUP(C20,DB_Impianti!C:H,6,0),0) -> -0.2 | I20: Febbraio 2026 | J20: =IFERROR(SUMIFS(Fonte_Dati!E:E,Fonte_Dati!D:D,C20,Fonte_Dati!C:C,"Febbraio")/1000,0) -> 851.4772 | K20: =IFERROR(SUMIFS(Fonte_Dati!F:F,Fonte_Dati!D:D,C20,Fonte_Dati!C:C,"Febbraio")/1000,0) -> 871.06118 | L20: =IFERROR(SUMIFS(Fonte_Dati!G:G,Fonte_Dati!D:D,C20,Fonte_Dati!C:C,"Febbraio"),0) -> 69188.297 | M20: =IFERROR(SUMIFS(Fonte_Dati!H:H,Fonte_Dati!D:D,C20,Fonte_Dati!C:C,"Febbraio"),0) -> -174.21224 | N20: =IFERROR(SUMIFS(Fonte_Dati!I:I,Fonte_Dati!D:D,C20,Fonte_Dati!C:C,"Febbraio"),0) -> 69014.085 | O20: =IFERROR(N20/K20,0) -> 79.229894
B21: 5 | C21: FV-Fauma Tetto | D21: Fotovoltaico | E21: =IFERROR(VLOOKUP(C21,DB_Impianti!C:E,3,0),"") -> AXPO | F21: =IFERROR(VLOOKUP(C21,DB_Impianti!C:F,4,0),"") -> Biopower 3 Srl | G21: =IFERROR(VLOOKUP(C21,DB_Impianti!C:G,5,0),"") -> 0 | H21: =IFERROR(VLOOKUP(C21,DB_Impianti!C:H,6,0),0) -> -0.2 | I21: Marzo 2026 | J21: =IFERROR(SUMIFS(Fonte_Dati!E:E,Fonte_Dati!D:D,C21,Fonte_Dati!C:C,"Marzo")/1000,0) -> 0 | K21: =IFERROR(SUMIFS(Fonte_Dati!F:F,Fonte_Dati!D:D,C21,Fonte_Dati!C:C,"Marzo")/1000,0) -> 0 | L21: =IFERROR(SUMIFS(Fonte_Dati!G:G,Fonte_Dati!D:D,C21,Fonte_Dati!C:C,"Marzo"),0) -> 0 | M21: =IFERROR(SUMIFS(Fonte_Dati!H:H,Fonte_Dati!D:D,C21,Fonte_Dati!C:C,"Marzo"),0) -> 0 | N21: =IFERROR(SUMIFS(Fonte_Dati!I:I,Fonte_Dati!D:D,C21,Fonte_Dati!C:C,"Marzo"),0) -> 0 | O21: =IFERROR(N21/K21,0) -> 0
B22: 6 | C22: FV-Batia S. Francesco | D22: Fotovoltaico | E22: =IFERROR(VLOOKUP(C22,DB_Impianti!C:E,3,0),"") -> DXT | F22: =IFERROR(VLOOKUP(C22,DB_Impianti!C:F,4,0),"") -> Energie Innovative Srl | G22: =IFERROR(VLOOKUP(C22,DB_Impianti!C:G,5,0),"") -> PVI_0435789_001 | H22: =IFERROR(VLOOKUP(C22,DB_Impianti!C:H,6,0),0) -> -0.2 | I22: Gennaio 2026 | J22: =IFERROR(SUMIFS(Fonte_Dati!E:E,Fonte_Dati!D:D,C22,Fonte_Dati!C:C,"Gennaio")/1000,0) -> 425.76024 | K22: =IFERROR(SUMIFS(Fonte_Dati!F:F,Fonte_Dati!D:D,C22,Fonte_Dati!C:C,"Gennaio")/1000,0) -> 424.0572 | L22: =IFERROR(SUMIFS(Fonte_Dati!G:G,Fonte_Dati!D:D,C22,Fonte_Dati!C:C,"Gennaio"),0) -> 47434.025 | M22: =IFERROR(SUMIFS(Fonte_Dati!H:H,Fonte_Dati!D:D,C22,Fonte_Dati!C:C,"Gennaio"),0) -> -84.81144 | N22: =IFERROR(SUMIFS(Fonte_Dati!I:I,Fonte_Dati!D:D,C22,Fonte_Dati!C:C,"Gennaio"),0) -> 47349.213 | O22: =IFERROR(N22/K22,0) -> 111.65761
B23: 6 | C23: FV-Batia S. Francesco | D23: Fotovoltaico | E23: =IFERROR(VLOOKUP(C23,DB_Impianti!C:E,3,0),"") -> DXT | F23: =IFERROR(VLOOKUP(C23,DB_Impianti!C:F,4,0),"") -> Energie Innovative Srl | G23: =IFERROR(VLOOKUP(C23,DB_Impianti!C:G,5,0),"") -> PVI_0435789_001 | H23: =IFERROR(VLOOKUP(C23,DB_Impianti!C:H,6,0),0) -> -0.2 | I23: Febbraio 2026 | J23: =IFERROR(SUMIFS(Fonte_Dati!E:E,Fonte_Dati!D:D,C23,Fonte_Dati!C:C,"Febbraio")/1000,0) -> 721.12824 | K23: =IFERROR(SUMIFS(Fonte_Dati!F:F,Fonte_Dati!D:D,C23,Fonte_Dati!C:C,"Febbraio")/1000,0) -> 718.24373 | L23: =IFERROR(SUMIFS(Fonte_Dati!G:G,Fonte_Dati!D:D,C23,Fonte_Dati!C:C,"Febbraio"),0) -> 56076.574 | M23: =IFERROR(SUMIFS(Fonte_Dati!H:H,Fonte_Dati!D:D,C23,Fonte_Dati!C:C,"Febbraio"),0) -> -143.64875 | N23: =IFERROR(SUMIFS(Fonte_Dati!I:I,Fonte_Dati!D:D,C23,Fonte_Dati!C:C,"Febbraio"),0) -> 55932.925 | O23: =IFERROR(N23/K23,0) -> 77.874575
B24: 6 | C24: FV-Batia S. Francesco | D24: Fotovoltaico | E24: =IFERROR(VLOOKUP(C24,DB_Impianti!C:E,3,0),"") -> DXT | F24: =IFERROR(VLOOKUP(C24,DB_Impianti!C:F,4,0),"") -> Energie Innovative Srl | G24: =IFERROR(VLOOKUP(C24,DB_Impianti!C:G,5,0),"") -> PVI_0435789_001 | H24: =IFERROR(VLOOKUP(C24,DB_Impianti!C:H,6,0),0) -> -0.2 | I24: Marzo 2026 | J24: =IFERROR(SUMIFS(Fonte_Dati!E:E,Fonte_Dati!D:D,C24,Fonte_Dati!C:C,"Marzo")/1000,0) -> 0 | K24: =IFERROR(SUMIFS(Fonte_Dati!F:F,Fonte_Dati!D:D,C24,Fonte_Dati!C:C,"Marzo")/1000,0) -> 0 | L24: =IFERROR(SUMIFS(Fonte_Dati!G:G,Fonte_Dati!D:D,C24,Fonte_Dati!C:C,"Marzo"),0) -> 0 | M24: =IFERROR(SUMIFS(Fonte_Dati!H:H,Fonte_Dati!D:D,C24,Fonte_Dati!C:C,"Marzo"),0) -> 0 | N24: =IFERROR(SUMIFS(Fonte_Dati!I:I,Fonte_Dati!D:D,C24,Fonte_Dati!C:C,"Marzo"),0) -> 0 | O24: =IFERROR(N24/K24,0) -> 0
B25: 7 | C25: FV-Serre S.Angelo Muxaro | D25: Fotovoltaico | E25: =IFERROR(VLOOKUP(C25,DB_Impianti!C:E,3,0),"") -> DXT | F25: =IFERROR(VLOOKUP(C25,DB_Impianti!C:F,4,0),"") -> Società Agricola Solar Farm 3 Srl | G25: =IFERROR(VLOOKUP(C25,DB_Impianti!C:G,5,0),"") -> PVI_0363736_001 | H25: =IFERROR(VLOOKUP(C25,DB_Impianti!C:H,6,0),0) -> -0.2 | I25: Gennaio 2026 | J25: =IFERROR(SUMIFS(Fonte_Dati!E:E,Fonte_Dati!D:D,C25,Fonte_Dati!C:C,"Gennaio")/1000,0) -> 356.1996 | K25: =IFERROR(SUMIFS(Fonte_Dati!F:F,Fonte_Dati!D:D,C25,Fonte_Dati!C:C,"Gennaio")/1000,0) -> 364.39219 | L25: =IFERROR(SUMIFS(Fonte_Dati!G:G,Fonte_Dati!D:D,C25,Fonte_Dati!C:C,"Gennaio"),0) -> 43280.191 | M25: =IFERROR(SUMIFS(Fonte_Dati!H:H,Fonte_Dati!D:D,C25,Fonte_Dati!C:C,"Gennaio"),0) -> -72.878438 | N25: =IFERROR(SUMIFS(Fonte_Dati!I:I,Fonte_Dati!D:D,C25,Fonte_Dati!C:C,"Gennaio"),0) -> 43207.313 | O25: =IFERROR(N25/K25,0) -> 118.57365
B26: 7 | C26: FV-Serre S.Angelo Muxaro | D26: Fotovoltaico | E26: =IFERROR(VLOOKUP(C26,DB_Impianti!C:E,3,0),"") -> DXT | F26: =IFERROR(VLOOKUP(C26,DB_Impianti!C:F,4,0),"") -> Società Agricola Solar Farm 3 Srl | G26: =IFERROR(VLOOKUP(C26,DB_Impianti!C:G,5,0),"") -> PVI_0363736_001 | H26: =IFERROR(VLOOKUP(C26,DB_Impianti!C:H,6,0),0) -> -0.2 | I26: Febbraio 2026 | J26: =IFERROR(SUMIFS(Fonte_Dati!E:E,Fonte_Dati!D:D,C26,Fonte_Dati!C:C,"Febbraio")/1000,0) -> 430.9296 | K26: =IFERROR(SUMIFS(Fonte_Dati!F:F,Fonte_Dati!D:D,C26,Fonte_Dati!C:C,"Febbraio")/1000,0) -> 440.84098 | L26: =IFERROR(SUMIFS(Fonte_Dati!G:G,Fonte_Dati!D:D,C26,Fonte_Dati!C:C,"Febbraio"),0) -> 34400.54 | M26: =IFERROR(SUMIFS(Fonte_Dati!H:H,Fonte_Dati!D:D,C26,Fonte_Dati!C:C,"Febbraio"),0) -> -88.168196 | N26: =IFERROR(SUMIFS(Fonte_Dati!I:I,Fonte_Dati!D:D,C26,Fonte_Dati!C:C,"Febbraio"),0) -> 34312.372 | O26: =IFERROR(N26/K26,0) -> 77.833898
B27: 7 | C27: FV-Serre S.Angelo Muxaro | D27: Fotovoltaico | E27: =IFERROR(VLOOKUP(C27,DB_Impianti!C:E,3,0),"") -> DXT | F27: =IFERROR(VLOOKUP(C27,DB_Impianti!C:F,4,0),"") -> Società Agricola Solar Farm 3 Srl | G27: =IFERROR(VLOOKUP(C27,DB_Impianti!C:G,5,0),"") -> PVI_0363736_001 | H27: =IFERROR(VLOOKUP(C27,DB_Impianti!C:H,6,0),0) -> -0.2 | I27: Marzo 2026 | J27: =IFERROR(SUMIFS(Fonte_Dati!E:E,Fonte_Dati!D:D,C27,Fonte_Dati!C:C,"Marzo")/1000,0) -> 0 | K27: =IFERROR(SUMIFS(Fonte_Dati!F:F,Fonte_Dati!D:D,C27,Fonte_Dati!C:C,"Marzo")/1000,0) -> 0 | L27: =IFERROR(SUMIFS(Fonte_Dati!G:G,Fonte_Dati!D:D,C27,Fonte_Dati!C:C,"Marzo"),0) -> 0 | M27: =IFERROR(SUMIFS(Fonte_Dati!H:H,Fonte_Dati!D:D,C27,Fonte_Dati!C:C,"Marzo"),0) -> 0 | N27: =IFERROR(SUMIFS(Fonte_Dati!I:I,Fonte_Dati!D:D,C27,Fonte_Dati!C:C,"Marzo"),0) -> 0 | O27: =IFERROR(N27/K27,0) -> 0
B28: 8 | C28: FV-Serre Narbone | D28: Fotovoltaico | E28: =IFERROR(VLOOKUP(C28,DB_Impianti!C:E,3,0),"") -> DXT | F28: =IFERROR(VLOOKUP(C28,DB_Impianti!C:F,4,0),"") -> Società Agricola Solar Farm Srl | G28: =IFERROR(VLOOKUP(C28,DB_Impianti!C:G,5,0),"") -> PVI_S19SNRR_001 | H28: =IFERROR(VLOOKUP(C28,DB_Impianti!C:H,6,0),0) -> -0.2 | I28: Gennaio 2026 | J28: =IFERROR(SUMIFS(Fonte_Dati!E:E,Fonte_Dati!D:D,C28,Fonte_Dati!C:C,"Gennaio")/1000,0) -> 353.3616 | K28: =IFERROR(SUMIFS(Fonte_Dati!F:F,Fonte_Dati!D:D,C28,Fonte_Dati!C:C,"Gennaio")/1000,0) -> 351.94815 | L28: =IFERROR(SUMIFS(Fonte_Dati!G:G,Fonte_Dati!D:D,C28,Fonte_Dati!C:C,"Gennaio"),0) -> 41581.31 | M28: =IFERROR(SUMIFS(Fonte_Dati!H:H,Fonte_Dati!D:D,C28,Fonte_Dati!C:C,"Gennaio"),0) -> -70.389631 | N28: =IFERROR(SUMIFS(Fonte_Dati!I:I,Fonte_Dati!D:D,C28,Fonte_Dati!C:C,"Gennaio"),0) -> 41510.92 | O28: =IFERROR(N28/K28,0) -> 117.94612
B29: 8 | C29: FV-Serre Narbone | D29: Fotovoltaico | E29: =IFERROR(VLOOKUP(C29,DB_Impianti!C:E,3,0),"") -> DXT | F29: =IFERROR(VLOOKUP(C29,DB_Impianti!C:F,4,0),"") -> Società Agricola Solar Farm Srl | G29: =IFERROR(VLOOKUP(C29,DB_Impianti!C:G,5,0),"") -> PVI_S19SNRR_001 | H29: =IFERROR(VLOOKUP(C29,DB_Impianti!C:H,6,0),0) -> -0.2 | I29: Febbraio 2026 | J29: =IFERROR(SUMIFS(Fonte_Dati!E:E,Fonte_Dati!D:D,C29,Fonte_Dati!C:C,"Febbraio")/1000,0) -> 448.146 | K29: =IFERROR(SUMIFS(Fonte_Dati!F:F,Fonte_Dati!D:D,C29,Fonte_Dati!C:C,"Febbraio")/1000,0) -> 446.35342 | L29: =IFERROR(SUMIFS(Fonte_Dati!G:G,Fonte_Dati!D:D,C29,Fonte_Dati!C:C,"Febbraio"),0) -> 34543.126 | M29: =IFERROR(SUMIFS(Fonte_Dati!H:H,Fonte_Dati!D:D,C29,Fonte_Dati!C:C,"Febbraio"),0) -> -89.270683 | N29: =IFERROR(SUMIFS(Fonte_Dati!I:I,Fonte_Dati!D:D,C29,Fonte_Dati!C:C,"Febbraio"),0) -> 34453.855 | O29: =IFERROR(N29/K29,0) -> 77.189631
B30: 8 | C30: FV-Serre Narbone | D30: Fotovoltaico | E30: =IFERROR(VLOOKUP(C30,DB_Impianti!C:E,3,0),"") -> DXT | F30: =IFERROR(VLOOKUP(C30,DB_Impianti!C:F,4,0),"") -> Società Agricola Solar Farm Srl | G30: =IFERROR(VLOOKUP(C30,DB_Impianti!C:G,5,0),"") -> PVI_S19SNRR_001 | H30: =IFERROR(VLOOKUP(C30,DB_Impianti!C:H,6,0),0) -> -0.2 | I30: Marzo 2026 | J30: =IFERROR(SUMIFS(Fonte_Dati!E:E,Fonte_Dati!D:D,C30,Fonte_Dati!C:C,"Marzo")/1000,0) -> 0 | K30: =IFERROR(SUMIFS(Fonte_Dati!F:F,Fonte_Dati!D:D,C30,Fonte_Dati!C:C,"Marzo")/1000,0) -> 0 | L30: =IFERROR(SUMIFS(Fonte_Dati!G:G,Fonte_Dati!D:D,C30,Fonte_Dati!C:C,"Marzo"),0) -> 0 | M30: =IFERROR(SUMIFS(Fonte_Dati!H:H,Fonte_Dati!D:D,C30,Fonte_Dati!C:C,"Marzo"),0) -> 0 | N30: =IFERROR(SUMIFS(Fonte_Dati!I:I,Fonte_Dati!D:D,C30,Fonte_Dati!C:C,"Marzo"),0) -> 0 | O30: =IFERROR(N30/K30,0) -> 0
B31: 9 | C31: FV-Perniciara | D31: Fotovoltaico | E31: =IFERROR(VLOOKUP(C31,DB_Impianti!C:E,3,0),"") -> AXPO | F31: =IFERROR(VLOOKUP(C31,DB_Impianti!C:F,4,0),"") -> Biopower 2 Srl | G31: =IFERROR(VLOOKUP(C31,DB_Impianti!C:G,5,0),"") -> 0 | H31: =IFERROR(VLOOKUP(C31,DB_Impianti!C:H,6,0),0) -> -0.2 | I31: Gennaio 2026 | J31: =IFERROR(SUMIFS(Fonte_Dati!E:E,Fonte_Dati!D:D,C31,Fonte_Dati!C:C,"Gennaio")/1000,0) -> 209.75475 | K31: =IFERROR(SUMIFS(Fonte_Dati!F:F,Fonte_Dati!D:D,C31,Fonte_Dati!C:C,"Gennaio")/1000,0) -> 214.57911 | L31: =IFERROR(SUMIFS(Fonte_Dati!G:G,Fonte_Dati!D:D,C31,Fonte_Dati!C:C,"Gennaio"),0) -> 25631.128 | M31: =IFERROR(SUMIFS(Fonte_Dati!H:H,Fonte_Dati!D:D,C31,Fonte_Dati!C:C,"Gennaio"),0) -> -42.915822 | N31: =IFERROR(SUMIFS(Fonte_Dati!I:I,Fonte_Dati!D:D,C31,Fonte_Dati!C:C,"Gennaio"),0) -> 25588.212 | O31: =IFERROR(N31/K31,0) -> 119.24838
B32: 9 | C32: FV-Perniciara | D32: Fotovoltaico | E32: =IFERROR(VLOOKUP(C32,DB_Impianti!C:E,3,0),"") -> AXPO | F32: =IFERROR(VLOOKUP(C32,DB_Impianti!C:F,4,0),"") -> Biopower 2 Srl | G32: =IFERROR(VLOOKUP(C32,DB_Impianti!C:G,5,0),"") -> 0 | H32: =IFERROR(VLOOKUP(C32,DB_Impianti!C:H,6,0),0) -> -0.2 | I32: Febbraio 2026 | J32: =IFERROR(SUMIFS(Fonte_Dati!E:E,Fonte_Dati!D:D,C32,Fonte_Dati!C:C,"Febbraio")/1000,0) -> 311.66175 | K32: =IFERROR(SUMIFS(Fonte_Dati!F:F,Fonte_Dati!D:D,C32,Fonte_Dati!C:C,"Febbraio")/1000,0) -> 318.82997 | L32: =IFERROR(SUMIFS(Fonte_Dati!G:G,Fonte_Dati!D:D,C32,Fonte_Dati!C:C,"Febbraio"),0) -> 25227.659 | M32: =IFERROR(SUMIFS(Fonte_Dati!H:H,Fonte_Dati!D:D,C32,Fonte_Dati!C:C,"Febbraio"),0) -> -63.765994 | N32: =IFERROR(SUMIFS(Fonte_Dati!I:I,Fonte_Dati!D:D,C32,Fonte_Dati!C:C,"Febbraio"),0) -> 25163.893 | O32: =IFERROR(N32/K32,0) -> 78.925747
B33: 9 | C33: FV-Perniciara | D33: Fotovoltaico | E33: =IFERROR(VLOOKUP(C33,DB_Impianti!C:E,3,0),"") -> AXPO | F33: =IFERROR(VLOOKUP(C33,DB_Impianti!C:F,4,0),"") -> Biopower 2 Srl | G33: =IFERROR(VLOOKUP(C33,DB_Impianti!C:G,5,0),"") -> 0 | H33: =IFERROR(VLOOKUP(C33,DB_Impianti!C:H,6,0),0) -> -0.2 | I33: Marzo 2026 | J33: =IFERROR(SUMIFS(Fonte_Dati!E:E,Fonte_Dati!D:D,C33,Fonte_Dati!C:C,"Marzo")/1000,0) -> 0 | K33: =IFERROR(SUMIFS(Fonte_Dati!F:F,Fonte_Dati!D:D,C33,Fonte_Dati!C:C,"Marzo")/1000,0) -> 0 | L33: =IFERROR(SUMIFS(Fonte_Dati!G:G,Fonte_Dati!D:D,C33,Fonte_Dati!C:C,"Marzo"),0) -> 0 | M33: =IFERROR(SUMIFS(Fonte_Dati!H:H,Fonte_Dati!D:D,C33,Fonte_Dati!C:C,"Marzo"),0) -> 0 | N33: =IFERROR(SUMIFS(Fonte_Dati!I:I,Fonte_Dati!D:D,C33,Fonte_Dati!C:C,"Marzo"),0) -> 0 | O33: =IFERROR(N33/K33,0) -> 0
B34: 10 | C34: FV-Serre Gela | D34: Fotovoltaico | E34: =IFERROR(VLOOKUP(C34,DB_Impianti!C:E,3,0),"") -> DXT | F34: =IFERROR(VLOOKUP(C34,DB_Impianti!C:F,4,0),"") -> Società Agricola Solar Farm 5 Srl | G34: =IFERROR(VLOOKUP(C34,DB_Impianti!C:G,5,0),"") -> PVI_0384558_001 | H34: =IFERROR(VLOOKUP(C34,DB_Impianti!C:H,6,0),0) -> -0.2 | I34: Gennaio 2026 | J34: =IFERROR(SUMIFS(Fonte_Dati!E:E,Fonte_Dati!D:D,C34,Fonte_Dati!C:C,"Gennaio")/1000,0) -> 199.29456 | K34: =IFERROR(SUMIFS(Fonte_Dati!F:F,Fonte_Dati!D:D,C34,Fonte_Dati!C:C,"Gennaio")/1000,0) -> 203.87833 | L34: =IFERROR(SUMIFS(Fonte_Dati!G:G,Fonte_Dati!D:D,C34,Fonte_Dati!C:C,"Gennaio"),0) -> 24021.424 | M34: =IFERROR(SUMIFS(Fonte_Dati!H:H,Fonte_Dati!D:D,C34,Fonte_Dati!C:C,"Gennaio"),0) -> -40.775667 | N34: =IFERROR(SUMIFS(Fonte_Dati!I:I,Fonte_Dati!D:D,C34,Fonte_Dati!C:C,"Gennaio"),0) -> 23980.648 | O34: =IFERROR(N34/K34,0) -> 117.62235
B35: 10 | C35: FV-Serre Gela | D35: Fotovoltaico | E35: =IFERROR(VLOOKUP(C35,DB_Impianti!C:E,3,0),"") -> DXT | F35: =IFERROR(VLOOKUP(C35,DB_Impianti!C:F,4,0),"") -> Società Agricola Solar Farm 5 Srl | G35: =IFERROR(VLOOKUP(C35,DB_Impianti!C:G,5,0),"") -> PVI_0384558_001 | H35: =IFERROR(VLOOKUP(C35,DB_Impianti!C:H,6,0),0) -> -0.2 | I35: Febbraio 2026 | J35: =IFERROR(SUMIFS(Fonte_Dati!E:E,Fonte_Dati!D:D,C35,Fonte_Dati!C:C,"Febbraio")/1000,0) -> 277.67152 | K35: =IFERROR(SUMIFS(Fonte_Dati!F:F,Fonte_Dati!D:D,C35,Fonte_Dati!C:C,"Febbraio")/1000,0) -> 284.05796 | L35: =IFERROR(SUMIFS(Fonte_Dati!G:G,Fonte_Dati!D:D,C35,Fonte_Dati!C:C,"Febbraio"),0) -> 22556.369 | M35: =IFERROR(SUMIFS(Fonte_Dati!H:H,Fonte_Dati!D:D,C35,Fonte_Dati!C:C,"Febbraio"),0) -> -56.811593 | N35: =IFERROR(SUMIFS(Fonte_Dati!I:I,Fonte_Dati!D:D,C35,Fonte_Dati!C:C,"Febbraio"),0) -> 22499.557 | O35: =IFERROR(N35/K35,0) -> 79.207626
B36: 10 | C36: FV-Serre Gela | D36: Fotovoltaico | E36: =IFERROR(VLOOKUP(C36,DB_Impianti!C:E,3,0),"") -> DXT | F36: =IFERROR(VLOOKUP(C36,DB_Impianti!C:F,4,0),"") -> Società Agricola Solar Farm 5 Srl | G36: =IFERROR(VLOOKUP(C36,DB_Impianti!C:G,5,0),"") -> PVI_0384558_001 | H36: =IFERROR(VLOOKUP(C36,DB_Impianti!C:H,6,0),0) -> -0.2 | I36: Marzo 2026 | J36: =IFERROR(SUMIFS(Fonte_Dati!E:E,Fonte_Dati!D:D,C36,Fonte_Dati!C:C,"Marzo")/1000,0) -> 0 | K36: =IFERROR(SUMIFS(Fonte_Dati!F:F,Fonte_Dati!D:D,C36,Fonte_Dati!C:C,"Marzo")/1000,0) -> 0 | L36: =IFERROR(SUMIFS(Fonte_Dati!G:G,Fonte_Dati!D:D,C36,Fonte_Dati!C:C,"Marzo"),0) -> 0 | M36: =IFERROR(SUMIFS(Fonte_Dati!H:H,Fonte_Dati!D:D,C36,Fonte_Dati!C:C,"Marzo"),0) -> 0 | N36: =IFERROR(SUMIFS(Fonte_Dati!I:I,Fonte_Dati!D:D,C36,Fonte_Dati!C:C,"Marzo"),0) -> 0 | O36: =IFERROR(N36/K36,0) -> 0
B37: 11 | C37: FV-Malvizzo Piccolo | D37: Fotovoltaico | E37: =IFERROR(VLOOKUP(C37,DB_Impianti!C:E,3,0),"") -> AXPO | F37: =IFERROR(VLOOKUP(C37,DB_Impianti!C:F,4,0),"") -> ERM Srl | G37: =IFERROR(VLOOKUP(C37,DB_Impianti!C:G,5,0),"") -> 0 | H37: =IFERROR(VLOOKUP(C37,DB_Impianti!C:H,6,0),0) -> -0.2 | I37: Gennaio 2026 | J37: =IFERROR(SUMIFS(Fonte_Dati!E:E,Fonte_Dati!D:D,C37,Fonte_Dati!C:C,"Gennaio")/1000,0) -> 111.37613 | K37: =IFERROR(SUMIFS(Fonte_Dati!F:F,Fonte_Dati!D:D,C37,Fonte_Dati!C:C,"Gennaio")/1000,0) -> 110.93062 | L37: =IFERROR(SUMIFS(Fonte_Dati!G:G,Fonte_Dati!D:D,C37,Fonte_Dati!C:C,"Gennaio"),0) -> 12280.38 | M37: =IFERROR(SUMIFS(Fonte_Dati!H:H,Fonte_Dati!D:D,C37,Fonte_Dati!C:C,"Gennaio"),0) -> -22.186124 | N37: =IFERROR(SUMIFS(Fonte_Dati!I:I,Fonte_Dati!D:D,C37,Fonte_Dati!C:C,"Gennaio"),0) -> 12258.194 | O37: =IFERROR(N37/K37,0) -> 110.50325
B38: 11 | C38: FV-Malvizzo Piccolo | D38: Fotovoltaico | E38: =IFERROR(VLOOKUP(C38,DB_Impianti!C:E,3,0),"") -> AXPO | F38: =IFERROR(VLOOKUP(C38,DB_Impianti!C:F,4,0),"") -> ERM Srl | G38: =IFERROR(VLOOKUP(C38,DB_Impianti!C:G,5,0),"") -> 0 | H38: =IFERROR(VLOOKUP(C38,DB_Impianti!C:H,6,0),0) -> -0.2 | I38: Febbraio 2026 | J38: =IFERROR(SUMIFS(Fonte_Dati!E:E,Fonte_Dati!D:D,C38,Fonte_Dati!C:C,"Febbraio")/1000,0) -> 214.7997 | K38: =IFERROR(SUMIFS(Fonte_Dati!F:F,Fonte_Dati!D:D,C38,Fonte_Dati!C:C,"Febbraio")/1000,0) -> 213.9405 | L38: =IFERROR(SUMIFS(Fonte_Dati!G:G,Fonte_Dati!D:D,C38,Fonte_Dati!C:C,"Febbraio"),0) -> 17453.896 | M38: =IFERROR(SUMIFS(Fonte_Dati!H:H,Fonte_Dati!D:D,C38,Fonte_Dati!C:C,"Febbraio"),0) -> -42.7881 | N38: =IFERROR(SUMIFS(Fonte_Dati!I:I,Fonte_Dati!D:D,C38,Fonte_Dati!C:C,"Febbraio"),0) -> 17411.108 | O38: =IFERROR(N38/K38,0) -> 81.382945
B39: 11 | C39: FV-Malvizzo Piccolo | D39: Fotovoltaico | E39: =IFERROR(VLOOKUP(C39,DB_Impianti!C:E,3,0),"") -> AXPO | F39: =IFERROR(VLOOKUP(C39,DB_Impianti!C:F,4,0),"") -> ERM Srl | G39: =IFERROR(VLOOKUP(C39,DB_Impianti!C:G,5,0),"") -> 0 | H39: =IFERROR(VLOOKUP(C39,DB_Impianti!C:H,6,0),0) -> -0.2 | I39: Marzo 2026 | J39: =IFERROR(SUMIFS(Fonte_Dati!E:E,Fonte_Dati!D:D,C39,Fonte_Dati!C:C,"Marzo")/1000,0) -> 0 | K39: =IFERROR(SUMIFS(Fonte_Dati!F:F,Fonte_Dati!D:D,C39,Fonte_Dati!C:C,"Marzo")/1000,0) -> 0 | L39: =IFERROR(SUMIFS(Fonte_Dati!G:G,Fonte_Dati!D:D,C39,Fonte_Dati!C:C,"Marzo"),0) -> 0 | M39: =IFERROR(SUMIFS(Fonte_Dati!H:H,Fonte_Dati!D:D,C39,Fonte_Dati!C:C,"Marzo"),0) -> 0 | N39: =IFERROR(SUMIFS(Fonte_Dati!I:I,Fonte_Dati!D:D,C39,Fonte_Dati!C:C,"Marzo"),0) -> 0 | O39: =IFERROR(N39/K39,0) -> 0
B40: 12 | C40: FV-Malvizzo a Terra | D40: Fotovoltaico | E40: =IFERROR(VLOOKUP(C40,DB_Impianti!C:E,3,0),"") -> DXT | F40: =IFERROR(VLOOKUP(C40,DB_Impianti!C:F,4,0),"") -> Moncada Energy Solar Srl | G40: =IFERROR(VLOOKUP(C40,DB_Impianti!C:G,5,0),"") -> PVI_0397946_001 | H40: =IFERROR(VLOOKUP(C40,DB_Impianti!C:H,6,0),0) -> -0.2 | I40: Gennaio 2026 | J40: =IFERROR(SUMIFS(Fonte_Dati!E:E,Fonte_Dati!D:D,C40,Fonte_Dati!C:C,"Gennaio")/1000,0) -> 112.0692 | K40: =IFERROR(SUMIFS(Fonte_Dati!F:F,Fonte_Dati!D:D,C40,Fonte_Dati!C:C,"Gennaio")/1000,0) -> 111.62092 | L40: =IFERROR(SUMIFS(Fonte_Dati!G:G,Fonte_Dati!D:D,C40,Fonte_Dati!C:C,"Gennaio"),0) -> 12199.659 | M40: =IFERROR(SUMIFS(Fonte_Dati!H:H,Fonte_Dati!D:D,C40,Fonte_Dati!C:C,"Gennaio"),0) -> -22.324185 | N40: =IFERROR(SUMIFS(Fonte_Dati!I:I,Fonte_Dati!D:D,C40,Fonte_Dati!C:C,"Gennaio"),0) -> 12177.335 | O40: =IFERROR(N40/K40,0) -> 109.09545
B41: 12 | C41: FV-Malvizzo a Terra | D41: Fotovoltaico | E41: =IFERROR(VLOOKUP(C41,DB_Impianti!C:E,3,0),"") -> DXT | F41: =IFERROR(VLOOKUP(C41,DB_Impianti!C:F,4,0),"") -> Moncada Energy Solar Srl | G41: =IFERROR(VLOOKUP(C41,DB_Impianti!C:G,5,0),"") -> PVI_0397946_001 | H41: =IFERROR(VLOOKUP(C41,DB_Impianti!C:H,6,0),0) -> -0.2 | I41: Febbraio 2026 | J41: =IFERROR(SUMIFS(Fonte_Dati!E:E,Fonte_Dati!D:D,C41,Fonte_Dati!C:C,"Febbraio")/1000,0) -> 208.40784 | K41: =IFERROR(SUMIFS(Fonte_Dati!F:F,Fonte_Dati!D:D,C41,Fonte_Dati!C:C,"Febbraio")/1000,0) -> 207.57421 | L41: =IFERROR(SUMIFS(Fonte_Dati!G:G,Fonte_Dati!D:D,C41,Fonte_Dati!C:C,"Febbraio"),0) -> 16847.599 | M41: =IFERROR(SUMIFS(Fonte_Dati!H:H,Fonte_Dati!D:D,C41,Fonte_Dati!C:C,"Febbraio"),0) -> -41.514842 | N41: =IFERROR(SUMIFS(Fonte_Dati!I:I,Fonte_Dati!D:D,C41,Fonte_Dati!C:C,"Febbraio"),0) -> 16806.084 | O41: =IFERROR(N41/K41,0) -> 80.96422
B42: 12 | C42: FV-Malvizzo a Terra | D42: Fotovoltaico | E42: =IFERROR(VLOOKUP(C42,DB_Impianti!C:E,3,0),"") -> DXT | F42: =IFERROR(VLOOKUP(C42,DB_Impianti!C:F,4,0),"") -> Moncada Energy Solar Srl | G42: =IFERROR(VLOOKUP(C42,DB_Impianti!C:G,5,0),"") -> PVI_0397946_001 | H42: =IFERROR(VLOOKUP(C42,DB_Impianti!C:H,6,0),0) -> -0.2 | I42: Marzo 2026 | J42: =IFERROR(SUMIFS(Fonte_Dati!E:E,Fonte_Dati!D:D,C42,Fonte_Dati!C:C,"Marzo")/1000,0) -> 0 | K42: =IFERROR(SUMIFS(Fonte_Dati!F:F,Fonte_Dati!D:D,C42,Fonte_Dati!C:C,"Marzo")/1000,0) -> 0 | L42: =IFERROR(SUMIFS(Fonte_Dati!G:G,Fonte_Dati!D:D,C42,Fonte_Dati!C:C,"Marzo"),0) -> 0 | M42: =IFERROR(SUMIFS(Fonte_Dati!H:H,Fonte_Dati!D:D,C42,Fonte_Dati!C:C,"Marzo"),0) -> 0 | N42: =IFERROR(SUMIFS(Fonte_Dati!I:I,Fonte_Dati!D:D,C42,Fonte_Dati!C:C,"Marzo"),0) -> 0 | O42: =IFERROR(N42/K42,0) -> 0
B43: 13 | C43: FV-Narbone a Terra Grande | D43: Fotovoltaico | E43: =IFERROR(VLOOKUP(C43,DB_Impianti!C:E,3,0),"") -> DXT | F43: =IFERROR(VLOOKUP(C43,DB_Impianti!C:F,4,0),"") -> Moncada Energy Solar Srl | G43: =IFERROR(VLOOKUP(C43,DB_Impianti!C:G,5,0),"") -> PVI_0397937_001 | H43: =IFERROR(VLOOKUP(C43,DB_Impianti!C:H,6,0),0) -> -0.2 | I43: Gennaio 2026 | J43: =IFERROR(SUMIFS(Fonte_Dati!E:E,Fonte_Dati!D:D,C43,Fonte_Dati!C:C,"Gennaio")/1000,0) -> 76.19016 | K43: =IFERROR(SUMIFS(Fonte_Dati!F:F,Fonte_Dati!D:D,C43,Fonte_Dati!C:C,"Gennaio")/1000,0) -> 75.885399 | L43: =IFERROR(SUMIFS(Fonte_Dati!G:G,Fonte_Dati!D:D,C43,Fonte_Dati!C:C,"Gennaio"),0) -> 8742.4718 | M43: =IFERROR(SUMIFS(Fonte_Dati!H:H,Fonte_Dati!D:D,C43,Fonte_Dati!C:C,"Gennaio"),0) -> -15.17708 | N43: =IFERROR(SUMIFS(Fonte_Dati!I:I,Fonte_Dati!D:D,C43,Fonte_Dati!C:C,"Gennaio"),0) -> 8727.2947 | O43: =IFERROR(N43/K43,0) -> 115.00624
B44: 13 | C44: FV-Narbone a Terra Grande | D44: Fotovoltaico | E44: =IFERROR(VLOOKUP(C44,DB_Impianti!C:E,3,0),"") -> DXT | F44: =IFERROR(VLOOKUP(C44,DB_Impianti!C:F,4,0),"") -> Moncada Energy Solar Srl | G44: =IFERROR(VLOOKUP(C44,DB_Impianti!C:G,5,0),"") -> PVI_0397937_001 | H44: =IFERROR(VLOOKUP(C44,DB_Impianti!C:H,6,0),0) -> -0.2 | I44: Febbraio 2026 | J44: =IFERROR(SUMIFS(Fonte_Dati!E:E,Fonte_Dati!D:D,C44,Fonte_Dati!C:C,"Febbraio")/1000,0) -> 0 | K44: =IFERROR(SUMIFS(Fonte_Dati!F:F,Fonte_Dati!D:D,C44,Fonte_Dati!C:C,"Febbraio")/1000,0) -> 0 | L44: =IFERROR(SUMIFS(Fonte_Dati!G:G,Fonte_Dati!D:D,C44,Fonte_Dati!C:C,"Febbraio"),0) -> 0 | M44: =IFERROR(SUMIFS(Fonte_Dati!H:H,Fonte_Dati!D:D,C44,Fonte_Dati!C:C,"Febbraio"),0) -> 0 | N44: =IFERROR(SUMIFS(Fonte_Dati!I:I,Fonte_Dati!D:D,C44,Fonte_Dati!C:C,"Febbraio"),0) -> 0 | O44: =IFERROR(N44/K44,0) -> 0
B45: 13 | C45: FV-Narbone a Terra Grande | D45: Fotovoltaico | E45: =IFERROR(VLOOKUP(C45,DB_Impianti!C:E,3,0),"") -> DXT | F45: =IFERROR(VLOOKUP(C45,DB_Impianti!C:F,4,0),"") -> Moncada Energy Solar Srl | G45: =IFERROR(VLOOKUP(C45,DB_Impianti!C:G,5,0),"") -> PVI_0397937_001 | H45: =IFERROR(VLOOKUP(C45,DB_Impianti!C:H,6,0),0) -> -0.2 | I45: Marzo 2026 | J45: =IFERROR(SUMIFS(Fonte_Dati!E:E,Fonte_Dati!D:D,C45,Fonte_Dati!C:C,"Marzo")/1000,0) -> 0 | K45: =IFERROR(SUMIFS(Fonte_Dati!F:F,Fonte_Dati!D:D,C45,Fonte_Dati!C:C,"Marzo")/1000,0) -> 0 | L45: =IFERROR(SUMIFS(Fonte_Dati!G:G,Fonte_Dati!D:D,C45,Fonte_Dati!C:C,"Marzo"),0) -> 0 | M45: =IFERROR(SUMIFS(Fonte_Dati!H:H,Fonte_Dati!D:D,C45,Fonte_Dati!C:C,"Marzo"),0) -> 0 | N45: =IFERROR(SUMIFS(Fonte_Dati!I:I,Fonte_Dati!D:D,C45,Fonte_Dati!C:C,"Marzo"),0) -> 0 | O45: =IFERROR(N45/K45,0) -> 0
B46: 14 | C46: FV-Narbone Piccolo | D46: Fotovoltaico | E46: =IFERROR(VLOOKUP(C46,DB_Impianti!C:E,3,0),"") -> AXPO | F46: =IFERROR(VLOOKUP(C46,DB_Impianti!C:F,4,0),"") -> ERM Srl | G46: =IFERROR(VLOOKUP(C46,DB_Impianti!C:G,5,0),"") -> 0 | H46: =IFERROR(VLOOKUP(C46,DB_Impianti!C:H,6,0),0) -> -0.2 | I46: Gennaio 2026 | J46: =IFERROR(SUMIFS(Fonte_Dati!E:E,Fonte_Dati!D:D,C46,Fonte_Dati!C:C,"Gennaio")/1000,0) -> 33.2097 | K46: =IFERROR(SUMIFS(Fonte_Dati!F:F,Fonte_Dati!D:D,C46,Fonte_Dati!C:C,"Gennaio")/1000,0) -> 33.076861 | L46: =IFERROR(SUMIFS(Fonte_Dati!G:G,Fonte_Dati!D:D,C46,Fonte_Dati!C:C,"Gennaio"),0) -> 3870.2981 | M46: =IFERROR(SUMIFS(Fonte_Dati!H:H,Fonte_Dati!D:D,C46,Fonte_Dati!C:C,"Gennaio"),0) -> -6.6153722 | N46: =IFERROR(SUMIFS(Fonte_Dati!I:I,Fonte_Dati!D:D,C46,Fonte_Dati!C:C,"Gennaio"),0) -> 3863.6828 | O46: =IFERROR(N46/K46,0) -> 116.80923
B47: 14 | C47: FV-Narbone Piccolo | D47: Fotovoltaico | E47: =IFERROR(VLOOKUP(C47,DB_Impianti!C:E,3,0),"") -> AXPO | F47: =IFERROR(VLOOKUP(C47,DB_Impianti!C:F,4,0),"") -> ERM Srl | G47: =IFERROR(VLOOKUP(C47,DB_Impianti!C:G,5,0),"") -> 0 | H47: =IFERROR(VLOOKUP(C47,DB_Impianti!C:H,6,0),0) -> -0.2 | I47: Febbraio 2026 | J47: =IFERROR(SUMIFS(Fonte_Dati!E:E,Fonte_Dati!D:D,C47,Fonte_Dati!C:C,"Febbraio")/1000,0) -> 45.30684 | K47: =IFERROR(SUMIFS(Fonte_Dati!F:F,Fonte_Dati!D:D,C47,Fonte_Dati!C:C,"Febbraio")/1000,0) -> 45.125613 | L47: =IFERROR(SUMIFS(Fonte_Dati!G:G,Fonte_Dati!D:D,C47,Fonte_Dati!C:C,"Febbraio"),0) -> 3532.2009 | M47: =IFERROR(SUMIFS(Fonte_Dati!H:H,Fonte_Dati!D:D,C47,Fonte_Dati!C:C,"Febbraio"),0) -> -9.0251225 | N47: =IFERROR(SUMIFS(Fonte_Dati!I:I,Fonte_Dati!D:D,C47,Fonte_Dati!C:C,"Febbraio"),0) -> 3523.1758 | O47: =IFERROR(N47/K47,0) -> 78.074857
B48: 14 | C48: FV-Narbone Piccolo | D48: Fotovoltaico | E48: =IFERROR(VLOOKUP(C48,DB_Impianti!C:E,3,0),"") -> AXPO | F48: =IFERROR(VLOOKUP(C48,DB_Impianti!C:F,4,0),"") -> ERM Srl | G48: =IFERROR(VLOOKUP(C48,DB_Impianti!C:G,5,0),"") -> 0 | H48: =IFERROR(VLOOKUP(C48,DB_Impianti!C:H,6,0),0) -> -0.2 | I48: Marzo 2026 | J48: =IFERROR(SUMIFS(Fonte_Dati!E:E,Fonte_Dati!D:D,C48,Fonte_Dati!C:C,"Marzo")/1000,0) -> 0 | K48: =IFERROR(SUMIFS(Fonte_Dati!F:F,Fonte_Dati!D:D,C48,Fonte_Dati!C:C,"Marzo")/1000,0) -> 0 | L48: =IFERROR(SUMIFS(Fonte_Dati!G:G,Fonte_Dati!D:D,C48,Fonte_Dati!C:C,"Marzo"),0) -> 0 | M48: =IFERROR(SUMIFS(Fonte_Dati!H:H,Fonte_Dati!D:D,C48,Fonte_Dati!C:C,"Marzo"),0) -> 0 | N48: =IFERROR(SUMIFS(Fonte_Dati!I:I,Fonte_Dati!D:D,C48,Fonte_Dati!C:C,"Marzo"),0) -> 0 | O48: =IFERROR(N48/K48,0) -> 0
B49: 15 | C49: FV-Campofranco Tetto | D49: Fotovoltaico | E49: =IFERROR(VLOOKUP(C49,DB_Impianti!C:E,3,0),"") -> DXT | F49: =IFERROR(VLOOKUP(C49,DB_Impianti!C:F,4,0),"") -> Moncada Energy Group Srl | G49: =IFERROR(VLOOKUP(C49,DB_Impianti!C:G,5,0),"") -> PVI_0130620_001 | H49: =IFERROR(VLOOKUP(C49,DB_Impianti!C:H,6,0),0) -> -0.2 | I49: Gennaio 2026 | J49: =IFERROR(SUMIFS(Fonte_Dati!E:E,Fonte_Dati!D:D,C49,Fonte_Dati!C:C,"Gennaio")/1000,0) -> 24.29524 | K49: =IFERROR(SUMIFS(Fonte_Dati!F:F,Fonte_Dati!D:D,C49,Fonte_Dati!C:C,"Gennaio")/1000,0) -> 24.854031 | L49: =IFERROR(SUMIFS(Fonte_Dati!G:G,Fonte_Dati!D:D,C49,Fonte_Dati!C:C,"Gennaio"),0) -> 3025.1312 | M49: =IFERROR(SUMIFS(Fonte_Dati!H:H,Fonte_Dati!D:D,C49,Fonte_Dati!C:C,"Gennaio"),0) -> -4.9708061 | N49: =IFERROR(SUMIFS(Fonte_Dati!I:I,Fonte_Dati!D:D,C49,Fonte_Dati!C:C,"Gennaio"),0) -> 3020.1604 | O49: =IFERROR(N49/K49,0) -> 121.51592
B50: 15 | C50: FV-Campofranco Tetto | D50: Fotovoltaico | E50: =IFERROR(VLOOKUP(C50,DB_Impianti!C:E,3,0),"") -> DXT | F50: =IFERROR(VLOOKUP(C50,DB_Impianti!C:F,4,0),"") -> Moncada Energy Group Srl | G50: =IFERROR(VLOOKUP(C50,DB_Impianti!C:G,5,0),"") -> PVI_0130620_001 | H50: =IFERROR(VLOOKUP(C50,DB_Impianti!C:H,6,0),0) -> -0.2 | I50: Febbraio 2026 | J50: =IFERROR(SUMIFS(Fonte_Dati!E:E,Fonte_Dati!D:D,C50,Fonte_Dati!C:C,"Febbraio")/1000,0) -> 46.40668 | K50: =IFERROR(SUMIFS(Fonte_Dati!F:F,Fonte_Dati!D:D,C50,Fonte_Dati!C:C,"Febbraio")/1000,0) -> 47.474034 | L50: =IFERROR(SUMIFS(Fonte_Dati!G:G,Fonte_Dati!D:D,C50,Fonte_Dati!C:C,"Febbraio"),0) -> 3611.6728 | M50: =IFERROR(SUMIFS(Fonte_Dati!H:H,Fonte_Dati!D:D,C50,Fonte_Dati!C:C,"Febbraio"),0) -> -9.4948067 | N50: =IFERROR(SUMIFS(Fonte_Dati!I:I,Fonte_Dati!D:D,C50,Fonte_Dati!C:C,"Febbraio"),0) -> 3602.178 | O50: =IFERROR(N50/K50,0) -> 75.876805
B51: 15 | C51: FV-Campofranco Tetto | D51: Fotovoltaico | E51: =IFERROR(VLOOKUP(C51,DB_Impianti!C:E,3,0),"") -> DXT | F51: =IFERROR(VLOOKUP(C51,DB_Impianti!C:F,4,0),"") -> Moncada Energy Group Srl | G51: =IFERROR(VLOOKUP(C51,DB_Impianti!C:G,5,0),"") -> PVI_0130620_001 | H51: =IFERROR(VLOOKUP(C51,DB_Impianti!C:H,6,0),0) -> -0.2 | I51: Marzo 2026 | J51: =IFERROR(SUMIFS(Fonte_Dati!E:E,Fonte_Dati!D:D,C51,Fonte_Dati!C:C,"Marzo")/1000,0) -> 0 | K51: =IFERROR(SUMIFS(Fonte_Dati!F:F,Fonte_Dati!D:D,C51,Fonte_Dati!C:C,"Marzo")/1000,0) -> 0 | L51: =IFERROR(SUMIFS(Fonte_Dati!G:G,Fonte_Dati!D:D,C51,Fonte_Dati!C:C,"Marzo"),0) -> 0 | M51: =IFERROR(SUMIFS(Fonte_Dati!H:H,Fonte_Dati!D:D,C51,Fonte_Dati!C:C,"Marzo"),0) -> 0 | N51: =IFERROR(SUMIFS(Fonte_Dati!I:I,Fonte_Dati!D:D,C51,Fonte_Dati!C:C,"Marzo"),0) -> 0 | O51: =IFERROR(N51/K51,0) -> 0
B52: 16 | C52: FV-Tumarrano MEG | D52: Fotovoltaico | E52: =IFERROR(VLOOKUP(C52,DB_Impianti!C:E,3,0),"") -> DXT | F52: =IFERROR(VLOOKUP(C52,DB_Impianti!C:F,4,0),"") -> Moncada Energy Group Srl | G52: =IFERROR(VLOOKUP(C52,DB_Impianti!C:G,5,0),"") -> PVI_0558896_001 | H52: =IFERROR(VLOOKUP(C52,DB_Impianti!C:H,6,0),0) -> -0.2 | I52: Gennaio 2026 | J52: =IFERROR(SUMIFS(Fonte_Dati!E:E,Fonte_Dati!D:D,C52,Fonte_Dati!C:C,"Gennaio")/1000,0) -> 7.469178 | K52: =IFERROR(SUMIFS(Fonte_Dati!F:F,Fonte_Dati!D:D,C52,Fonte_Dati!C:C,"Gennaio")/1000,0) -> 7.6409691 | L52: =IFERROR(SUMIFS(Fonte_Dati!G:G,Fonte_Dati!D:D,C52,Fonte_Dati!C:C,"Gennaio"),0) -> 900.69488 | M52: =IFERROR(SUMIFS(Fonte_Dati!H:H,Fonte_Dati!D:D,C52,Fonte_Dati!C:C,"Gennaio"),0) -> -1.5281938 | N52: =IFERROR(SUMIFS(Fonte_Dati!I:I,Fonte_Dati!D:D,C52,Fonte_Dati!C:C,"Gennaio"),0) -> 899.16669 | O52: =IFERROR(N52/K52,0) -> 117.67705
B53: 16 | C53: FV-Tumarrano MEG | D53: Fotovoltaico | E53: =IFERROR(VLOOKUP(C53,DB_Impianti!C:E,3,0),"") -> DXT | F53: =IFERROR(VLOOKUP(C53,DB_Impianti!C:F,4,0),"") -> Moncada Energy Group Srl | G53: =IFERROR(VLOOKUP(C53,DB_Impianti!C:G,5,0),"") -> PVI_0558896_001 | H53: =IFERROR(VLOOKUP(C53,DB_Impianti!C:H,6,0),0) -> -0.2 | I53: Febbraio 2026 | J53: =IFERROR(SUMIFS(Fonte_Dati!E:E,Fonte_Dati!D:D,C53,Fonte_Dati!C:C,"Febbraio")/1000,0) -> 11.697042 | K53: =IFERROR(SUMIFS(Fonte_Dati!F:F,Fonte_Dati!D:D,C53,Fonte_Dati!C:C,"Febbraio")/1000,0) -> 11.966074 | L53: =IFERROR(SUMIFS(Fonte_Dati!G:G,Fonte_Dati!D:D,C53,Fonte_Dati!C:C,"Febbraio"),0) -> 928.29321 | M53: =IFERROR(SUMIFS(Fonte_Dati!H:H,Fonte_Dati!D:D,C53,Fonte_Dati!C:C,"Febbraio"),0) -> -2.3932148 | N53: =IFERROR(SUMIFS(Fonte_Dati!I:I,Fonte_Dati!D:D,C53,Fonte_Dati!C:C,"Febbraio"),0) -> 925.9 | O53: =IFERROR(N53/K53,0) -> 77.377091
B54: 16 | C54: FV-Tumarrano MEG | D54: Fotovoltaico | E54: =IFERROR(VLOOKUP(C54,DB_Impianti!C:E,3,0),"") -> DXT | F54: =IFERROR(VLOOKUP(C54,DB_Impianti!C:F,4,0),"") -> Moncada Energy Group Srl | G54: =IFERROR(VLOOKUP(C54,DB_Impianti!C:G,5,0),"") -> PVI_0558896_001 | H54: =IFERROR(VLOOKUP(C54,DB_Impianti!C:H,6,0),0) -> -0.2 | I54: Marzo 2026 | J54: =IFERROR(SUMIFS(Fonte_Dati!E:E,Fonte_Dati!D:D,C54,Fonte_Dati!C:C,"Marzo")/1000,0) -> 0 | K54: =IFERROR(SUMIFS(Fonte_Dati!F:F,Fonte_Dati!D:D,C54,Fonte_Dati!C:C,"Marzo")/1000,0) -> 0 | L54: =IFERROR(SUMIFS(Fonte_Dati!G:G,Fonte_Dati!D:D,C54,Fonte_Dati!C:C,"Marzo"),0) -> 0 | M54: =IFERROR(SUMIFS(Fonte_Dati!H:H,Fonte_Dati!D:D,C54,Fonte_Dati!C:C,"Marzo"),0) -> 0 | N54: =IFERROR(SUMIFS(Fonte_Dati!I:I,Fonte_Dati!D:D,C54,Fonte_Dati!C:C,"Marzo"),0) -> 0 | O54: =IFERROR(N54/K54,0) -> 0
B55: TOTALE PORTFOLIO Q1 | J55: =SUM(J7:J54) -> 28821.906 | K55: =SUM(K7:K54) -> 28924.178 | L55: =SUM(L7:L54) -> 3133013.1 | M55: =SUM(M7:M54) -> -5784.8357 | N55: =SUM(N7:N54) -> 3127228.3 | O55: =IFERROR(N55/K55,0) -> 108.11814

Sheet Ranking
B1: 🏆 RANKING PERFORMANCE IMPIANTI — Q1 2026
B4: Classifica per Fatturato Netto e EUR/MWh | Fonte: Dati Reali
B6: 🥇 RANKING PER FATTURATO NETTO Q1 2026
B7: Rank | C7: Impianto | D7: Tipo | E7: Trader | F7: MWh Misurati | G7: MWh Maggiorati | H7: Fat. Netto (€) | I7: EUR/MWh | J7: Fee App. (€) | K7: Quota %
B8: 🥇 1 | C8: Wind - Monte Narbone | D8: Eolico | E8: DXT | F8: =IFERROR(SUMIFS(Fonte_Dati!E:E,Fonte_Dati!D:D,C8)/1000,0) -> 9096.2236 | G8: =IFERROR(SUMIFS(Fonte_Dati!F:F,Fonte_Dati!D:D,C8)/1000,0) -> 9096.2316 | H8: =IFERROR(SUMIFS(Fonte_Dati!I:I,Fonte_Dati!D:D,C8),0) -> 1040798.1 | I8: =IFERROR(H8/G8,0) -> 114.4208 | J8: =IFERROR(VLOOKUP(C8,DB_Impianti!C:H,6,0),0) -> -1.36 | K8: =IFERROR(H8/3127228.3,0) -> 0.33281807
B9: 🥈 2 | C9: Wind - Monte Durrà | D9: Eolico | E9: BANCO ENERGIA | F9: =IFERROR(SUMIFS(Fonte_Dati!E:E,Fonte_Dati!D:D,C9)/1000,0) -> 8107.3148 | G9: =IFERROR(SUMIFS(Fonte_Dati!F:F,Fonte_Dati!D:D,C9)/1000,0) -> 8107.3148 | H9: =IFERROR(SUMIFS(Fonte_Dati!I:I,Fonte_Dati!D:D,C9),0) -> 906810.8 | I9: =IFERROR(H9/G9,0) -> 111.85094 | J9: =IFERROR(VLOOKUP(C9,DB_Impianti!C:H,6,0),0) -> -1.86 | K9: =IFERROR(H9/3127228.3,0) -> 0.28997269
B10: 🥉 3 | C10: Wind - Monte Malvizzo | D10: Eolico | E10: DXT | F10: =IFERROR(SUMIFS(Fonte_Dati!E:E,Fonte_Dati!D:D,C10)/1000,0) -> 3945.0563 | G10: =IFERROR(SUMIFS(Fonte_Dati!F:F,Fonte_Dati!D:D,C10)/1000,0) -> 3945.0775 | H10: =IFERROR(SUMIFS(Fonte_Dati!I:I,Fonte_Dati!D:D,C10),0) -> 444266.5 | I10: =IFERROR(H10/G10,0) -> 112.61287 | J10: =IFERROR(VLOOKUP(C10,DB_Impianti!C:H,6,0),0) -> -1.36 | K10: =IFERROR(H10/3127228.3,0) -> 0.14206398
B11: 4 | C11: FV-Favara Grande | D11: Fotovoltaico | E11: AXPO | F11: =IFERROR(SUMIFS(Fonte_Dati!E:E,Fonte_Dati!D:D,C11)/1000,0) -> 1544.2125 | G11: =IFERROR(SUMIFS(Fonte_Dati!F:F,Fonte_Dati!D:D,C11)/1000,0) -> 1579.7294 | H11: =IFERROR(SUMIFS(Fonte_Dati!I:I,Fonte_Dati!D:D,C11),0) -> 150090.73 | I11: =IFERROR(H11/G11,0) -> 95.010406 | J11: =IFERROR(VLOOKUP(C11,DB_Impianti!C:H,6,0),0) -> -0.2 | K11: =IFERROR(H11/3127228.3,0) -> 0.04799481
B12: 5 | C12: FV-Fauma Tetto | D12: Fotovoltaico | E12: AXPO | F12: =IFERROR(SUMIFS(Fonte_Dati!E:E,Fonte_Dati!D:D,C12)/1000,0) -> 1503.9636 | G12: =IFERROR(SUMIFS(Fonte_Dati!F:F,Fonte_Dati!D:D,C12)/1000,0) -> 1538.5548 | H12: =IFERROR(SUMIFS(Fonte_Dati!I:I,Fonte_Dati!D:D,C12),0) -> 148049 | I12: =IFERROR(H12/G12,0) -> 96.226018 | J12: =IFERROR(VLOOKUP(C12,DB_Impianti!C:H,6,0),0) -> -0.2 | K12: =IFERROR(H12/3127228.3,0) -> 0.047341922
B13: 6 | C13: FV-Batia S. Francesco | D13: Fotovoltaico | E13: DXT | F13: =IFERROR(SUMIFS(Fonte_Dati!E:E,Fonte_Dati!D:D,C13)/1000,0) -> 1146.8885 | G13: =IFERROR(SUMIFS(Fonte_Dati!F:F,Fonte_Dati!D:D,C13)/1000,0) -> 1142.3009 | H13: =IFERROR(SUMIFS(Fonte_Dati!I:I,Fonte_Dati!D:D,C13),0) -> 103282.14 | I13: =IFERROR(H13/G13,0) -> 90.415876 | J13: =IFERROR(VLOOKUP(C13,DB_Impianti!C:H,6,0),0) -> -0.2 | K13: =IFERROR(H13/3127228.3,0) -> 0.033026734
B14: 7 | C14: FV-Serre S.Angelo Muxaro | D14: Fotovoltaico | E14: DXT | F14: =IFERROR(SUMIFS(Fonte_Dati!E:E,Fonte_Dati!D:D,C14)/1000,0) -> 787.1292 | G14: =IFERROR(SUMIFS(Fonte_Dati!F:F,Fonte_Dati!D:D,C14)/1000,0) -> 805.23317 | H14: =IFERROR(SUMIFS(Fonte_Dati!I:I,Fonte_Dati!D:D,C14),0) -> 77519.685 | I14: =IFERROR(H14/G14,0) -> 96.26986 | J14: =IFERROR(VLOOKUP(C14,DB_Impianti!C:H,6,0),0) -> -0.2 | K14: =IFERROR(H14/3127228.3,0) -> 0.024788623
B15: 8 | C15: FV-Serre Narbone | D15: Fotovoltaico | E15: DXT | F15: =IFERROR(SUMIFS(Fonte_Dati!E:E,Fonte_Dati!D:D,C15)/1000,0) -> 801.5076 | G15: =IFERROR(SUMIFS(Fonte_Dati!F:F,Fonte_Dati!D:D,C15)/1000,0) -> 798.30157 | H15: =IFERROR(SUMIFS(Fonte_Dati!I:I,Fonte_Dati!D:D,C15),0) -> 75964.775 | I15: =IFERROR(H15/G15,0) -> 95.157993 | J15: =IFERROR(VLOOKUP(C15,DB_Impianti!C:H,6,0),0) -> -0.2 | K15: =IFERROR(H15/3127228.3,0) -> 0.024291407
B16: 9 | C16: FV-Perniciara | D16: Fotovoltaico | E16: AXPO | F16: =IFERROR(SUMIFS(Fonte_Dati!E:E,Fonte_Dati!D:D,C16)/1000,0) -> 521.4165 | G16: =IFERROR(SUMIFS(Fonte_Dati!F:F,Fonte_Dati!D:D,C16)/1000,0) -> 533.40908 | H16: =IFERROR(SUMIFS(Fonte_Dati!I:I,Fonte_Dati!D:D,C16),0) -> 50752.105 | I16: =IFERROR(H16/G16,0) -> 95.146684 | J16: =IFERROR(VLOOKUP(C16,DB_Impianti!C:H,6,0),0) -> -0.2 | K16: =IFERROR(H16/3127228.3,0) -> 0.016229101
B17: 10 | C17: FV-Serre Gela | D17: Fotovoltaico | E17: DXT | F17: =IFERROR(SUMIFS(Fonte_Dati!E:E,Fonte_Dati!D:D,C17)/1000,0) -> 476.96608 | G17: =IFERROR(SUMIFS(Fonte_Dati!F:F,Fonte_Dati!D:D,C17)/1000,0) -> 487.9363 | H17: =IFERROR(SUMIFS(Fonte_Dati!I:I,Fonte_Dati!D:D,C17),0) -> 46480.205 | I17: =IFERROR(H17/G17,0) -> 95.258757 | J17: =IFERROR(VLOOKUP(C17,DB_Impianti!C:H,6,0),0) -> -0.2 | K17: =IFERROR(H17/3127228.3,0) -> 0.014863068
B18: 11 | C18: FV-Malvizzo Piccolo | D18: Fotovoltaico | E18: AXPO | F18: =IFERROR(SUMIFS(Fonte_Dati!E:E,Fonte_Dati!D:D,C18)/1000,0) -> 326.17582 | G18: =IFERROR(SUMIFS(Fonte_Dati!F:F,Fonte_Dati!D:D,C18)/1000,0) -> 324.87112 | H18: =IFERROR(SUMIFS(Fonte_Dati!I:I,Fonte_Dati!D:D,C18),0) -> 29669.302 | I18: =IFERROR(H18/G18,0) -> 91.326377 | J18: =IFERROR(VLOOKUP(C18,DB_Impianti!C:H,6,0),0) -> -0.2 | K18: =IFERROR(H18/3127228.3,0) -> 0.0094874117
B19: 12 | C19: FV-Malvizzo a Terra | D19: Fotovoltaico | E19: DXT | F19: =IFERROR(SUMIFS(Fonte_Dati!E:E,Fonte_Dati!D:D,C19)/1000,0) -> 320.47704 | G19: =IFERROR(SUMIFS(Fonte_Dati!F:F,Fonte_Dati!D:D,C19)/1000,0) -> 319.19513 | H19: =IFERROR(SUMIFS(Fonte_Dati!I:I,Fonte_Dati!D:D,C19),0) -> 28983.419 | I19: =IFERROR(H19/G19,0) -> 90.80157 | J19: =IFERROR(VLOOKUP(C19,DB_Impianti!C:H,6,0),0) -> -0.2 | K19: =IFERROR(H19/3127228.3,0) -> 0.0092680854
... B23: 16 | C23: FV-Tumarrano MEG | D23: Fotovoltaico | E23: DXT | F23: =IFERROR(SUMIFS(Fonte_Dati!E:E,Fonte_Dati!D:D,C23)/1000,0) -> 19.16622 | G23: =IFERROR(SUMIFS(Fonte_Dati!F:F,Fonte_Dati!D:D,C23)/1000,0) -> 19.607043 | H23: =IFERROR(SUMIFS(Fonte_Dati!I:I,Fonte_Dati!D:D,C23),0) -> 1825.0667 | I23: =IFERROR(H23/G23,0) -> 93.082199 | J23: =IFERROR(VLOOKUP(C23,DB_Impianti!C:H,6,0),0) -> -0.2 | K23: =IFERROR(H23/3127228.3,0) -> 0.0005836052
B26: 💹 RANKING PER PREZZO EUR/MWh Q1 2026
B27: Rank | C27: Impianto | D27: Tipo | E27: Trader | F27: MWh Mis. | G27: MWh Magg. | H27: Fat. Netto (€) | I27: EUR/MWh | J27: Fee (€/MWh) | K27: Δ vs Media
B28: 🥇 1 | C28: FV-Narbone a Terra Grande | D28: Fotovoltaico | E28: DXT | F28: =IFERROR(SUMIFS(Fonte_Dati!E:E,Fonte_Dati!D:D,C28)/1000,0) -> 76.19016 | G28: =IFERROR(SUMIFS(Fonte_Dati!F:F,Fonte_Dati!D:D,C28)/1000,0) -> 75.885399 | H28: =IFERROR(SUMIFS(Fonte_Dati!I:I,Fonte_Dati!D:D,C28),0) -> 8727.2947 | I28: =IFERROR(H28/G28,0) -> 115.00624 | J28: =IFERROR(VLOOKUP(C28,DB_Impianti!C:H,6,0),0) -> -0.2 | K28: 6.8881054
B29: 🥈 2 | C29: Wind - Monte Narbone | D29: Eolico | E29: DXT | F29: =IFERROR(SUMIFS(Fonte_Dati!E:E,Fonte_Dati!D:D,C29)/1000,0) -> 9096.2236 | G29: =IFERROR(SUMIFS(Fonte_Dati!F:F,Fonte_Dati!D:D,C29)/1000,0) -> 9096.2316 | H29: =IFERROR(SUMIFS(Fonte_Dati!I:I,Fonte_Dati!D:D,C29),0) -> 1040798.1 | I29: =IFERROR(H29/G29,0) -> 114.4208 | J29: =IFERROR(VLOOKUP(C29,DB_Impianti!C:H,6,0),0) -> -1.36 | K29: 6.3026607
B30: 🥉 3 | C30: Wind - Monte Malvizzo | D30: Eolico | E30: DXT | F30: =IFERROR(SUMIFS(Fonte_Dati!E:E,Fonte_Dati!D:D,C30)/1000,0) -> 3945.0563 | G30: =IFERROR(SUMIFS(Fonte_Dati!F:F,Fonte_Dati!D:D,C30)/1000,0) -> 3945.0775 | H30: =IFERROR(SUMIFS(Fonte_Dati!I:I,Fonte_Dati!D:D,C30),0) -> 444266.5 | I30: =IFERROR(H30/G30,0) -> 112.61287 | J30: =IFERROR(VLOOKUP(C30,DB_Impianti!C:H,6,0),0) -> -1.36 | K30: 4.4947319
B31: 4 | C31: Wind - Monte Durrà | D31: Eolico | E31: BANCO ENERGIA | F31: =IFERROR(SUMIFS(Fonte_Dati!E:E,Fonte_Dati!D:D,C31)/1000,0) -> 8107.3148 | G31: =IFERROR(SUMIFS(Fonte_Dati!F:F,Fonte_Dati!D:D,C31)/1000,0) -> 8107.3148 | H31: =IFERROR(SUMIFS(Fonte_Dati!I:I,Fonte_Dati!D:D,C31),0) -> 906810.8 | I31: =IFERROR(H31/G31,0) -> 111.85094 | J31: =IFERROR(VLOOKUP(C31,DB_Impianti!C:H,6,0),0) -> -1.86 | K31: 3.7328043
B32: 5 | C32: FV-Serre S.Angelo Muxaro | D32: Fotovoltaico | E32: DXT | F32: =IFERROR(SUMIFS(Fonte_Dati!E:E,Fonte_Dati!D:D,C32)/1000,0) -> 787.1292 | G32: =IFERROR(SUMIFS(Fonte_Dati!F:F,Fonte_Dati!D:D,C32)/1000,0) -> 805.23317 | H32: =IFERROR(SUMIFS(Fonte_Dati!I:I,Fonte_Dati!D:D,C32),0) -> 77519.685 | I32: =IFERROR(H32/G32,0) -> 96.26986 | J32: =IFERROR(VLOOKUP(C32,DB_Impianti!C:H,6,0),0) -> -0.2 | K32: -11.848278
B33: 6 | C33: FV-Fauma Tetto | D33: Fotovoltaico | E33: AXPO | F33: =IFERROR(SUMIFS(Fonte_Dati!E:E,Fonte_Dati!D:D,C33)/1000,0) -> 1503.9636 | G33: =IFERROR(SUMIFS(Fonte_Dati!F:F,Fonte_Dati!D:D,C33)/1000,0) -> 1538.5548 | H33: =IFERROR(SUMIFS(Fonte_Dati!I:I,Fonte_Dati!D:D,C33),0) -> 148049 | I33: =IFERROR(H33/G33,0) -> 96.226018 | J33: =IFERROR(VLOOKUP(C33,DB_Impianti!C:H,6,0),0) -> -0.2 | K33: -11.892119
B34: 7 | C34: FV-Serre Gela | D34: Fotovoltaico | E34: DXT | F34: =IFERROR(SUMIFS(Fonte_Dati!E:E,Fonte_Dati!D:D,C34)/1000,0) -> 476.96608 | G34: =IFERROR(SUMIFS(Fonte_Dati!F:F,Fonte_Dati!D:D,C34)/1000,0) -> 487.9363 | H34: =IFERROR(SUMIFS(Fonte_Dati!I:I,Fonte_Dati!D:D,C34),0) -> 46480.205 | I34: =IFERROR(H34/G34,0) -> 95.258757 | J34: =IFERROR(VLOOKUP(C34,DB_Impianti!C:H,6,0),0) -> -0.2 | K34: -12.859381
B35: 8 | C35: FV-Serre Narbone | D35: Fotovoltaico | E35: DXT | F35: =IFERROR(SUMIFS(Fonte_Dati!E:E,Fonte_Dati!D:D,C35)/1000,0) -> 801.5076 | G35: =IFERROR(SUMIFS(Fonte_Dati!F:F,Fonte_Dati!D:D,C35)/1000,0) -> 798.30157 | H35: =IFERROR(SUMIFS(Fonte_Dati!I:I,Fonte_Dati!D:D,C35),0) -> 75964.775 | I35: =IFERROR(H35/G35,0) -> 95.157993 | J35: =IFERROR(VLOOKUP(C35,DB_Impianti!C:H,6,0),0) -> -0.2 | K35: -12.960144
B36: 9 | C36: FV-Perniciara | D36: Fotovoltaico | E36: AXPO | F36: =IFERROR(SUMIFS(Fonte_Dati!E:E,Fonte_Dati!D:D,C36)/1000,0) -> 521.4165 | G36: =IFERROR(SUMIFS(Fonte_Dati!F:F,Fonte_Dati!D:D,C36)/1000,0) -> 533.40908 | H36: =IFERROR(SUMIFS(Fonte_Dati!I:I,Fonte_Dati!D:D,C36),0) -> 50752.105 | I36: =IFERROR(H36/G36,0) -> 95.146684 | J36: =IFERROR(VLOOKUP(C36,DB_Impianti!C:H,6,0),0) -> -0.2 | K36: -12.971454
B37: 10 | C37: FV-Favara Grande | D37: Fotovoltaico | E37: AXPO | F37: =IFERROR(SUMIFS(Fonte_Dati!E:E,Fonte_Dati!D:D,C37)/1000,0) -> 1544.2125 | G37: =IFERROR(SUMIFS(Fonte_Dati!F:F,Fonte_Dati!D:D,C37)/1000,0) -> 1579.7294 | H37: =IFERROR(SUMIFS(Fonte_Dati!I:I,Fonte_Dati!D:D,C37),0) -> 150090.73 | I37: =IFERROR(H37/G37,0) -> 95.010406 | J37: =IFERROR(VLOOKUP(C37,DB_Impianti!C:H,6,0),0) -> -0.2 | K37: -13.107732
B38: 11 | C38: FV-Narbone Piccolo | D38: Fotovoltaico | E38: AXPO | F38: =IFERROR(SUMIFS(Fonte_Dati!E:E,Fonte_Dati!D:D,C38)/1000,0) -> 78.51654 | G38: =IFERROR(SUMIFS(Fonte_Dati!F:F,Fonte_Dati!D:D,C38)/1000,0) -> 78.202474 | H38: =IFERROR(SUMIFS(Fonte_Dati!I:I,Fonte_Dati!D:D,C38),0) -> 7386.8585 | I38: =IFERROR(H38/G38,0) -> 94.458118 | J38: =IFERROR(VLOOKUP(C38,DB_Impianti!C:H,6,0),0) -> -0.2 | K38: -13.66002
B39: 12 | C39: FV-Tumarrano MEG | D39: Fotovoltaico | E39: DXT | F39: =IFERROR(SUMIFS(Fonte_Dati!E:E,Fonte_Dati!D:D,C39)/1000,0) -> 19.16622 | G39: =IFERROR(SUMIFS(Fonte_Dati!F:F,Fonte_Dati!D:D,C39)/1000,0) -> 19.607043 | H39: =IFERROR(SUMIFS(Fonte_Dati!I:I,Fonte_Dati!D:D,C39),0) -> 1825.0667 | I39: =IFERROR(H39/G39,0) -> 93.082199 | J39: =IFERROR(VLOOKUP(C39,DB_Impianti!C:H,6,0),0) -> -0.2 | K39: -15.035939
... B43: 16 | C43: FV-Batia S. Francesco | D43: Fotovoltaico | E43: DXT | F43: =IFERROR(SUMIFS(Fonte_Dati!E:E,Fonte_Dati!D:D,C43)/1000,0) -> 1146.8885 | G43: =IFERROR(SUMIFS(Fonte_Dati!F:F,Fonte_Dati!D:D,C43)/1000,0) -> 1142.3009 | H43: =IFERROR(SUMIFS(Fonte_Dati!I:I,Fonte_Dati!D:D,C43),0) -> 103282.14 | I43: =IFERROR(H43/G43,0) -> 90.415876 | J43: =IFERROR(VLOOKUP(C43,DB_Impianti!C:H,6,0),0) -> -0.2 | K43: -17.702262

Sheet Finanziario
B1: 💰 ANALISI FINANZIARIA CONSOLIDATA — PORTFOLIO Q1 2026
B4: P&L per Impianto con dati reali di fatturazione | Fonte: _Storico_Dati_
B5: P&L PER IMPIANTO — Q1 2026 (DATI REALI + INCENTIVI)
B6: P&L PER IMPIANTO — Q1 2026 (DATI REALI)
B7: ID | C7: Impianto | D7: Tipo | E7: Fat. Lordo (€) | F7: Fee App. (€) | G7: Fat. Netto (€) | H7: OPEX est. (€) | I7: EBITDA est. (€) | J7: EBITDA Margin | K7: EUR/MWh | L7: Acconto Incentivi Q1 (€) | M7: Consuntivo Incentivi Q1 (€) | N7: EBITDA + Incentivi (€) | O7: Margin + Incentivi
B8: 1 | C8: Wind - Monte Narbone | D8: Eolico | E8: =IFERROR(SUMIFS(Fonte_Dati!G:G,Fonte_Dati!D:D,C8),0) -> 1042617.3 | F8: =IFERROR(SUMIFS(Fonte_Dati!H:H,Fonte_Dati!D:D,C8),0) -> -1819.2463 | G8: =IFERROR(SUMIFS(Fonte_Dati!I:I,Fonte_Dati!D:D,C8),0) -> 1040798.1 | H8: =IFERROR(G8*0.08,0) -> 83263.847 | I8: =IFERROR(G8-H8,0) -> 957534.24 | J8: =IFERROR(I8/G8,0) -> 0.92 | K8: =IFERROR(SUMIFS(Fonte_Dati!I:I,Fonte_Dati!D:D,C8)/SUMIFS(Fonte_Dati!F:F,Fonte_Dati!D:D,C8)*1000,0) -> 114.4208 | L8: =IFERROR(SUMIF('💹 Incentivi'!D8:D23,"*Narbone*",'💹 Incentivi'!R8:R23),0) -> 1146908.8 | M8: =IFERROR(SUMIF('💹 Incentivi'!D28:D43,"*Narbone*",'💹 Incentivi'!R28:R43),0) -> 418280.79 | N8: =IFERROR(I8+M8,"") -> 1375815 | O8: =IFERROR(N8/(G8+M8),"") -> 0.94293396
B9: 2 | C9: Wind - Monte Durrà | D9: Eolico | E9: =IFERROR(SUMIFS(Fonte_Dati!G:G,Fonte_Dati!D:D,C9),0) -> 908432.26 | F9: =IFERROR(SUMIFS(Fonte_Dati!H:H,Fonte_Dati!D:D,C9),0) -> -1621.463 | G9: =IFERROR(SUMIFS(Fonte_Dati!I:I,Fonte_Dati!D:D,C9),0) -> 906810.8 | H9: =IFERROR(G9*0.08,0) -> 72544.864 | I9: =IFERROR(G9-H9,0) -> 834265.94 | J9: =IFERROR(I9/G9,0) -> 0.92 | K9: =IFERROR(SUMIFS(Fonte_Dati!I:I,Fonte_Dati!D:D,C9)/SUMIFS(Fonte_Dati!F:F,Fonte_Dati!D:D,C9)*1000,0) -> 111.85094 | L9: =IFERROR(SUMIF('💹 Incentivi'!D8:D23,"*Durr*",'💹 Incentivi'!R8:R23),0) -> 0 | M9: =IFERROR(SUMIF('💹 Incentivi'!D28:D43,"*Durr*",'💹 Incentivi'!R28:R43),0) -> 0 | N9: =IFERROR(I9+M9,"") -> 834265.94 | O9: =IFERROR(N9/(G9+M9),"") -> 0.92
B10: 3 | C10: Wind - Monte Malvizzo | D10: Eolico | E10: =IFERROR(SUMIFS(Fonte_Dati!G:G,Fonte_Dati!D:D,C10),0) -> 445055.51 | F10: =IFERROR(SUMIFS(Fonte_Dati!H:H,Fonte_Dati!D:D,C10),0) -> -789.0155 | G10: =IFERROR(SUMIFS(Fonte_Dati!I:I,Fonte_Dati!D:D,C10),0) -> 444266.5 | H10: =IFERROR(G10*0.08,0) -> 35541.32 | I10: =IFERROR(G10-H10,0) -> 408725.18 | J10: =IFERROR(I10/G10,0) -> 0.92 | K10: =IFERROR(SUMIFS(Fonte_Dati!I:I,Fonte_Dati!D:D,C10)/SUMIFS(Fonte_Dati!F:F,Fonte_Dati!D:D,C10)*1000,0) -> 112.61287 | L10: =IFERROR(SUMIF('💹 Incentivi'!D8:D23,"*Malvizzo*",'💹 Incentivi'!R8:R23),0) -> 243603.03 | M10: =IFERROR(SUMIF('💹 Incentivi'!D28:D43,"*Malvizzo*",'💹 Incentivi'!R28:R43),0) -> 82537.585 | N10: =IFERROR(I10+M10,"") -> 491262.76 | O10: =IFERROR(N10/(G10+M10),"") -> 0.93253408
B11: 4 | C11: FV-Favara Grande | D11: Fotovoltaico | E11: =IFERROR(SUMIFS(Fonte_Dati!G:G,Fonte_Dati!D:D,C11),0) -> 150406.67 | F11: =IFERROR(SUMIFS(Fonte_Dati!H:H,Fonte_Dati!D:D,C11),0) -> -315.94587 | G11: =IFERROR(SUMIFS(Fonte_Dati!I:I,Fonte_Dati!D:D,C11),0) -> 150090.73 | H11: =IFERROR(G11*0.08,0) -> 12007.258 | I11: =IFERROR(G11-H11,0) -> 138083.47 | J11: =IFERROR(I11/G11,0) -> 0.92 | K11: =IFERROR(SUMIFS(Fonte_Dati!I:I,Fonte_Dati!D:D,C11)/SUMIFS(Fonte_Dati!F:F,Fonte_Dati!D:D,C11)*1000,0) -> 95.010406 | L11: =IFERROR(SUMIF('💹 Incentivi'!D8:D23,"*Favara*",'💹 Incentivi'!R8:R23),0) -> 0 | M11: =IFERROR(SUMIF('💹 Incentivi'!D28:D43,"*Favara*",'💹 Incentivi'!R28:R43),0) -> 0 | N11: =IFERROR(I11+M11,"") -> 138083.47 | O11: =IFERROR(N11/(G11+M11),"") -> 0.92
B12: 5 | C12: FV-Fauma Tetto | D12: Fotovoltaico | E12: =IFERROR(SUMIFS(Fonte_Dati!G:G,Fonte_Dati!D:D,C12),0) -> 148356.71 | F12: =IFERROR(SUMIFS(Fonte_Dati!H:H,Fonte_Dati!D:D,C12),0) -> -307.71095 | G12: =IFERROR(SUMIFS(Fonte_Dati!I:I,Fonte_Dati!D:D,C12),0) -> 148049 | H12: =IFERROR(G12*0.08,0) -> 11843.92 | I12: =IFERROR(G12-H12,0) -> 136205.08 | J12: =IFERROR(I12/G12,0) -> 0.92 | K12: =IFERROR(SUMIFS(Fonte_Dati!I:I,Fonte_Dati!D:D,C12)/SUMIFS(Fonte_Dati!F:F,Fonte_Dati!D:D,C12)*1000,0) -> 96.226018 | L12: =IFERROR(SUMIF('💹 Incentivi'!D8:D23,"*Fauma*",'💹 Incentivi'!R8:R23),0) -> 0 | M12: =IFERROR(SUMIF('💹 Incentivi'!D28:D43,"*Fauma*",'💹 Incentivi'!R28:R43),0) -> 0 | N12: =IFERROR(I12+M12,"") -> 136205.08 | O12: =IFERROR(N12/(G12+M12),"") -> 0.92
B13: 6 | C13: FV-Batia S. Francesco | D13: Fotovoltaico | E13: =IFERROR(SUMIFS(Fonte_Dati!G:G,Fonte_Dati!D:D,C13),0) -> 103510.6 | F13: =IFERROR(SUMIFS(Fonte_Dati!H:H,Fonte_Dati!D:D,C13),0) -> -228.46019 | G13: =IFERROR(SUMIFS(Fonte_Dati!I:I,Fonte_Dati!D:D,C13),0) -> 103282.14 | H13: =IFERROR(G13*0.08,0) -> 8262.5711 | I13: =IFERROR(G13-H13,0) -> 95019.567 | J13: =IFERROR(I13/G13,0) -> 0.92 | K13: =IFERROR(SUMIFS(Fonte_Dati!I:I,Fonte_Dati!D:D,C13)/SUMIFS(Fonte_Dati!F:F,Fonte_Dati!D:D,C13)*1000,0) -> 90.415876 | L13: =IFERROR(SUMIF('💹 Incentivi'!D8:D23,"*Batia*",'💹 Incentivi'!R8:R23),0) -> 328842.23 | M13: =IFERROR(SUMIF('💹 Incentivi'!D28:D43,"*Batia*",'💹 Incentivi'!R28:R43),0) -> 139074.7 | N13: =IFERROR(I13+M13,"") -> 234094.27 | O13: =IFERROR(N13/(G13+M13),"") -> 0.96590742
B14: 7 | C14: FV-Serre S.Angelo Muxaro | D14: Fotovoltaico | E14: =IFERROR(SUMIFS(Fonte_Dati!G:G,Fonte_Dati!D:D,C14),0) -> 77680.731 | F14: =IFERROR(SUMIFS(Fonte_Dati!H:H,Fonte_Dati!D:D,C14),0) -> -161.04663 | G14: =IFERROR(SUMIFS(Fonte_Dati!I:I,Fonte_Dati!D:D,C14),0) -> 77519.685 | H14: =IFERROR(G14*0.08,0) -> 6201.5748 | I14: =IFERROR(G14-H14,0) -> 71318.11 | J14: =IFERROR(I14/G14,0) -> 0.92 | K14: =IFERROR(SUMIFS(Fonte_Dati!I:I,Fonte_Dati!D:D,C14)/SUMIFS(Fonte_Dati!F:F,Fonte_Dati!D:D,C14)*1000,0) -> 96.26986 | L14: =IFERROR(SUMIF('💹 Incentivi'!D8:D23,"*Muxaro*",'💹 Incentivi'!R8:R23),0) -> 626391.11 | M14: =IFERROR(SUMIF('💹 Incentivi'!D28:D43,"*Muxaro*",'💹 Incentivi'!R28:R43),0) -> 256900.42 | N14: =IFERROR(I14+M14,"") -> 328218.53 | O14: =IFERROR(N14/(G14+M14),"") -> 0.98145574
B15: 8 | C15: FV-Serre Narbone | D15: Fotovoltaico | E15: =IFERROR(SUMIFS(Fonte_Dati!G:G,Fonte_Dati!D:D,C15),0) -> 76124.436 | F15: =IFERROR(SUMIFS(Fonte_Dati!H:H,Fonte_Dati!D:D,C15),0) -> -159.66031 | G15: =IFERROR(SUMIFS(Fonte_Dati!I:I,Fonte_Dati!D:D,C15),0) -> 75964.775 | H15: =IFERROR(G15*0.08,0) -> 6077.182 | I15: =IFERROR(G15-H15,0) -> 69887.593 | J15: =IFERROR(I15/G15,0) -> 0.92 | K15: =IFERROR(SUMIFS(Fonte_Dati!I:I,Fonte_Dati!D:D,C15)/SUMIFS(Fonte_Dati!F:F,Fonte_Dati!D:D,C15)*1000,0) -> 95.157993 | L15: =IFERROR(SUMIF('💹 Incentivi'!D8:D23,"*Narbone*",'💹 Incentivi'!R8:R23),0) -> 1146908.8 | M15: =IFERROR(SUMIF('💹 Incentivi'!D28:D43,"*Narbone*",'💹 Incentivi'!R28:R43),0) -> 418280.79 | N15: =IFERROR(I15+M15,"") -> 488168.38 | O15: =IFERROR(N15/(G15+M15),"") -> 0.98770412
B16: 9 | C16: FV-Perniciara | D16: Fotovoltaico | E16: =IFERROR(SUMIFS(Fonte_Dati!G:G,Fonte_Dati!D:D,C16),0) -> 50858.787 | F16: =IFERROR(SUMIFS(Fonte_Dati!H:H,Fonte_Dati!D:D,C16),0) -> -106.68182 | G16: =IFERROR(SUMIFS(Fonte_Dati!I:I,Fonte_Dati!D:D,C16),0) -> 50752.105 | H16: =IFERROR(G16*0.08,0) -> 4060.1684 | I16: =IFERROR(G16-H16,0) -> 46691.937 | J16: =IFERROR(I16/G16,0) -> 0.92 | K16: =IFERROR(SUMIFS(Fonte_Dati!I:I,Fonte_Dati!D:D,C16)/SUMIFS(Fonte_Dati!F:F,Fonte_Dati!D:D,C16)*1000,0) -> 95.146684 | L16: =IFERROR(SUMIF('💹 Incentivi'!D8:D23,"*Perniciara*",'💹 Incentivi'!R8:R23),0) -> 0 | M16: =IFERROR(SUMIF('💹 Incentivi'!D28:D43,"*Perniciara*",'💹 Incentivi'!R28:R43),0) -> 0 | N16: =IFERROR(I16+M16,"") -> 46691.937 | O16: =IFERROR(N16/(G16+M16),"") -> 0.92
B17: 10 | C17: FV-Serre Gela | D17: Fotovoltaico | E17: =IFERROR(SUMIFS(Fonte_Dati!G:G,Fonte_Dati!D:D,C17),0) -> 46577.793 | F17: =IFERROR(SUMIFS(Fonte_Dati!H:H,Fonte_Dati!D:D,C17),0) -> -97.58726 | G17: =IFERROR(SUMIFS(Fonte_Dati!I:I,Fonte_Dati!D:D,C17),0) -> 46480.205 | H17: =IFERROR(G17*0.08,0) -> 3718.4164 | I17: =IFERROR(G17-H17,0) -> 42761.789 | J17: =IFERROR(I17/G17,0) -> 0.92 | K17: =IFERROR(SUMIFS(Fonte_Dati!I:I,Fonte_Dati!D:D,C17)/SUMIFS(Fonte_Dati!F:F,Fonte_Dati!D:D,C17)*1000,0) -> 95.258757 | L17: =IFERROR(SUMIF('💹 Incentivi'!D8:D23,"*Gela*",'💹 Incentivi'!R8:R23),0) -> 343824.57 | M17: =IFERROR(SUMIF('💹 Incentivi'!D28:D43,"*Gela*",'💹 Incentivi'!R28:R43),0) -> 138878.39 | N17: =IFERROR(I17+M17,"") -> 181640.18 | O17: =IFERROR(N17/(G17+M17),"") -> 0.97993934
B18: 11 | C18: FV-Malvizzo Piccolo | D18: Fotovoltaico | E18: =IFERROR(SUMIFS(Fonte_Dati!G:G,Fonte_Dati!D:D,C18),0) -> 29734.277 | F18: =IFERROR(SUMIFS(Fonte_Dati!H:H,Fonte_Dati!D:D,C18),0) -> -64.974224 | G18: =IFERROR(SUMIFS(Fonte_Dati!I:I,Fonte_Dati!D:D,C18),0) -> 29669.302 | H18: =IFERROR(G18*0.08,0) -> 2373.5442 | I18: =IFERROR(G18-H18,0) -> 27295.758 | J18: =IFERROR(I18/G18,0) -> 0.92 | K18: =IFERROR(SUMIFS(Fonte_Dati!I:I,Fonte_Dati!D:D,C18)/SUMIFS(Fonte_Dati!F:F,Fonte_Dati!D:D,C18)*1000,0) -> 91.326377 | L18: =IFERROR(SUMIF('💹 Incentivi'!D8:D23,"*Malvizzo*",'💹 Incentivi'!R8:R23),0) -> 243603.03 | M18: =IFERROR(SUMIF('💹 Incentivi'!D28:D43,"*Malvizzo*",'💹 Incentivi'!R28:R43),0) -> 82537.585 | N18: =IFERROR(I18+M18,"") -> 109833.34 | O18: =IFERROR(N18/(G18+M18),"") -> 0.97884672
B19: 12 | C19: FV-Malvizzo a Terra | D19: Fotovoltaico | E19: =IFERROR(SUMIFS(Fonte_Dati!G:G,Fonte_Dati!D:D,C19),0) -> 29047.258 | F19: =IFERROR(SUMIFS(Fonte_Dati!H:H,Fonte_Dati!D:D,C19),0) -> -63.839026 | G19: =IFERROR(SUMIFS(Fonte_Dati!I:I,Fonte_Dati!D:D,C19),0) -> 28983.419 | H19: =IFERROR(G19*0.08,0) -> 2318.6735 | I19: =IFERROR(G19-H19,0) -> 26664.745 | J19: =IFERROR(I19/G19,0) -> 0.92 | K19: =IFERROR(SUMIFS(Fonte_Dati!I:I,Fonte_Dati!D:D,C19)/SUMIFS(Fonte_Dati!F:F,Fonte_Dati!D:D,C19)*1000,0) -> 90.80157 | L19: =IFERROR(SUMIF('💹 Incentivi'!D8:D23,"*Malvizzo a Terra*",'💹 Incentivi'!R8:R23),0) -> 243603.03 | M19: =IFERROR(SUMIF('💹 Incentivi'!D28:D43,"*Malvizzo a Terra*",'💹 Incentivi'!R28:R43),0) -> 82537.585 | N19: =IFERROR(I19+M19,"") -> 109202.33 | O19: =IFERROR(N19/(G19+M19),"") -> 0.97920864
B20: 13 | C20: FV-Narbone a Terra Grande | D20: Fotovoltaico | E20: =IFERROR(SUMIFS(Fonte_Dati!G:G,Fonte_Dati!D:D,C20),0) -> 8742.4718 | F20: =IFERROR(SUMIFS(Fonte_Dati!H:H,Fonte_Dati!D:D,C20),0) -> -15.17708 | G20: =IFERROR(SUMIFS(Fonte_Dati!I:I,Fonte_Dati!D:D,C20),0) -> 8727.2947 | H20: =IFERROR(G20*0.08,0) -> 698.18358 | I20: =IFERROR(G20-H20,0) -> 8029.1111 | J20: =IFERROR(I20/G20,0) -> 0.92 | K20: =IFERROR(SUMIFS(Fonte_Dati!I:I,Fonte_Dati!D:D,C20)/SUMIFS(Fonte_Dati!F:F,Fonte_Dati!D:D,C20)*1000,0) -> 115.00624 | L20: =IFERROR(SUMIF('💹 Incentivi'!D8:D23,"*Narbone a Terra*",'💹 Incentivi'!R8:R23),0) -> 168704.66 | M20: =IFERROR(SUMIF('💹 Incentivi'!D28:D43,"*Narbone a Terra*",'💹 Incentivi'!R28:R43),0) -> 24935.823 | N20: =IFERROR(I20+M20,"") -> 32964.934 | O20: =IFERROR(N20/(G20+M20),"") -> 0.97925969
B21: 14 | C21: FV-Narbone Piccolo | D21: Fotovoltaico | E21: =IFERROR(SUMIFS(Fonte_Dati!G:G,Fonte_Dati!D:D,C21),0) -> 7402.499 | F21: =IFERROR(SUMIFS(Fonte_Dati!H:H,Fonte_Dati!D:D,C21),0) -> -15.640495 | G21: =IFERROR(SUMIFS(Fonte_Dati!I:I,Fonte_Dati!D:D,C21),0) -> 7386.8585 | H21: =IFERROR(G21*0.08,0) -> 590.94868 | I21: =IFERROR(G21-H21,0) -> 6795.9098 | J21: =IFERROR(I21/G21,0) -> 0.92 | K21: =IFERROR(SUMIFS(Fonte_Dati!I:I,Fonte_Dati!D:D,C21)/SUMIFS(Fonte_Dati!F:F,Fonte_Dati!D:D,C21)*1000,0) -> 94.458118 | L21: =IFERROR(SUMIF('💹 Incentivi'!D8:D23,"*Narbone Piccolo*",'💹 Incentivi'!R8:R23),0) -> 0 | M21: =IFERROR(SUMIF('💹 Incentivi'!D28:D43,"*Narbone Piccolo*",'💹 Incentivi'!R28:R43),0) -> 0 | N21: =IFERROR(I21+M21,"") -> 6795.9098 | O21: =IFERROR(N21/(G21+M21),"") -> 0.92
B22: 15 | C22: FV-Campofranco Tetto | D22: Fotovoltaico | E22: =IFERROR(SUMIFS(Fonte_Dati!G:G,Fonte_Dati!D:D,C22),0) -> 6636.8041 | F22: =IFERROR(SUMIFS(Fonte_Dati!H:H,Fonte_Dati!D:D,C22),0) -> -14.465613 | G22: =IFERROR(SUMIFS(Fonte_Dati!I:I,Fonte_Dati!D:D,C22),0) -> 6622.3385 | H22: =IFERROR(G22*0.08,0) -> 529.78708 | I22: =IFERROR(G22-H22,0) -> 6092.5514 | J22: =IFERROR(I22/G22,0) -> 0.92 | K22: =IFERROR(SUMIFS(Fonte_Dati!I:I,Fonte_Dati!D:D,C22)/SUMIFS(Fonte_Dati!F:F,Fonte_Dati!D:D,C22)*1000,0) -> 91.559736 | L22: =IFERROR(SUMIF('💹 Incentivi'!D8:D23,"*Campofranco*",'💹 Incentivi'!R8:R23),0) -> 99855.048 | M22: =IFERROR(SUMIF('💹 Incentivi'!D28:D43,"*Campofranco*",'💹 Incentivi'!R28:R43),0) -> 39361.299 | N22: =IFERROR(I22+M22,"") -> 45453.851 | O22: =IFERROR(N22/(G22+M22),"") -> 0.98847879
B23: 16 | C23: FV-Tumarrano MEG | D23: Fotovoltaico | E23: =IFERROR(SUMIFS(Fonte_Dati!G:G,Fonte_Dati!D:D,C23),0) -> 1828.9881 | F23: =IFERROR(SUMIFS(Fonte_Dati!H:H,Fonte_Dati!D:D,C23),0) -> -3.9214086 | G23: =IFERROR(SUMIFS(Fonte_Dati!I:I,Fonte_Dati!D:D,C23),0) -> 1825.0667 | H23: =IFERROR(G23*0.08,0) -> 146.00533 | I23: =IFERROR(G23-H23,0) -> 1679.0613 | J23: =IFERROR(I23/G23,0) -> 0.92 | K23: =IFERROR(SUMIFS(Fonte_Dati!I:I,Fonte_Dati!D:D,C23)/SUMIFS(Fonte_Dati!F:F,Fonte_Dati!D:D,C23)*1000,0) -> 93.082199 | L23: =IFERROR(SUMIF('💹 Incentivi'!D8:D23,"*Tumarrano*",'💹 Incentivi'!R8:R23),0) -> 5264.1805 | M23: =IFERROR(SUMIF('💹 Incentivi'!D28:D43,"*Tumarrano*",'💹 Incentivi'!R28:R43),0) -> 21633.913 | N23: =IFERROR(I23+M23,"") -> 23312.975 | O23: =IFERROR(N23/(G23+M23),"") -> 0.99377614
B24: TOTALE PORTFOLIO | E24: =SUM(E8:E23) -> 3133013.1 | F24: =SUM(F8:F23) -> -5784.8357 | G24: =SUM(G8:G23) -> 3127228.3 | H24: =SUM(H8:H23) -> 250178.26 | I24: =SUM(I8:I23) -> 2877050 | J24: =IFERROR(I24/G24,0) -> 0.92 | K24: =IFERROR(G24/E24,0) -> 0.99815359 | L24: =SUM(L8:L23) -> 4597508.5 | M24: =SUM(M8:M23) -> 1704958.9 | N24: =SUM(N8:N23) -> 4582008.9 | O24: =IFERROR(N24/(G24+M24),0) -> 0.9482267
B26: RIEPILOGO MENSILE — FATTURATO NETTO (€) + INCENTIVI GSE
B27: ID | C27: Impianto | D27: Tipo | E27: Gennaio 2026 | F27: Febbraio 2026 | G27: Marzo 2026 | H27: Totale Q1 | I27: Var Feb/Gen | J27: Var % | K27: EUR/MWh Q1 | L27: Acc.Inc. Gen (€) | M27: Acc.Inc. Feb (€) | N27: Acc.Inc. Mar (€) | O27: Cons.Inc. Gen (€) | P27: Cons.Inc. Feb (€) | Q27: Cons.Inc. Mar (€) | R27: Tot.Cons. Inc. Q1
B28: 1 | C28: Wind - Monte Narbone | D28: Eolico | E28: =IFERROR(SUMIFS(Fonte_Dati!I:I,Fonte_Dati!D:D,C28,Fonte_Dati!C:C,"Gennaio"),0) -> 588427.8 | F28: =IFERROR(SUMIFS(Fonte_Dati!I:I,Fonte_Dati!D:D,C28,Fonte_Dati!C:C,"Febbraio"),0) -> 452327.04 | G28: =IFERROR(SUMIFS(Fonte_Dati!I:I,Fonte_Dati!D:D,C28,Fonte_Dati!C:C,"Marzo"),0) -> 43.243264 | H28: =IFERROR(SUM(E28:G28),0) -> 1040798.1 | I28: =IFERROR(F28-E28,"") -> -136100.76 | J28: =IFERROR((F28-E28)/E28,"") -> -0.23129559 | K28: =IFERROR(SUMIFS(Fonte_Dati!I:I,Fonte_Dati!D:D,C28)/SUMIFS(Fonte_Dati!F:F,Fonte_Dati!D:D,C28)*1000,0) -> 114.4208 | L28: =IFERROR(SUMIF('💹 Incentivi'!D8:D23,"*Narbone*",'💹 Incentivi'!F8:F23),0) -> 382302.94 | M28: =IFERROR(SUMIF('💹 Incentivi'!D8:D23,"*Narbone*",'💹 Incentivi'!G8:G23),0) -> 382302.94 | N28: =IFERROR(SUMIF('💹 Incentivi'!D8:D23,"*Narbone*",'💹 Incentivi'!H8:H23),0) -> 382302.94 | O28: =IFERROR(SUMIF('💹 Incentivi'!D28:D43,"*Narbone*",'💹 Incentivi'!F28:F43),0) -> 198419.79 | P28: =IFERROR(SUMIF('💹 Incentivi'!D28:D43,"*Narbone*",'💹 Incentivi'!G28:G43),0) -> 219861 | Q28: =IFERROR(SUMIF('💹 Incentivi'!D28:D43,"*Narbone*",'💹 Incentivi'!H28:H43),0) -> 0 | R28: =IFERROR(SUM(O28:Q28),0) -> 418280.79
B29: 2 | C29: Wind - Monte Durrà | D29: Eolico | E29: =IFERROR(SUMIFS(Fonte_Dati!I:I,Fonte_Dati!D:D,C29,Fonte_Dati!C:C,"Gennaio"),0) -> 480407.1 | F29: =IFERROR(SUMIFS(Fonte_Dati!I:I,Fonte_Dati!D:D,C29,Fonte_Dati!C:C,"Febbraio"),0) -> 426403.7 | G29: =IFERROR(SUMIFS(Fonte_Dati!I:I,Fonte_Dati!D:D,C29,Fonte_Dati!C:C,"Marzo"),0) -> 0 | H29: =IFERROR(SUM(E29:G29),0) -> 906810.8 | I29: =IFERROR(F29-E29,"") -> -54003.393 | J29: =IFERROR((F29-E29)/E29,"") -> -0.11241173 | K29: =IFERROR(SUMIFS(Fonte_Dati!I:I,Fonte_Dati!D:D,C29)/SUMIFS(Fonte_Dati!F:F,Fonte_Dati!D:D,C29)*1000,0) -> 111.85094 | L29: =IFERROR(SUMIF('💹 Incentivi'!D8:D23,"*Durr*",'💹 Incentivi'!F8:F23),0) -> 0 | M29: =IFERROR(SUMIF('💹 Incentivi'!D8:D23,"*Durr*",'💹 Incentivi'!G8:G23),0) -> 0 | N29: =IFERROR(SUMIF('💹 Incentivi'!D8:D23,"*Durr*",'💹 Incentivi'!H8:H23),0) -> 0 | O29: =IFERROR(SUMIF('💹 Incentivi'!D28:D43,"*Durr*",'💹 Incentivi'!F28:F43),0) -> 0 | P29: =IFERROR(SUMIF('💹 Incentivi'!D28:D43,"*Durr*",'💹 Incentivi'!G28:G43),0) -> 0 | Q29: =IFERROR(SUMIF('💹 Incentivi'!D28:D43,"*Durr*",'💹 Incentivi'!H28:H43),0) -> 0 | R29: =IFERROR(SUM(O29:Q29),0) -> 0
B30: 3 | C30: Wind - Monte Malvizzo | D30: Eolico | E30: =IFERROR(SUMIFS(Fonte_Dati!I:I,Fonte_Dati!D:D,C30,Fonte_Dati!C:C,"Gennaio"),0) -> 226960.12 | F30: =IFERROR(SUMIFS(Fonte_Dati!I:I,Fonte_Dati!D:D,C30,Fonte_Dati!C:C,"Febbraio"),0) -> 217191.86 | G30: =IFERROR(SUMIFS(Fonte_Dati!I:I,Fonte_Dati!D:D,C30,Fonte_Dati!C:C,"Marzo"),0) -> 114.50981 | H30: =IFERROR(SUM(E30:G30),0) -> 444266.5 | I30: =IFERROR(F30-E30,"") -> -9768.2603 | J30: =IFERROR((F30-E30)/E30,"") -> -0.043039544 | K30: =IFERROR(SUMIFS(Fonte_Dati!I:I,Fonte_Dati!D:D,C30)/SUMIFS(Fonte_Dati!F:F,Fonte_Dati!D:D,C30)*1000,0) -> 112.61287 | L30: =IFERROR(SUMIF('💹 Incentivi'!D8:D23,"*Malvizzo*",'💹 Incentivi'!F8:F23),0) -> 81201.01 | M30: =IFERROR(SUMIF('💹 Incentivi'!D8:D23,"*Malvizzo*",'💹 Incentivi'!G8:G23),0) -> 81201.01 | N30: =IFERROR(SUMIF('💹 Incentivi'!D8:D23,"*Malvizzo*",'💹 Incentivi'!H8:H23),0) -> 81201.01 | O30: =IFERROR(SUMIF('💹 Incentivi'!D28:D43,"*Malvizzo*",'💹 Incentivi'!F28:F43),0) -> 28936.51 | P30: =IFERROR(SUMIF('💹 Incentivi'!D28:D43,"*Malvizzo*",'💹 Incentivi'!G28:G43),0) -> 53601.075 | Q30: =IFERROR(SUMIF('💹 Incentivi'!D28:D43,"*Malvizzo*",'💹 Incentivi'!H28:H43),0) -> 0 | R30: =IFERROR(SUM(O30:Q30),0) -> 82537.585
B31: 4 | C31: FV-Favara Grande | D31: Fotovoltaico | E31: =IFERROR(SUMIFS(Fonte_Dati!I:I,Fonte_Dati!D:D,C31,Fonte_Dati!C:C,"Gennaio"),0) -> 76630.904 | F31: =IFERROR(SUMIFS(Fonte_Dati!I:I,Fonte_Dati!D:D,C31,Fonte_Dati!C:C,"Febbraio"),0) -> 73459.825 | G31: =IFERROR(SUMIFS(Fonte_Dati!I:I,Fonte_Dati!D:D,C31,Fonte_Dati!C:C,"Marzo"),0) -> 0 | H31: =IFERROR(SUM(E31:G31),0) -> 150090.73 | I31: =IFERROR(F31-E31,"") -> -3171.0785 | J31: =IFERROR((F31-E31)/E31,"") -> -0.041381196 | K31: =IFERROR(SUMIFS(Fonte_Dati!I:I,Fonte_Dati!D:D,C31)/SUMIFS(Fonte_Dati!F:F,Fonte_Dati!D:D,C31)*1000,0) -> 95.010406 | L31: =IFERROR(SUMIF('💹 Incentivi'!D8:D23,"*Favara*",'💹 Incentivi'!F8:F23),0) -> 0 | M31: =IFERROR(SUMIF('💹 Incentivi'!D8:D23,"*Favara*",'💹 Incentivi'!G8:G23),0) -> 0 | N31: =IFERROR(SUMIF('💹 Incentivi'!D8:D23,"*Favara*",'💹 Incentivi'!H8:H23),0) -> 0 | O31: =IFERROR(SUMIF('💹 Incentivi'!D28:D43,"*Favara*",'💹 Incentivi'!F28:F43),0) -> 0 | P31: =IFERROR(SUMIF('💹 Incentivi'!D28:D43,"*Favara*",'💹 Incentivi'!G28:G43),0) -> 0 | Q31: =IFERROR(SUMIF('💹 Incentivi'!D28:D43,"*Favara*",'💹 Incentivi'!H28:H43),0) -> 0 | R31: =IFERROR(SUM(O31:Q31),0) -> 0
B32: 5 | C32: FV-Fauma Tetto | D32: Fotovoltaico | E32: =IFERROR(SUMIFS(Fonte_Dati!I:I,Fonte_Dati!D:D,C32,Fonte_Dati!C:C,"Gennaio"),0) -> 79034.914 | F32: =IFERROR(SUMIFS(Fonte_Dati!I:I,Fonte_Dati!D:D,C32,Fonte_Dati!C:C,"Febbraio"),0) -> 69014.085 | G32: =IFERROR(SUMIFS(Fonte_Dati!I:I,Fonte_Dati!D:D,C32,Fonte_Dati!C:C,"Marzo"),0) -> 0 | H32: =IFERROR(SUM(E32:G32),0) -> 148049 | I32: =IFERROR(F32-E32,"") -> -10020.829 | J32: =IFERROR((F32-E32)/E32,"") -> -0.1267899 | K32: =IFERROR(SUMIFS(Fonte_Dati!I:I,Fonte_Dati!D:D,C32)/SUMIFS(Fonte_Dati!F:F,Fonte_Dati!D:D,C32)*1000,0) -> 96.226018 | L32: =IFERROR(SUMIF('💹 Incentivi'!D8:D23,"*Fauma*",'💹 Incentivi'!F8:F23),0) -> 0 | M32: =IFERROR(SUMIF('💹 Incentivi'!D8:D23,"*Fauma*",'💹 Incentivi'!G8:G23),0) -> 0 | N32: =IFERROR(SUMIF('💹 Incentivi'!D8:D23,"*Fauma*",'💹 Incentivi'!H8:H23),0) -> 0 | O32: =IFERROR(SUMIF('💹 Incentivi'!D28:D43,"*Fauma*",'💹 Incentivi'!F28:F43),0) -> 0 | P32: =IFERROR(SUMIF('💹 Incentivi'!D28:D43,"*Fauma*",'💹 Incentivi'!G28:G43),0) -> 0 | Q32: =IFERROR(SUMIF('💹 Incentivi'!D28:D43,"*Fauma*",'💹 Incentivi'!H28:H43),0) -> 0 | R32: =IFERROR(SUM(O32:Q32),0) -> 0
B33: 6 | C33: FV-Batia S. Francesco | D33: Fotovoltaico | E33: =IFERROR(SUMIFS(Fonte_Dati!I:I,Fonte_Dati!D:D,C33,Fonte_Dati!C:C,"Gennaio"),0) -> 47349.213 | F33: =IFERROR(SUMIFS(Fonte_Dati!I:I,Fonte_Dati!D:D,C33,Fonte_Dati!C:C,"Febbraio"),0) -> 55932.925 | G33: =IFERROR(SUMIFS(Fonte_Dati!I:I,Fonte_Dati!D:D,C33,Fonte_Dati!C:C,"Marzo"),0) -> 0 | H33: =IFERROR(SUM(E33:G33),0) -> 103282.14 | I33: =IFERROR(F33-E33,"") -> 8583.7119 | J33: =IFERROR((F33-E33)/E33,"") -> 0.18128521 | K33: =IFERROR(SUMIFS(Fonte_Dati!I:I,Fonte_Dati!D:D,C33)/SUMIFS(Fonte_Dati!F:F,Fonte_Dati!D:D,C33)*1000,0) -> 90.415876 | L33: =IFERROR(SUMIF('💹 Incentivi'!D8:D23,"*Batia*",'💹 Incentivi'!F8:F23),0) -> 109614.08 | M33: =IFERROR(SUMIF('💹 Incentivi'!D8:D23,"*Batia*",'💹 Incentivi'!G8:G23),0) -> 109614.08 | N33: =IFERROR(SUMIF('💹 Incentivi'!D8:D23,"*Batia*",'💹 Incentivi'!H8:H23),0) -> 109614.08 | O33: =IFERROR(SUMIF('💹 Incentivi'!D28:D43,"*Batia*",'💹 Incentivi'!F28:F43),0) -> 50249.214 | P33: =IFERROR(SUMIF('💹 Incentivi'!D28:D43,"*Batia*",'💹 Incentivi'!G28:G43),0) -> 88825.489 | Q33: =IFERROR(SUMIF('💹 Incentivi'!D28:D43,"*Batia*",'💹 Incentivi'!H28:H43),0) -> 0 | R33: =IFERROR(SUM(O33:Q33),0) -> 139074.7
B34: 7 | C34: FV-Serre S.Angelo Muxaro | D34: Fotovoltaico | E34: =IFERROR(SUMIFS(Fonte_Dati!I:I,Fonte_Dati!D:D,C34,Fonte_Dati!C:C,"Gennaio"),0) -> 43207.313 | F34: =IFERROR(SUMIFS(Fonte_Dati!I:I,Fonte_Dati!D:D,C34,Fonte_Dati!C:C,"Febbraio"),0) -> 34312.372 | G34: =IFERROR(SUMIFS(Fonte_Dati!I:I,Fonte_Dati!D:D,C34,Fonte_Dati!C:C,"Marzo"),0) -> 0 | H34: =IFERROR(SUM(E34:G34),0) -> 77519.685 | I34: =IFERROR(F34-E34,"") -> -8894.9409 | J34: =IFERROR((F34-E34)/E34,"") -> -0.20586656 | K34: =IFERROR(SUMIFS(Fonte_Dati!I:I,Fonte_Dati!D:D,C34)/SUMIFS(Fonte_Dati!F:F,Fonte_Dati!D:D,C34)*1000,0) -> 96.26986 | L34: =IFERROR(SUMIF('💹 Incentivi'!D8:D23,"*Muxaro*",'💹 Incentivi'!F8:F23),0) -> 208797.04 | M34: =IFERROR(SUMIF('💹 Incentivi'!D8:D23,"*Muxaro*",'💹 Incentivi'!G8:G23),0) -> 208797.04 | N34: =IFERROR(SUMIF('💹 Incentivi'!D8:D23,"*Muxaro*",'💹 Incentivi'!H8:H23),0) -> 208797.04 | O34: =IFERROR(SUMIF('💹 Incentivi'!D28:D43,"*Muxaro*",'💹 Incentivi'!F28:F43),0) -> 116538.4 | P34: =IFERROR(SUMIF('💹 Incentivi'!D28:D43,"*Muxaro*",'💹 Incentivi'!G28:G43),0) -> 140362.02 | Q34: =IFERROR(SUMIF('💹 Incentivi'!D28:D43,"*Muxaro*",'💹 Incentivi'!H28:H43),0) -> 0 | R34: =IFERROR(SUM(O34:Q34),0) -> 256900.42
B35: 8 | C35: FV-Serre Narbone | D35: Fotovoltaico | E35: =IFERROR(SUMIFS(Fonte_Dati!I:I,Fonte_Dati!D:D,C35,Fonte_Dati!C:C,"Gennaio"),0) -> 41510.92 | F35: =IFERROR(SUMIFS(Fonte_Dati!I:I,Fonte_Dati!D:D,C35,Fonte_Dati!C:C,"Febbraio"),0) -> 34453.855 | G35: =IFERROR(SUMIFS(Fonte_Dati!I:I,Fonte_Dati!D:D,C35,Fonte_Dati!C:C,"Marzo"),0) -> 0 | H35: =IFERROR(SUM(E35:G35),0) -> 75964.775 | I35: =IFERROR(F35-E35,"") -> -7057.0648 | J35: =IFERROR((F35-E35)/E35,"") -> -0.17000502 | K35: =IFERROR(SUMIFS(Fonte_Dati!I:I,Fonte_Dati!D:D,C35)/SUMIFS(Fonte_Dati!F:F,Fonte_Dati!D:D,C35)*1000,0) -> 95.157993 | L35: =IFERROR(SUMIF('💹 Incentivi'!D8:D23,"*Narbone*",'💹 Incentivi'!F8:F23),0) -> 382302.94 | M35: =IFERROR(SUMIF('💹 Incentivi'!D8:D23,"*Narbone*",'💹 Incentivi'!G8:G23),0) -> 382302.94 | N35: =IFERROR(SUMIF('💹 Incentivi'!D8:D23,"*Narbone*",'💹 Incentivi'!H8:H23),0) -> 382302.94 | O35: =IFERROR(SUMIF('💹 Incentivi'!D28:D43,"*Narbone*",'💹 Incentivi'!F28:F43),0) -> 198419.79 | P35: =IFERROR(SUMIF('💹 Incentivi'!D28:D43,"*Narbone*",'💹 Incentivi'!G28:G43),0) -> 219861 | Q35: =IFERROR(SUMIF('💹 Incentivi'!D28:D43,"*Narbone*",'💹 Incentivi'!H28:H43),0) -> 0 | R35: =IFERROR(SUM(O35:Q35),0) -> 418280.79
B36: 9 | C36: FV-Perniciara | D36: Fotovoltaico | E36: =IFERROR(SUMIFS(Fonte_Dati!I:I,Fonte_Dati!D:D,C36,Fonte_Dati!C:C,"Gennaio"),0) -> 25588.212 | F36: =IFERROR(SUMIFS(Fonte_Dati!I:I,Fonte_Dati!D:D,C36,Fonte_Dati!C:C,"Febbraio"),0) -> 25163.893 | G36: =IFERROR(SUMIFS(Fonte_Dati!I:I,Fonte_Dati!D:D,C36,Fonte_Dati!C:C,"Marzo"),0) -> 0 | H36: =IFERROR(SUM(E36:G36),0) -> 50752.105 | I36: =IFERROR(F36-E36,"") -> -424.31832 | J36: =IFERROR((F36-E36)/E36,"") -> -0.01658257 | K36: =IFERROR(SUMIFS(Fonte_Dati!I:I,Fonte_Dati!D:D,C36)/SUMIFS(Fonte_Dati!F:F,Fonte_Dati!D:D,C36)*1000,0) -> 95.146684 | L36: =IFERROR(SUMIF('💹 Incentivi'!D8:D23,"*Perniciara*",'💹 Incentivi'!F8:F23),0) -> 0 | M36: =IFERROR(SUMIF('💹 Incentivi'!D8:D23,"*Perniciara*",'💹 Incentivi'!G8:G23),0) -> 0 | N36: =IFERROR(SUMIF('💹 Incentivi'!D8:D23,"*Perniciara*",'💹 Incentivi'!H8:H23),0) -> 0 | O36: =IFERROR(SUMIF('💹 Incentivi'!D28:D43,"*Perniciara*",'💹 Incentivi'!F28:F43),0) -> 0 | P36: =IFERROR(SUMIF('💹 Incentivi'!D28:D43,"*Perniciara*",'💹 Incentivi'!G28:G43),0) -> 0 | Q36: =IFERROR(SUMIF('💹 Incentivi'!D28:D43,"*Perniciara*",'💹 Incentivi'!H28:H43),0) -> 0 | R36: =IFERROR(SUM(O36:Q36),0) -> 0
B37: 10 | C37: FV-Serre Gela | D37: Fotovoltaico | E37: =IFERROR(SUMIFS(Fonte_Dati!I:I,Fonte_Dati!D:D,C37,Fonte_Dati!C:C,"Gennaio"),0) -> 23980.648 | F37: =IFERROR(SUMIFS(Fonte_Dati!I:I,Fonte_Dati!D:D,C37,Fonte_Dati!C:C,"Febbraio"),0) -> 22499.557 | G37: =IFERROR(SUMIFS(Fonte_Dati!I:I,Fonte_Dati!D:D,C37,Fonte_Dati!C:C,"Marzo"),0) -> 0 | H37: =IFERROR(SUM(E37:G37),0) -> 46480.205 | I37: =IFERROR(F37-E37,"") -> -1481.0913 | J37: =IFERROR((F37-E37)/E37,"") -> -0.061761937 | K37: =IFERROR(SUMIFS(Fonte_Dati!I:I,Fonte_Dati!D:D,C37)/SUMIFS(Fonte_Dati!F:F,Fonte_Dati!D:D,C37)*1000,0) -> 95.258757 | L37: =IFERROR(SUMIF('💹 Incentivi'!D8:D23,"*Gela*",'💹 Incentivi'!F8:F23),0) -> 114608.19 | M37: =IFERROR(SUMIF('💹 Incentivi'!D8:D23,"*Gela*",'💹 Incentivi'!G8:G23),0) -> 114608.19 | N37: =IFERROR(SUMIF('💹 Incentivi'!D8:D23,"*Gela*",'💹 Incentivi'!H8:H23),0) -> 114608.19 | O37: =IFERROR(SUMIF('💹 Incentivi'!D28:D43,"*Gela*",'💹 Incentivi'!F28:F43),0) -> 58189.505 | P37: =IFERROR(SUMIF('💹 Incentivi'!D28:D43,"*Gela*",'💹 Incentivi'!G28:G43),0) -> 80688.886 | Q37: =IFERROR(SUMIF('💹 Incentivi'!D28:D43,"*Gela*",'💹 Incentivi'!H28:H43),0) -> 0 | R37: =IFERROR(SUM(O37:Q37),0) -> 138878.39
B38: 11 | C38: FV-Malvizzo Piccolo | D38: Fotovoltaico | E38: =IFERROR(SUMIFS(Fonte_Dati!I:I,Fonte_Dati!D:D,C38,Fonte_Dati!C:C,"Gennaio"),0) -> 12258.194 | F38: =IFERROR(SUMIFS(Fonte_Dati!I:I,Fonte_Dati!D:D,C38,Fonte_Dati!C:C,"Febbraio"),0) -> 17411.108 | G38: =IFERROR(SUMIFS(Fonte_Dati!I:I,Fonte_Dati!D:D,C38,Fonte_Dati!C:C,"Marzo"),0) -> 0 | H38: =IFERROR(SUM(E38:G38),0) -> 29669.302 | I38: =IFERROR(F38-E38,"") -> 5152.9138 | J38: =IFERROR((F38-E38)/E38,"") -> 0.42036483 | K38: =IFERROR(SUMIFS(Fonte_Dati!I:I,Fonte_Dati!D:D,C38)/SUMIFS(Fonte_Dati!F:F,Fonte_Dati!D:D,C38)*1000,0) -> 91.326377 | L38: =IFERROR(SUMIF('💹 Incentivi'!D8:D23,"*Malvizzo*",'💹 Incentivi'!F8:F23),0) -> 81201.01 | M38: =IFERROR(SUMIF('💹 Incentivi'!D8:D23,"*Malvizzo*",'💹 Incentivi'!G8:G23),0) -> 81201.01 | N38: =IFERROR(SUMIF('💹 Incentivi'!D8:D23,"*Malvizzo*",'💹 Incentivi'!H8:H23),0) -> 81201.01 | O38: =IFERROR(SUMIF('💹 Incentivi'!D28:D43,"*Malvizzo*",'💹 Incentivi'!F28:F43),0) -> 28936.51 | P38: =IFERROR(SUMIF('💹 Incentivi'!D28:D43,"*Malvizzo*",'💹 Incentivi'!G28:G43),0) -> 53601.075 | Q38: =IFERROR(SUMIF('💹 Incentivi'!D28:D43,"*Malvizzo*",'💹 Incentivi'!H28:H43),0) -> 0 | R38: =IFERROR(SUM(O38:Q38),0) -> 82537.585
B39: 12 | C39: FV-Malvizzo a Terra | D39: Fotovoltaico | E39: =IFERROR(SUMIFS(Fonte_Dati!I:I,Fonte_Dati!D:D,C39,Fonte_Dati!C:C,"Gennaio"),0) -> 12177.335 | F39: =IFERROR(SUMIFS(Fonte_Dati!I:I,Fonte_Dati!D:D,C39,Fonte_Dati!C:C,"Febbraio"),0) -> 16806.084 | G39: =IFERROR(SUMIFS(Fonte_Dati!I:I,Fonte_Dati!D:D,C39,Fonte_Dati!C:C,"Marzo"),0) -> 0 | H39: =IFERROR(SUM(E39:G39),0) -> 28983.419 | I39: =IFERROR(F39-E39,"") -> 4628.7489 | J39: =IFERROR((F39-E39)/E39,"") -> 0.38011181 | K39: =IFERROR(SUMIFS(Fonte_Dati!I:I,Fonte_Dati!D:D,C39)/SUMIFS(Fonte_Dati!F:F,Fonte_Dati!D:D,C39)*1000,0) -> 90.80157 | L39: =IFERROR(SUMIF('💹 Incentivi'!D8:D23,"*Malvizzo a Terra*",'💹 Incentivi'!F8:F23),0) -> 81201.01 | M39: =IFERROR(SUMIF('💹 Incentivi'!D8:D23,"*Malvizzo a Terra*",'💹 Incentivi'!G8:G23),0) -> 81201.01 | N39: =IFERROR(SUMIF('💹 Incentivi'!D8:D23,"*Malvizzo a Terra*",'💹 Incentivi'!H8:H23),0) -> 81201.01 | O39: =IFERROR(SUMIF('💹 Incentivi'!D28:D43,"*Malvizzo a Terra*",'💹 Incentivi'!F28:F43),0) -> 28936.51 | P39: =IFERROR(SUMIF('💹 Incentivi'!D28:D43,"*Malvizzo a Terra*",'💹 Incentivi'!G28:G43),0) -> 53601.075 | Q39: =IFERROR(SUMIF('💹 Incentivi'!D28:D43,"*Malvizzo a Terra*",'💹 Incentivi'!H28:H43),0) -> 0 | R39: =IFERROR(SUM(O39:Q39),0) -> 82537.585
B40: 13 | C40: FV-Narbone a Terra Grande | D40: Fotovoltaico | E40: =IFERROR(SUMIFS(Fonte_Dati!I:I,Fonte_Dati!D:D,C40,Fonte_Dati!C:C,"Gennaio"),0) -> 8727.2947 | F40: =IFERROR(SUMIFS(Fonte_Dati!I:I,Fonte_Dati!D:D,C40,Fonte_Dati!C:C,"Febbraio"),0) -> 0 | G40: =IFERROR(SUMIFS(Fonte_Dati!I:I,Fonte_Dati!D:D,C40,Fonte_Dati!C:C,"Marzo"),0) -> 0 | H40: =IFERROR(SUM(E40:G40),0) -> 8727.2947 | I40: =IFERROR(F40-E40,"") -> -8727.2947 | J40: =IFERROR((F40-E40)/E40,"") -> -1 | K40: =IFERROR(SUMIFS(Fonte_Dati!I:I,Fonte_Dati!D:D,C40)/SUMIFS(Fonte_Dati!F:F,Fonte_Dati!D:D,C40)*1000,0) -> 115.00624 | L40: =IFERROR(SUMIF('💹 Incentivi'!D8:D23,"*Narbone a Terra*",'💹 Incentivi'!F8:F23),0) -> 56234.888 | M40: =IFERROR(SUMIF('💹 Incentivi'!D8:D23,"*Narbone a Terra*",'💹 Incentivi'!G8:G23),0) -> 56234.888 | N40: =IFERROR(SUMIF('💹 Incentivi'!D8:D23,"*Narbone a Terra*",'💹 Incentivi'!H8:H23),0) -> 56234.888 | O40: =IFERROR(SUMIF('💹 Incentivi'!D28:D43,"*Narbone a Terra*",'💹 Incentivi'!F28:F43),0) -> 24935.823 | P40: =IFERROR(SUMIF('💹 Incentivi'!D28:D43,"*Narbone a Terra*",'💹 Incentivi'!G28:G43),0) -> 0 | Q40: =IFERROR(SUMIF('💹 Incentivi'!D28:D43,"*Narbone a Terra*",'💹 Incentivi'!H28:H43),0) -> 0 | R40: =IFERROR(SUM(O40:Q40),0) -> 24935.823
B41: 14 | C41: FV-Narbone Piccolo | D41: Fotovoltaico | E41: =IFERROR(SUMIFS(Fonte_Dati!I:I,Fonte_Dati!D:D,C41,Fonte_Dati!C:C,"Gennaio"),0) -> 3863.6828 | F41: =IFERROR(SUMIFS(Fonte_Dati!I:I,Fonte_Dati!D:D,C41,Fonte_Dati!C:C,"Febbraio"),0) -> 3523.1758 | G41: =IFERROR(SUMIFS(Fonte_Dati!I:I,Fonte_Dati!D:D,C41,Fonte_Dati!C:C,"Marzo"),0) -> 0 | H41: =IFERROR(SUM(E41:G41),0) -> 7386.8585 | I41: =IFERROR(F41-E41,"") -> -340.507 | J41: =IFERROR((F41-E41)/E41,"") -> -0.088130165 | K41: =IFERROR(SUMIFS(Fonte_Dati!I:I,Fonte_Dati!D:D,C41)/SUMIFS(Fonte_Dati!F:F,Fonte_Dati!D:D,C41)*1000,0) -> 94.458118 | L41: =IFERROR(SUMIF('💹 Incentivi'!D8:D23,"*Narbone Piccolo*",'💹 Incentivi'!F8:F23),0) -> 0 | M41: =IFERROR(SUMIF('💹 Incentivi'!D8:D23,"*Narbone Piccolo*",'💹 Incentivi'!G8:G23),0) -> 0 | N41: =IFERROR(SUMIF('💹 Incentivi'!D8:D23,"*Narbone Piccolo*",'💹 Incentivi'!H8:H23),0) -> 0 | O41: =IFERROR(SUMIF('💹 Incentivi'!D28:D43,"*Narbone Piccolo*",'💹 Incentivi'!F28:F43),0) -> 0 | P41: =IFERROR(SUMIF('💹 Incentivi'!D28:D43,"*Narbone Piccolo*",'💹 Incentivi'!G28:G43),0) -> 0 | Q41: =IFERROR(SUMIF('💹 Incentivi'!D28:D43,"*Narbone Piccolo*",'💹 Incentivi'!H28:H43),0) -> 0 | R41: =IFERROR(SUM(O41:Q41),0) -> 0
B42: 15 | C42: FV-Campofranco Tetto | D42: Fotovoltaico | E42: =IFERROR(SUMIFS(Fonte_Dati!I:I,Fonte_Dati!D:D,C42,Fonte_Dati!C:C,"Gennaio"),0) -> 3020.1604 | F42: =IFERROR(SUMIFS(Fonte_Dati!I:I,Fonte_Dati!D:D,C42,Fonte_Dati!C:C,"Febbraio"),0) -> 3602.178 | G42: =IFERROR(SUMIFS(Fonte_Dati!I:I,Fonte_Dati!D:D,C42,Fonte_Dati!C:C,"Marzo"),0) -> 0 | H42: =IFERROR(SUM(E42:G42),0) -> 6622.3385 | I42: =IFERROR(F42-E42,"") -> 582.01758 | J42: =IFERROR((F42-E42)/E42,"") -> 0.19271081 | K42: =IFERROR(SUMIFS(Fonte_Dati!I:I,Fonte_Dati!D:D,C42)/SUMIFS(Fonte_Dati!F:F,Fonte_Dati!D:D,C42)*1000,0) -> 91.559736 | L42: =IFERROR(SUMIF('💹 Incentivi'!D8:D23,"*Campofranco*",'💹 Incentivi'!F8:F23),0) -> 33285.016 | M42: =IFERROR(SUMIF('💹 Incentivi'!D8:D23,"*Campofranco*",'💹 Incentivi'!G8:G23),0) -> 33285.016 | N42: =IFERROR(SUMIF('💹 Incentivi'!D8:D23,"*Campofranco*",'💹 Incentivi'!H8:H23),0) -> 33285.016 | O42: =IFERROR(SUMIF('💹 Incentivi'!D28:D43,"*Campofranco*",'💹 Incentivi'!F28:F43),0) -> 14054.254 | P42: =IFERROR(SUMIF('💹 Incentivi'!D28:D43,"*Campofranco*",'💹 Incentivi'!G28:G43),0) -> 25307.046 | Q42: =IFERROR(SUMIF('💹 Incentivi'!D28:D43,"*Campofranco*",'💹 Incentivi'!H28:H43),0) -> 0 | R42: =IFERROR(SUM(O42:Q42),0) -> 39361.299
B43: 16 | C43: FV-Tumarrano MEG | D43: Fotovoltaico | E43: =IFERROR(SUMIFS(Fonte_Dati!I:I,Fonte_Dati!D:D,C43,Fonte_Dati!C:C,"Gennaio"),0) -> 899.16669 | F43: =IFERROR(SUMIFS(Fonte_Dati!I:I,Fonte_Dati!D:D,C43,Fonte_Dati!C:C,"Febbraio"),0) -> 925.9 | G43: =IFERROR(SUMIFS(Fonte_Dati!I:I,Fonte_Dati!D:D,C43,Fonte_Dati!C:C,"Marzo"),0) -> 0 | H43: =IFERROR(SUM(E43:G43),0) -> 1825.0667 | I43: =IFERROR(F43-E43,"") -> 26.733312 | J43: =IFERROR((F43-E43)/E43,"") -> 0.029731209 | K43: =IFERROR(SUMIFS(Fonte_Dati!I:I,Fonte_Dati!D:D,C43)/SUMIFS(Fonte_Dati!F:F,Fonte_Dati!D:D,C43)*1000,0) -> 93.082199 | L43: =IFERROR(SUMIF('💹 Incentivi'!D8:D23,"*Tumarrano*",'💹 Incentivi'!F8:F23),0) -> 5264.1805 | M43: =IFERROR(SUMIF('💹 Incentivi'!D8:D23,"*Tumarrano*",'💹 Incentivi'!G8:G23),0) -> 0 | N43: =IFERROR(SUMIF('💹 Incentivi'!D8:D23,"*Tumarrano*",'💹 Incentivi'!H8:H23),0) -> 0 | O43: =IFERROR(SUMIF('💹 Incentivi'!D28:D43,"*Tumarrano*",'💹 Incentivi'!F28:F43),0) -> 9292.1038 | P43: =IFERROR(SUMIF('💹 Incentivi'!D28:D43,"*Tumarrano*",'💹 Incentivi'!G28:G43),0) -> 12341.809 | Q43: =IFERROR(SUMIF('💹 Incentivi'!D28:D43,"*Tumarrano*",'💹 Incentivi'!H28:H43),0) -> 0 | R43: =IFERROR(SUM(O43:Q43),0) -> 21633.913
B44: TOTALE Q1 | E44: =SUM(E28:E43) -> 1674043 | F44: =SUM(F28:F43) -> 1453027.6 | G44: =SUM(G28:G43) -> 157.75308 | H44: =SUM(H28:H43) -> 3127228.3 | I44: =IFERROR(F44-E44,"") -> -221015.41 | J44: =IFERROR((F44-E44)/E44,"") -> -0.13202493 | K44: =SUM(K28:K43) -> 1578.6044 | L44: =SUM(L28:L43) -> 1536012.3 | M44: =SUM(M28:M43) -> 1530748.1 | N44: =SUM(N28:N43) -> 1530748.1 | O44: =SUM(O28:O43) -> 756908.41 | P44: =SUM(P28:P43) -> 948050.48 | Q44: =SUM(Q28:Q43) -> 0 | R44: =SUM(R28:R43) -> 1704958.9

Sheet Irraggiamento_PVGIS
B1: 🌞 IRRAGGIAMENTO SOLARE — DATI PVGIS PER IMPIANTO
B4: Fonte: PVGIS EU JRC (re.jrc.ec.europa.eu) | Piano inclinato H(i) [kWh/m²] | Aggiornato automaticamente dalla macro
B6: REGISTRO COORDINATE E PARAMETRI IMPIANTI
B7: ⚠ Verifica/correggi le coordinate gialle prima di avviare la macro PVGIS — sono coordinate indicative da validare
B8: ID | C8: Impianto | D8: Tipo | E8: Latitudine | F8: Longitudine | G8: Tilt (°) | H8: Azimuth (°)
B9: 1 | C9: FV-Batia S. Francesco | D9: Fotovoltaico | E9: 37.23675 | F9: 13.742667 | G9: 30 | H9: 0
B10: 2 | C10: FV-Campofranco Tetto | D10: Fotovoltaico | E10: 37.497556 | F10: 13.692333 | G10: 4 | H10: -23
B11: 3 | C11: FV-Fauma Tetto | D11: Fotovoltaico | E11: 37.343611 | F11: 13.476417 | G11: 15 | H11: -13
B12: 4 | C12: FV-Favara Grande | D12: Fotovoltaico | E12: 37.362222 | F12: 13.639111 | G12: 30 | H12: 0
B13: 5 | C13: FV-Malvizzo Piccolo | D13: Fotovoltaico | E13: 37.26525 | F13: 13.711694 | G13: 30 | H13: 0
B14: 6 | C14: FV-Malvizzo a Terra | D14: Fotovoltaico | E14: 37.260694 | F14: 13.699972 | G14: 30 | H14: 0
B15: 7 | C15: FV-Narbone Piccolo | D15: Fotovoltaico | E15: 37.233611 | F15: 13.726 | G15: 30 | H15: 0
B16: 8 | C16: FV-Narbone a Terra Grande | D16: Fotovoltaico | E16: 37.231722 | F16: 13.725722 | G16: 30 | H16: 0
B17: 9 | C17: FV-Perniciara | D17: Fotovoltaico | E17: 37.369417 | F17: 13.645139 | G17: 30 | H17: 0
B18: 10 | C18: FV-Serre Gela | D18: Fotovoltaico | E18: 37.063222 | F18: 14.391556 | G18: 17 | H18: 0
B19: 11 | C19: FV-Serre Narbone | D19: Fotovoltaico | E19: 37.218528 | F19: 13.719556 | G19: 17 | H19: 0
B20: 12 | C20: FV-Serre S.Angelo Muxaro | D20: Fotovoltaico | E20: 37.485972 | F20: 13.576306 | G20: 20 | H20: 0
... B24: 16 | C24: Wind - Monte Narbone | D24: Eolico | E24: 37.225917 | F24: 13.723556 | G24: 0 | H24: 0
B27: IRRAGGIAMENTO MENSILE H(i) [kWh/m²] — FV: Piano inclinato (PVGIS) | EOLICI: Vento medio mensile [m/s] @ 55m hub — Open-Meteo ERA5 (interp. log. 10m↔100m)
B28: 🔄 Dati compilati automaticamente dalla macro ▶ AGGIORNA DATI + PVGIS | Anno di riferimento configurabile in ⚙️ Setup & Macro cella E10
B29: ID | C29: Impianto | D29: Tipo | E29: Gen | F29: Feb | G29: Mar | H29: Apr | I29: Mag | J29: Giu | K29: Lug | L29: Ago | M29: Set | N29: Ott | O29: Nov | P29: Dic | Q29: Totale Anno | R29: Fonte | S29: Ultimo Agg.
B30: 1 | C30: FV-Batia S. Francesco | D30: Fotovoltaico | Q30: =IFERROR(SUM(E30:P30),"") -> 0 | R30: PVGIS v5.2
B31: 2 | C31: FV-Campofranco Tetto | D31: Fotovoltaico | Q31: =IFERROR(SUM(E31:P31),"") -> 0 | R31: PVGIS v5.2
B32: 3 | C32: FV-Fauma Tetto | D32: Fotovoltaico | Q32: =IFERROR(SUM(E32:P32),"") -> 0 | R32: PVGIS v5.2
B33: 4 | C33: FV-Favara Grande | D33: Fotovoltaico | Q33: =IFERROR(SUM(E33:P33),"") -> 0 | R33: PVGIS v5.2
B34: 5 | C34: FV-Malvizzo Piccolo | D34: Fotovoltaico | Q34: =IFERROR(SUM(E34:P34),"") -> 0 | R34: PVGIS v5.2
B35: 6 | C35: FV-Malvizzo a Terra | D35: Fotovoltaico | Q35: =IFERROR(SUM(E35:P35),"") -> 0 | R35: PVGIS v5.2
B36: 7 | C36: FV-Narbone Piccolo | D36: Fotovoltaico | Q36: =IFERROR(SUM(E36:P36),"") -> 0 | R36: PVGIS v5.2
B37: 8 | C37: FV-Narbone a Terra Grande | D37: Fotovoltaico | Q37: =IFERROR(SUM(E37:P37),"") -> 0 | R37: PVGIS v5.2
B38: 9 | C38: FV-Perniciara | D38: Fotovoltaico | Q38: =IFERROR(SUM(E38:P38),"") -> 0 | R38: PVGIS v5.2
B39: 10 | C39: FV-Serre Gela | D39: Fotovoltaico | Q39: =IFERROR(SUM(E39:P39),"") -> 0 | R39: PVGIS v5.2
B40: 11 | C40: FV-Serre Narbone | D40: Fotovoltaico | Q40: =IFERROR(SUM(E40:P40),"") -> 0 | R40: PVGIS v5.2
B41: 12 | C41: FV-Serre S.Angelo Muxaro | D41: Fotovoltaico | Q41: =IFERROR(SUM(E41:P41),"") -> 0 | R41: PVGIS v5.2
... B45: 16 | C45: Wind - Monte Narbone | D45: Eolico (m/s) | Q45: =IFERROR(SUM(E45:P45),"") -> 0 | R45: Open-Meteo
B46: MEDIA PORTFOLIO | I46: =IFERROR(AVERAGE(I30:I45),"") | J46: =IFERROR(AVERAGE(J30:J45),"") | K46: =IFERROR(AVERAGE(K30:K45),"") | L46: =IFERROR(AVERAGE(L30:L45),"") | M46: =IFERROR(AVERAGE(M30:M45),"") | N46: =IFERROR(AVERAGE(N30:N45),"") | O46: =IFERROR(AVERAGE(O30:O45),"") | P46: =IFERROR(AVERAGE(P30:P45),"") | ... S46: =IFERROR(AVERAGE(S30:S45),"")
B48: ⚙️ CONFIGURAZIONE CORREZIONE — modifica le celle gialle
B49: ☀ Fattore correzione FV (%): | E49: 0 | F49: PVGIS 2020 → es. -3 = riduzione 3% | Applica solo ai 13 impianti FV
B50: 💨 Fattore correzione Eolico (%): | E50: 0 | F50: Open-Meteo ERA5 → es. +5 = aumento 5% | Applica solo ai 3 impianti Eolici
B51: ⚠ FV: mult. = (1+E49/100) | Eolico: mult. = (1+E50/100) | Le celle Lookup Q1 usano automaticamente il fattore corretto per tipo impianto
B52: LOOKUP Q1 — VALORI CORRETTI PER CALCOLO PR (☀ FV applica fattore E49 | 💨 Eolico applica fattore E50)
B53: 1 | C53: FV-Batia S. Francesco | D53: Fotovoltaico | E53: =IFERROR(E30*(1+Irraggiamento_PVGIS!$E$49/100),"") -> 0 | F53: =IFERROR(F30*(1+Irraggiamento_PVGIS!$E$49/100),"") -> 0 | G53: =IFERROR(G30*(1+Irraggiamento_PVGIS!$E$49/100),"") -> 0 | H53: =IFERROR(SUM(E53:G53),"") -> 0
B54: 2 | C54: FV-Campofranco Tetto | D54: Fotovoltaico | E54: =IFERROR(E31*(1+Irraggiamento_PVGIS!$E$49/100),"") -> 0 | F54: =IFERROR(F31*(1+Irraggiamento_PVGIS!$E$49/100),"") -> 0 | G54: =IFERROR(G31*(1+Irraggiamento_PVGIS!$E$49/100),"") -> 0 | H54: =IFERROR(SUM(E54:G54),"") -> 0
B55: 3 | C55: FV-Fauma Tetto | D55: Fotovoltaico | E55: =IFERROR(E32*(1+Irraggiamento_PVGIS!$E$49/100),"") -> 0 | F55: =IFERROR(F32*(1+Irraggiamento_PVGIS!$E$49/100),"") -> 0 | G55: =IFERROR(G32*(1+Irraggiamento_PVGIS!$E$49/100),"") -> 0 | H55: =IFERROR(SUM(E55:G55),"") -> 0
B56: 4 | C56: FV-Favara Grande | D56: Fotovoltaico | E56: =IFERROR(E33*(1+Irraggiamento_PVGIS!$E$49/100),"") -> 0 | F56: =IFERROR(F33*(1+Irraggiamento_PVGIS!$E$49/100),"") -> 0 | G56: =IFERROR(G33*(1+Irraggiamento_PVGIS!$E$49/100),"") -> 0 | H56: =IFERROR(SUM(E56:G56),"") -> 0
B57: 5 | C57: FV-Malvizzo Piccolo | D57: Fotovoltaico | E57: =IFERROR(E34*(1+Irraggiamento_PVGIS!$E$49/100),"") -> 0 | F57: =IFERROR(F34*(1+Irraggiamento_PVGIS!$E$49/100),"") -> 0 | G57: =IFERROR(G34*(1+Irraggiamento_PVGIS!$E$49/100),"") -> 0 | H57: =IFERROR(SUM(E57:G57),"") -> 0
B58: 6 | C58: FV-Malvizzo a Terra | D58: Fotovoltaico | E58: =IFERROR(E35*(1+Irraggiamento_PVGIS!$E$49/100),"") -> 0 | F58: =IFERROR(F35*(1+Irraggiamento_PVGIS!$E$49/100),"") -> 0 | G58: =IFERROR(G35*(1+Irraggiamento_PVGIS!$E$49/100),"") -> 0 | H58: =IFERROR(SUM(E58:G58),"") -> 0
B59: 7 | C59: FV-Narbone Piccolo | D59: Fotovoltaico | E59: =IFERROR(E36*(1+Irraggiamento_PVGIS!$E$49/100),"") -> 0 | F59: =IFERROR(F36*(1+Irraggiamento_PVGIS!$E$49/100),"") -> 0 | G59: =IFERROR(G36*(1+Irraggiamento_PVGIS!$E$49/100),"") -> 0 | H59: =IFERROR(SUM(E59:G59),"") -> 0
B60: 8 | C60: FV-Narbone a Terra Grande | D60: Fotovoltaico | E60: =IFERROR(E37*(1+Irraggiamento_PVGIS!$E$49/100),"") -> 0 | F60: =IFERROR(F37*(1+Irraggiamento_PVGIS!$E$49/100),"") -> 0 | G60: =IFERROR(G37*(1+Irraggiamento_PVGIS!$E$49/100),"") -> 0 | H60: =IFERROR(SUM(E60:G60),"") -> 0
B61: 9 | C61: FV-Perniciara | D61: Fotovoltaico | E61: =IFERROR(E38*(1+Irraggiamento_PVGIS!$E$49/100),"") -> 0 | F61: =IFERROR(F38*(1+Irraggiamento_PVGIS!$E$49/100),"") -> 0 | G61: =IFERROR(G38*(1+Irraggiamento_PVGIS!$E$49/100),"") -> 0 | H61: =IFERROR(SUM(E61:G61),"") -> 0
B62: 10 | C62: FV-Serre Gela | D62: Fotovoltaico | E62: =IFERROR(E39*(1+Irraggiamento_PVGIS!$E$49/100),"") -> 0 | F62: =IFERROR(F39*(1+Irraggiamento_PVGIS!$E$49/100),"") -> 0 | G62: =IFERROR(G39*(1+Irraggiamento_PVGIS!$E$49/100),"") -> 0 | H62: =IFERROR(SUM(E62:G62),"") -> 0
B63: 11 | C63: FV-Serre Narbone | D63: Fotovoltaico | E63: =IFERROR(E40*(1+Irraggiamento_PVGIS!$E$49/100),"") -> 0 | F63: =IFERROR(F40*(1+Irraggiamento_PVGIS!$E$49/100),"") -> 0 | G63: =IFERROR(G40*(1+Irraggiamento_PVGIS!$E$49/100),"") -> 0 | H63: =IFERROR(SUM(E63:G63),"") -> 0
B64: 12 | C64: FV-Serre S.Angelo Muxaro | D64: Fotovoltaico | E64: =IFERROR(E41*(1+Irraggiamento_PVGIS!$E$49/100),"") -> 0 | F64: =IFERROR(F41*(1+Irraggiamento_PVGIS!$E$49/100),"") -> 0 | G64: =IFERROR(G41*(1+Irraggiamento_PVGIS!$E$49/100),"") -> 0 | H64: =IFERROR(SUM(E64:G64),"") -> 0
B65: 13 | C65: FV-Tumarrano MEG | D65: Fotovoltaico | E65: =IFERROR(E42*(1+Irraggiamento_PVGIS!$E$49/100),"") -> 0 | F65: =IFERROR(F42*(1+Irraggiamento_PVGIS!$E$49/100),"") -> 0 | G65: =IFERROR(G42*(1+Irraggiamento_PVGIS!$E$49/100),"") -> 0 | H65: =IFERROR(SUM(E65:G65),"") -> 0
B66: 14 | C66: Wind - Monte Durrà | D66: Eolico (m/s) | E66: =IFERROR(E43*(1+Irraggiamento_PVGIS!$E$50/100),"") -> 0 | F66: =IFERROR(F43*(1+Irraggiamento_PVGIS!$E$50/100),"") -> 0 | G66: =IFERROR(G43*(1+Irraggiamento_PVGIS!$E$50/100),"") -> 0 | H66: =IFERROR(SUM(E66:G66),"") -> 0
B67: 15 | C67: Wind - Monte Malvizzo | D67: Eolico (m/s) | E67: =IFERROR(E44*(1+Irraggiamento_PVGIS!$E$50/100),"") -> 0 | F67: =IFERROR(F44*(1+Irraggiamento_PVGIS!$E$50/100),"") -> 0 | G67: =IFERROR(G44*(1+Irraggiamento_PVGIS!$E$50/100),"") -> 0 | H67: =IFERROR(SUM(E67:G67),"") -> 0
B68: 16 | C68: Wind - Monte Narbone | D68: Eolico (m/s) | E68: =IFERROR(E45*(1+Irraggiamento_PVGIS!$E$50/100),"") -> 0 | F68: =IFERROR(F45*(1+Irraggiamento_PVGIS!$E$50/100),"") -> 0 | G68: =IFERROR(G45*(1+Irraggiamento_PVGIS!$E$50/100),"") -> 0 | H68: =IFERROR(SUM(E68:G68),"") -> 0

Sheet SRC_Incentivi
A1: FONTE DATI INCENTIVI — Aggiornato dalla macro (non modificare)
A3: ADVANCE-GSE (kWh — Acconto GSE per mese)
A4: CODE | B4: SPV | C4: SITE | D4: ID_GSE | E4: Gennaio | F4: Febbraio | G4: Marzo | H4: Aprile | I4: Maggio | J4: Giugno | K4: Luglio | L4: Agosto | M4: Settembre | N4: Ottobre | O4: Novembre | P4: Dicembre
A5: MONC1A01_01 | B5: ENERGIE INNOVATIVE SRL | C5: FV-Batia S.Francesco Sez. 01 | D5: 668458,01 | E5: 505134 | F5: 505134 | G5: 505134 | H5: 0 | I5: 0 | J5: 0 | K5: 0 | L5: 0 | M5: 0 | N5: 0 | O5: 0 | P5: 0
A6: MONC1A01_03 | B6: ENERGIE INNOVATIVE SRL | C6: FV-Batia S.Francesco Sez. 02 | D6: 668458,03 | E6: 0 | F6: 0 | G6: 0 | H6: 0 | I6: 0 | J6: 0 | K6: 0 | L6: 0 | M6: 0 | N6: 0 | O6: 0 | P6: 0
A7: MONC1A01_04 | B7: ENERGIE INNOVATIVE SRL | C7: FV-Batia S.Francesco Sez. 03 | D7: 668458,04 | E7: 0 | F7: 0 | G7: 0 | H7: 0 | I7: 0 | J7: 0 | K7: 0 | L7: 0 | M7: 0 | N7: 0 | O7: 0 | P7: 0
A8: MONC2A03 | B8: MONCADA ENERGY GROUP SRL | C8: FV-Campofranco Tetto | D8: 157365,01 | E8: 68207 | F8: 68207 | G8: 68207 | H8: 0 | I8: 0 | J8: 0 | K8: 0 | L8: 0 | M8: 0 | N8: 0 | O8: 0 | P8: 0
A9: MONC2A06 | B9: MONCADA ENERGY GROUP SRL | C9: FV-Kronion Tetto | D9: 789725,01 | E9: 0 | F9: 0 | G9: 0 | H9: 0 | I9: 0 | J9: 0 | K9: 0 | L9: 0 | M9: 0 | N9: 0 | O9: 0 | P9: 0
A10: MONC2A07 | B10: MONCADA ENERGY SOLAR S.R.L. | C10: FV-Malvizzo a Terra | D10: 657220 | E10: 323510 | F10: 323510 | G10: 323510 | H10: 0 | I10: 0 | J10: 0 | K10: 0 | L10: 0 | M10: 0 | N10: 0 | O10: 0 | P10: 0
A11: MONC2A09 | B11: MONCADA ENERGY GROUP SRL | C11: FV-Melilli | D11: 609577 | E11: 26742 | F11: 26742 | G11: 26742 | H11: 0 | I11: 0 | J11: 0 | K11: 0 | L11: 0 | M11: 0 | N11: 0 | O11: 0 | P11: 0
A12: MONC2A10 | B12: MONCADA ENERGY SOLAR S.R.L. | C12: FV-Narbone a Terra Grande | D12: 640248,01 | E12: 179092 | F12: 179092 | G12: 179092 | H12: 0 | I12: 0 | J12: 0 | K12: 0 | L12: 0 | M12: 0 | N12: 0 | O12: 0 | P12: 0
A13: MONC2A13 | B13: MONCADA ENERGY GROUP SRL | C13: FV-Palazzetto | D13: 272016 | E13: 12850 | F13: 12850 | G13: 12850 | H13: 0 | I13: 0 | J13: 0 | K13: 0 | L13: 0 | M13: 0 | N13: 0 | O13: 0 | P13: 0
A14: MONC2A15 | B14: SOCIETA' AGRICOLA SOLAR FARM 5 S.R.L. | C14: FV-Serre Gela | D14: 611248 | E14: 402134 | F14: 402134 | G14: 402134 | H14: 0 | I14: 0 | J14: 0 | K14: 0 | L14: 0 | M14: 0 | N14: 0 | O14: 0 | P14: 0
A15: MONC2A16_01 | B15: SOCIETA' AGRICOLA SOLAR FARM S.R.L. | C15: FV-Serre Narbone Sez. 01 | D15: 135769,01 | E15: 249902 | F15: 249902 | G15: 249902 | H15: 0 | I15: 0 | J15: 0 | K15: 0 | L15: 0 | M15: 0 | N15: 0 | O15: 0 | P15: 0
A16: MONC2A16_02 | B16: SOCIETA' AGRICOLA SOLAR FARM S.R.L. | C16: FV-Serre Narbone Sez. 02 | D16: 135769,02 | E16: 212693 | F16: 212693 | G16: 212693 | H16: 0 | I16: 0 | J16: 0 | K16: 0 | L16: 0 | M16: 0 | N16: 0 | O16: 0 | P16: 0
... A20: MONC2A18 | B20: TUMARRANO ENERGY SOLAR SRL | C20: FV-Tumarrano Partner | D20: 1003118,01 | E20: 39104 | F20: 0 | G20: 0 | H20: 0 | I20: 0 | J20: 0 | K20: 0 | L20: 0 | M20: 0 | N20: 0 | O20: 0 | P20: 0
A23: OWNER (kWh — Consuntivo per mese)
A24: CODE | B24: SPV | C24: SITE | D24: ID_GSE | E24: Gennaio | F24: Febbraio | G24: Marzo | H24: Aprile | I24: Maggio | J24: Giugno | K24: Luglio | L24: Agosto | M24: Settembre | N24: Ottobre | O24: Novembre | P24: Dicembre
A25: MONC1A01_01 | B25: ENERGIE INNOVATIVE SRL | C25: FV-Batia S.Francesco Sez. 01 | D25: 668458,01 | E25: 231563.2 | F25: 409334.05 | G25: 0 | H25: 0 | I25: 0 | J25: 0 | K25: 0 | L25: 0 | M25: 0 | N25: 0 | O25: 0 | P25: 0
A26: MONC1A01_03 | B26: ENERGIE INNOVATIVE SRL | C26: FV-Batia S.Francesco Sez. 02 | D26: 668458,03 | E26: 113561.05 | F26: 197765.17 | G26: 0 | H26: 0 | I26: 0 | J26: 0 | K26: 0 | L26: 0 | M26: 0 | N26: 0 | O26: 0 | P26: 0
A27: MONC1A01_04 | B27: ENERGIE INNOVATIVE SRL | C27: FV-Batia S.Francesco Sez. 03 | D27: 668458,04 | E27: 47337.13 | F27: 78860.3 | G27: 0 | H27: 0 | I27: 0 | J27: 0 | K27: 0 | L27: 0 | M27: 0 | N27: 0 | O27: 0 | P27: 0
A28: MONC2A03 | B28: MONCADA ENERGY GROUP SRL | C28: FV-Campofranco Tetto | D28: 157365,01 | E28: 28799.7 | F28: 51858.7 | G28: 0 | H28: 0 | I28: 0 | J28: 0 | K28: 0 | L28: 0 | M28: 0 | N28: 0 | O28: 0 | P28: 0
A29: MONC2A06 | B29: MONCADA ENERGY GROUP SRL | C29: FV-Kronion Tetto | D29: 789725,01 | E29: 16583.525 | F29: 15486.86 | G29: 0 | H29: 0 | I29: 0 | J29: 0 | K29: 0 | L29: 0 | M29: 0 | N29: 0 | O29: 0 | P29: 0
A30: MONC2A07 | B30: MONCADA ENERGY SOLAR S.R.L. | C30: FV-Malvizzo a Terra | D30: 657220 | E30: 115284.9 | F30: 213550.1 | G30: 0 | H30: 0 | I30: 0 | J30: 0 | K30: 0 | L30: 0 | M30: 0 | N30: 0 | O30: 0 | P30: 0
A31: MONC2A09 | B31: MONCADA ENERGY GROUP SRL | C31: FV-Melilli | D31: 609577 | E31: 37335 | F31: 59888.56 | G31: 0 | H31: 0 | I31: 0 | J31: 0 | K31: 0 | L31: 0 | M31: 0 | N31: 0 | O31: 0 | P31: 0
A32: MONC2A10 | B32: MONCADA ENERGY SOLAR S.R.L. | C32: FV-Narbone a Terra Grande | D32: 640248,01 | E32: 79413.45 | F32: 0 | G32: 0 | H32: 0 | I32: 0 | J32: 0 | K32: 0 | L32: 0 | M32: 0 | N32: 0 | O32: 0 | P32: 0
A33: MONC2A13 | B33: MONCADA ENERGY GROUP SRL | C33: FV-Palazzetto | D33: 272016 | E33: 6574.56 | F33: 10105.89 | G33: 0 | H33: 0 | I33: 0 | J33: 0 | K33: 0 | L33: 0 | M33: 0 | N33: 0 | O33: 0 | P33: 0
A34: MONC2A15 | B34: SOCIETA' AGRICOLA SOLAR FARM 5 S.R.L. | C34: FV-Serre Gela | D34: 611248 | E34: 204173.7 | F34: 283118.9 | G34: 0 | H34: 0 | I34: 0 | J34: 0 | K34: 0 | L34: 0 | M34: 0 | N34: 0 | O34: 0 | P34: 0
A35: MONC2A16_01 | B35: SOCIETA' AGRICOLA SOLAR FARM S.R.L. | C35: FV-Serre Narbone Sez. 01 | D35: 135769,01 | E35: 133667.12 | F35: 163986.35 | G35: 0 | H35: 0 | I35: 0 | J35: 0 | K35: 0 | L35: 0 | M35: 0 | N35: 0 | O35: 0 | P35: 0
A36: MONC2A16_02 | B36: SOCIETA' AGRICOLA SOLAR FARM S.R.L. | C36: FV-Serre Narbone Sez. 02 | D36: 135769,02 | E36: 112743.65 | F36: 144874.5 | G36: 0 | H36: 0 | I36: 0 | J36: 0 | K36: 0 | L36: 0 | M36: 0 | N36: 0 | O36: 0 | P36: 0
... A40: MONC2A18 | B40: TUMARRANO ENERGY SOLAR SRL | C40: FV-Tumarrano Partner | D40: 1003118,01 | E40: 69024.69 | F40: 91678.87 | G40: 0 | H40: 0 | I40: 0 | J40: 0 | K40: 0 | L40: 0 | M40: 0 | N40: 0 | O40: 0 | P40: 0
A42: TARIFF (€/kWh — Tariffa incentivante per mese)
A43: CODE | B43: SPV | C43: SITE | D43: ID_GSE | E43: Gennaio | F43: Febbraio | G43: Marzo | H43: Aprile | I43: Maggio | J43: Giugno | K43: Luglio | L43: Agosto | M43: Settembre | N43: Ottobre | O43: Novembre | P43: Dicembre
A44: MONC1A01_01 | B44: ENERGIE INNOVATIVE SRL | C44: FV-Batia S.Francesco Sez. 01 | D44: 668458,01 | E44: 0.217 | F44: 0.217 | G44: 0.217 | H44: 0.217 | I44: 0.217 | J44: 0.217 | K44: 0.217 | L44: 0.217 | M44: 0.217 | N44: 0.217 | O44: 0.217 | P44: 0.217
A45: MONC1A01_03 | B45: ENERGIE INNOVATIVE SRL | C45: FV-Batia S.Francesco Sez. 02 | D45: 668458,03 | E45: 0 | F45: 0 | G45: 0 | H45: 0 | I45: 0 | J45: 0 | K45: 0 | L45: 0 | M45: 0 | N45: 0 | O45: 0 | P45: 0
A46: MONC1A01_04 | B46: ENERGIE INNOVATIVE SRL | C46: FV-Batia S.Francesco Sez. 03 | D46: 668458,04 | E46: 0 | F46: 0 | G46: 0 | H46: 0 | I46: 0 | J46: 0 | K46: 0 | L46: 0 | M46: 0 | N46: 0 | O46: 0 | P46: 0
A47: MONC2A03 | B47: MONCADA ENERGY GROUP SRL | C47: FV-Campofranco Tetto | D47: 157365,01 | E47: 0.488 | F47: 0.488 | G47: 0.488 | H47: 0.488 | I47: 0.488 | J47: 0.488 | K47: 0.488 | L47: 0.488 | M47: 0.488 | N47: 0.488 | O47: 0.488 | P47: 0.488
A48: MONC2A06 | B48: MONCADA ENERGY GROUP SRL | C48: FV-Kronion Tetto | D48: 789725,01 | E48: 0 | F48: 0 | G48: 0 | H48: 0 | I48: 0 | J48: 0 | K48: 0 | L48: 0 | M48: 0 | N48: 0 | O48: 0 | P48: 0
A49: MONC2A07 | B49: MONCADA ENERGY SOLAR S.R.L. | C49: FV-Malvizzo a Terra | D49: 657220 | E49: 0.251 | F49: 0.251 | G49: 0.251 | H49: 0.251 | I49: 0.251 | J49: 0.251 | K49: 0.251 | L49: 0.251 | M49: 0.251 | N49: 0.251 | O49: 0.251 | P49: 0.251
A50: MONC2A09 | B50: MONCADA ENERGY GROUP SRL | C50: FV-Melilli | D50: 609577 | E50: 0.207 | F50: 0.207 | G50: 0.207 | H50: 0.207 | I50: 0.207 | J50: 0.207 | K50: 0.207 | L50: 0.207 | M50: 0.207 | N50: 0.207 | O50: 0.207 | P50: 0.207
A51: MONC2A10 | B51: MONCADA ENERGY SOLAR S.R.L. | C51: FV-Narbone a Terra Grande | D51: 640248,01 | E51: 0.314 | F51: 0.314 | G51: 0.314 | H51: 0.314 | I51: 0.314 | J51: 0.314 | K51: 0.314 | L51: 0.314 | M51: 0.314 | N51: 0.314 | O51: 0.314 | P51: 0.314
A52: MONC2A13 | B52: MONCADA ENERGY GROUP SRL | C52: FV-Palazzetto | D52: 272016 | E52: 0.384 | F52: 0.384 | G52: 0.384 | H52: 0.384 | I52: 0.384 | J52: 0.384 | K52: 0.384 | L52: 0.384 | M52: 0.384 | N52: 0.384 | O52: 0.384 | P52: 0.384
A53: MONC2A15 | B53: SOCIETA' AGRICOLA SOLAR FARM 5 S.R.L. | C53: FV-Serre Gela | D53: 611248 | E53: 0.285 | F53: 0.285 | G53: 0.285 | H53: 0.285 | I53: 0.285 | J53: 0.285 | K53: 0.285 | L53: 0.285 | M53: 0.285 | N53: 0.285 | O53: 0.285 | P53: 0.285
A54: MONC2A16_01 | B54: SOCIETA' AGRICOLA SOLAR FARM S.R.L. | C54: FV-Serre Narbone Sez. 01 | D54: 135769,01 | E54: 0.491 | F54: 0.491 | G54: 0.491 | H54: 0.491 | I54: 0.491 | J54: 0.491 | K54: 0.491 | L54: 0.491 | M54: 0.491 | N54: 0.491 | O54: 0.491 | P54: 0.491
A55: MONC2A16_02 | B55: SOCIETA' AGRICOLA SOLAR FARM S.R.L. | C55: FV-Serre Narbone Sez. 02 | D55: 135769,02 | E55: 0.49 | F55: 0.49 | G55: 0.49 | H55: 0.49 | I55: 0.49 | J55: 0.49 | K55: 0.49 | L55: 0.49 | M55: 0.49 | N55: 0.49 | O55: 0.49 | P55: 0.49
... A59: MONC2A18 | B59: TUMARRANO ENERGY SOLAR SRL | C59: FV-Tumarrano Partner | D59: 1003118,01 | E59: 0.13462 | F59: 0.13462 | G59: 0.13462 | H59: 0.13462 | I59: 0.13462 | J59: 0.13462 | K59: 0.13462 | L59: 0.13462 | M59: 0.13462 | N59: 0.13462 | O59: 0.13462 | P59: 0.13462

Sheet 💹 Incentivi
B1: 💹 KPI INCENTIVI — CALCOLO ACCONTO & CONSUNTIVO GSE
B4: Acconto: ADVANCE-GSE (kWh) × TARIFF (€/kWh) | Consuntivo: OWNER (kWh) × TARIFF (€/kWh) | Fonte: detailed-history.xlsx aggiornato via macro
B6: 📊 ACCONTO INCENTIVI GSE — ADVANCE-GSE × TARIFF
B7: ID | C7: CODE | D7: Impianto / SPV | E7: Tariffa (€/kWh) | F7: Gen | G7: Feb | H7: Mar | I7: Apr | J7: Mag | K7: Giu | L7: Lug | M7: Ago | N7: Set | O7: Ott | P7: Nov | Q7: Dic | R7: Totale Anno (€)
B8: 1 | C8: MONC1A01_01 | D8: FV-Batia S.Francesco Sez. 01 | E8: =IFERROR(AVERAGE(SRC_Incentivi!E44:P44),0) -> 0.217 | F8: =IFERROR(SRC_Incentivi!E5*SRC_Incentivi!E44,0) -> 109614.08 | G8: =IFERROR(SRC_Incentivi!F5*SRC_Incentivi!F44,0) -> 109614.08 | H8: =IFERROR(SRC_Incentivi!G5*SRC_Incentivi!G44,0) -> 109614.08 | I8: =IFERROR(SRC_Incentivi!H5*SRC_Incentivi!H44,0) -> 0 | J8: =IFERROR(SRC_Incentivi!I5*SRC_Incentivi!I44,0) -> 0 | K8: =IFERROR(SRC_Incentivi!J5*SRC_Incentivi!J44,0) -> 0 | L8: =IFERROR(SRC_Incentivi!K5*SRC_Incentivi!K44,0) -> 0 | M8: =IFERROR(SRC_Incentivi!L5*SRC_Incentivi!L44,0) -> 0 | ... Q8: =IFERROR(SRC_Incentivi!P5*SRC_Incentivi!P44,0) -> 0 | R8: =SUM(F8:Q8) -> 328842.23
B9: 2 | C9: MONC1A01_03 | D9: FV-Batia S.Francesco Sez. 02 | E9: =IFERROR(AVERAGE(SRC_Incentivi!E45:P45),0) -> 0 | F9: =IFERROR(SRC_Incentivi!E6*SRC_Incentivi!E45,0) -> 0 | G9: =IFERROR(SRC_Incentivi!F6*SRC_Incentivi!F45,0) -> 0 | H9: =IFERROR(SRC_Incentivi!G6*SRC_Incentivi!G45,0) -> 0 | I9: =IFERROR(SRC_Incentivi!H6*SRC_Incentivi!H45,0) -> 0 | J9: =IFERROR(SRC_Incentivi!I6*SRC_Incentivi!I45,0) -> 0 | K9: =IFERROR(SRC_Incentivi!J6*SRC_Incentivi!J45,0) -> 0 | L9: =IFERROR(SRC_Incentivi!K6*SRC_Incentivi!K45,0) -> 0 | M9: =IFERROR(SRC_Incentivi!L6*SRC_Incentivi!L45,0) -> 0 | ... Q9: =IFERROR(SRC_Incentivi!P6*SRC_Incentivi!P45,0) -> 0 | R9: =SUM(F9:Q9) -> 0
B10: 3 | C10: MONC1A01_04 | D10: FV-Batia S.Francesco Sez. 03 | E10: =IFERROR(AVERAGE(SRC_Incentivi!E46:P46),0) -> 0 | F10: =IFERROR(SRC_Incentivi!E7*SRC_Incentivi!E46,0) -> 0 | G10: =IFERROR(SRC_Incentivi!F7*SRC_Incentivi!F46,0) -> 0 | H10: =IFERROR(SRC_Incentivi!G7*SRC_Incentivi!G46,0) -> 0 | I10: =IFERROR(SRC_Incentivi!H7*SRC_Incentivi!H46,0) -> 0 | J10: =IFERROR(SRC_Incentivi!I7*SRC_Incentivi!I46,0) -> 0 | K10: =IFERROR(SRC_Incentivi!J7*SRC_Incentivi!J46,0) -> 0 | L10: =IFERROR(SRC_Incentivi!K7*SRC_Incentivi!K46,0) -> 0 | M10: =IFERROR(SRC_Incentivi!L7*SRC_Incentivi!L46,0) -> 0 | ... Q10: =IFERROR(SRC_Incentivi!P7*SRC_Incentivi!P46,0) -> 0 | R10: =SUM(F10:Q10) -> 0
B11: 4 | C11: MONC2A03 | D11: FV-Campofranco Tetto | E11: =IFERROR(AVERAGE(SRC_Incentivi!E47:P47),0) -> 0.488 | F11: =IFERROR(SRC_Incentivi!E8*SRC_Incentivi!E47,0) -> 33285.016 | G11: =IFERROR(SRC_Incentivi!F8*SRC_Incentivi!F47,0) -> 33285.016 | H11: =IFERROR(SRC_Incentivi!G8*SRC_Incentivi!G47,0) -> 33285.016 | I11: =IFERROR(SRC_Incentivi!H8*SRC_Incentivi!H47,0) -> 0 | J11: =IFERROR(SRC_Incentivi!I8*SRC_Incentivi!I47,0) -> 0 | K11: =IFERROR(SRC_Incentivi!J8*SRC_Incentivi!J47,0) -> 0 | L11: =IFERROR(SRC_Incentivi!K8*SRC_Incentivi!K47,0) -> 0 | M11: =IFERROR(SRC_Incentivi!L8*SRC_Incentivi!L47,0) -> 0 | ... Q11: =IFERROR(SRC_Incentivi!P8*SRC_Incentivi!P47,0) -> 0 | R11: =SUM(F11:Q11) -> 99855.048
B12: 5 | C12: MONC2A06 | D12: FV-Kronion Tetto | E12: =IFERROR(AVERAGE(SRC_Incentivi!E48:P48),0) -> 0 | F12: =IFERROR(SRC_Incentivi!E9*SRC_Incentivi!E48,0) -> 0 | G12: =IFERROR(SRC_Incentivi!F9*SRC_Incentivi!F48,0) -> 0 | H12: =IFERROR(SRC_Incentivi!G9*SRC_Incentivi!G48,0) -> 0 | I12: =IFERROR(SRC_Incentivi!H9*SRC_Incentivi!H48,0) -> 0 | J12: =IFERROR(SRC_Incentivi!I9*SRC_Incentivi!I48,0) -> 0 | K12: =IFERROR(SRC_Incentivi!J9*SRC_Incentivi!J48,0) -> 0 | L12: =IFERROR(SRC_Incentivi!K9*SRC_Incentivi!K48,0) -> 0 | M12: =IFERROR(SRC_Incentivi!L9*SRC_Incentivi!L48,0) -> 0 | ... Q12: =IFERROR(SRC_Incentivi!P9*SRC_Incentivi!P48,0) -> 0 | R12: =SUM(F12:Q12) -> 0
B13: 6 | C13: MONC2A07 | D13: FV-Malvizzo a Terra | E13: =IFERROR(AVERAGE(SRC_Incentivi!E49:P49),0) -> 0.251 | F13: =IFERROR(SRC_Incentivi!E10*SRC_Incentivi!E49,0) -> 81201.01 | G13: =IFERROR(SRC_Incentivi!F10*SRC_Incentivi!F49,0) -> 81201.01 | H13: =IFERROR(SRC_Incentivi!G10*SRC_Incentivi!G49,0) -> 81201.01 | I13: =IFERROR(SRC_Incentivi!H10*SRC_Incentivi!H49,0) -> 0 | J13: =IFERROR(SRC_Incentivi!I10*SRC_Incentivi!I49,0) -> 0 | K13: =IFERROR(SRC_Incentivi!J10*SRC_Incentivi!J49,0) -> 0 | L13: =IFERROR(SRC_Incentivi!K10*SRC_Incentivi!K49,0) -> 0 | M13: =IFERROR(SRC_Incentivi!L10*SRC_Incentivi!L49,0) -> 0 | ... Q13: =IFERROR(SRC_Incentivi!P10*SRC_Incentivi!P49,0) -> 0 | R13: =SUM(F13:Q13) -> 243603.03
B14: 7 | C14: MONC2A09 | D14: FV-Melilli | E14: =IFERROR(AVERAGE(SRC_Incentivi!E50:P50),0) -> 0.207 | F14: =IFERROR(SRC_Incentivi!E11*SRC_Incentivi!E50,0) -> 5535.594 | G14: =IFERROR(SRC_Incentivi!F11*SRC_Incentivi!F50,0) -> 5535.594 | H14: =IFERROR(SRC_Incentivi!G11*SRC_Incentivi!G50,0) -> 5535.594 | I14: =IFERROR(SRC_Incentivi!H11*SRC_Incentivi!H50,0) -> 0 | J14: =IFERROR(SRC_Incentivi!I11*SRC_Incentivi!I50,0) -> 0 | K14: =IFERROR(SRC_Incentivi!J11*SRC_Incentivi!J50,0) -> 0 | L14: =IFERROR(SRC_Incentivi!K11*SRC_Incentivi!K50,0) -> 0 | M14: =IFERROR(SRC_Incentivi!L11*SRC_Incentivi!L50,0) -> 0 | ... Q14: =IFERROR(SRC_Incentivi!P11*SRC_Incentivi!P50,0) -> 0 | R14: =SUM(F14:Q14) -> 16606.782
B15: 8 | C15: MONC2A10 | D15: FV-Narbone a Terra Grande | E15: =IFERROR(AVERAGE(SRC_Incentivi!E51:P51),0) -> 0.314 | F15: =IFERROR(SRC_Incentivi!E12*SRC_Incentivi!E51,0) -> 56234.888 | G15: =IFERROR(SRC_Incentivi!F12*SRC_Incentivi!F51,0) -> 56234.888 | H15: =IFERROR(SRC_Incentivi!G12*SRC_Incentivi!G51,0) -> 56234.888 | I15: =IFERROR(SRC_Incentivi!H12*SRC_Incentivi!H51,0) -> 0 | J15: =IFERROR(SRC_Incentivi!I12*SRC_Incentivi!I51,0) -> 0 | K15: =IFERROR(SRC_Incentivi!J12*SRC_Incentivi!J51,0) -> 0 | L15: =IFERROR(SRC_Incentivi!K12*SRC_Incentivi!K51,0) -> 0 | M15: =IFERROR(SRC_Incentivi!L12*SRC_Incentivi!L51,0) -> 0 | ... Q15: =IFERROR(SRC_Incentivi!P12*SRC_Incentivi!P51,0) -> 0 | R15: =SUM(F15:Q15) -> 168704.66
B16: 9 | C16: MONC2A13 | D16: FV-Palazzetto | E16: =IFERROR(AVERAGE(SRC_Incentivi!E52:P52),0) -> 0.384 | F16: =IFERROR(SRC_Incentivi!E13*SRC_Incentivi!E52,0) -> 4934.4 | G16: =IFERROR(SRC_Incentivi!F13*SRC_Incentivi!F52,0) -> 4934.4 | H16: =IFERROR(SRC_Incentivi!G13*SRC_Incentivi!G52,0) -> 4934.4 | I16: =IFERROR(SRC_Incentivi!H13*SRC_Incentivi!H52,0) -> 0 | J16: =IFERROR(SRC_Incentivi!I13*SRC_Incentivi!I52,0) -> 0 | K16: =IFERROR(SRC_Incentivi!J13*SRC_Incentivi!J52,0) -> 0 | L16: =IFERROR(SRC_Incentivi!K13*SRC_Incentivi!K52,0) -> 0 | M16: =IFERROR(SRC_Incentivi!L13*SRC_Incentivi!L52,0) -> 0 | ... Q16: =IFERROR(SRC_Incentivi!P13*SRC_Incentivi!P52,0) -> 0 | R16: =SUM(F16:Q16) -> 14803.2
B17: 10 | C17: MONC2A15 | D17: FV-Serre Gela | E17: =IFERROR(AVERAGE(SRC_Incentivi!E53:P53),0) -> 0.285 | F17: =IFERROR(SRC_Incentivi!E14*SRC_Incentivi!E53,0) -> 114608.19 | G17: =IFERROR(SRC_Incentivi!F14*SRC_Incentivi!F53,0) -> 114608.19 | H17: =IFERROR(SRC_Incentivi!G14*SRC_Incentivi!G53,0) -> 114608.19 | I17: =IFERROR(SRC_Incentivi!H14*SRC_Incentivi!H53,0) -> 0 | J17: =IFERROR(SRC_Incentivi!I14*SRC_Incentivi!I53,0) -> 0 | K17: =IFERROR(SRC_Incentivi!J14*SRC_Incentivi!J53,0) -> 0 | L17: =IFERROR(SRC_Incentivi!K14*SRC_Incentivi!K53,0) -> 0 | M17: =IFERROR(SRC_Incentivi!L14*SRC_Incentivi!L53,0) -> 0 | ... Q17: =IFERROR(SRC_Incentivi!P14*SRC_Incentivi!P53,0) -> 0 | R17: =SUM(F17:Q17) -> 343824.57
B18: 11 | C18: MONC2A16_01 | D18: FV-Serre Narbone Sez. 01 | E18: =IFERROR(AVERAGE(SRC_Incentivi!E54:P54),0) -> 0.491 | F18: =IFERROR(SRC_Incentivi!E15*SRC_Incentivi!E54,0) -> 122701.88 | G18: =IFERROR(SRC_Incentivi!F15*SRC_Incentivi!F54,0) -> 122701.88 | H18: =IFERROR(SRC_Incentivi!G15*SRC_Incentivi!G54,0) -> 122701.88 | I18: =IFERROR(SRC_Incentivi!H15*SRC_Incentivi!H54,0) -> 0 | J18: =IFERROR(SRC_Incentivi!I15*SRC_Incentivi!I54,0) -> 0 | K18: =IFERROR(SRC_Incentivi!J15*SRC_Incentivi!J54,0) -> 0 | L18: =IFERROR(SRC_Incentivi!K15*SRC_Incentivi!K54,0) -> 0 | M18: =IFERROR(SRC_Incentivi!L15*SRC_Incentivi!L54,0) -> 0 | ... Q18: =IFERROR(SRC_Incentivi!P15*SRC_Incentivi!P54,0) -> 0 | R18: =SUM(F18:Q18) -> 368105.65
B19: 12 | C19: MONC2A16_02 | D19: FV-Serre Narbone Sez. 02 | E19: =IFERROR(AVERAGE(SRC_Incentivi!E55:P55),0) -> 0.49 | F19: =IFERROR(SRC_Incentivi!E16*SRC_Incentivi!E55,0) -> 104219.57 | G19: =IFERROR(SRC_Incentivi!F16*SRC_Incentivi!F55,0) -> 104219.57 | H19: =IFERROR(SRC_Incentivi!G16*SRC_Incentivi!G55,0) -> 104219.57 | I19: =IFERROR(SRC_Incentivi!H16*SRC_Incentivi!H55,0) -> 0 | J19: =IFERROR(SRC_Incentivi!I16*SRC_Incentivi!I55,0) -> 0 | K19: =IFERROR(SRC_Incentivi!J16*SRC_Incentivi!J55,0) -> 0 | L19: =IFERROR(SRC_Incentivi!K16*SRC_Incentivi!K55,0) -> 0 | M19: =IFERROR(SRC_Incentivi!L16*SRC_Incentivi!L55,0) -> 0 | ... Q19: =IFERROR(SRC_Incentivi!P16*SRC_Incentivi!P55,0) -> 0 | R19: =SUM(F19:Q19) -> 312658.71
... B23: 16 | C23: MONC2A18 | D23: FV-Tumarrano Partner | E23: =IFERROR(AVERAGE(SRC_Incentivi!E59:P59),0) -> 0.13462 | F23: =IFERROR(SRC_Incentivi!E20*SRC_Incentivi!E59,0) -> 5264.1805 | G23: =IFERROR(SRC_Incentivi!F20*SRC_Incentivi!F59,0) -> 0 | H23: =IFERROR(SRC_Incentivi!G20*SRC_Incentivi!G59,0) -> 0 | I23: =IFERROR(SRC_Incentivi!H20*SRC_Incentivi!H59,0) -> 0 | J23: =IFERROR(SRC_Incentivi!I20*SRC_Incentivi!I59,0) -> 0 | K23: =IFERROR(SRC_Incentivi!J20*SRC_Incentivi!J59,0) -> 0 | L23: =IFERROR(SRC_Incentivi!K20*SRC_Incentivi!K59,0) -> 0 | M23: =IFERROR(SRC_Incentivi!L20*SRC_Incentivi!L59,0) -> 0 | ... Q23: =IFERROR(SRC_Incentivi!P20*SRC_Incentivi!P59,0) -> 0 | R23: =SUM(F23:Q23) -> 5264.1805
B24: TOTALE 📊 ACCONTO INCENTIVI GSE | F24: =SUM(F8:F23) -> 945542.44 | G24: =SUM(G8:G23) -> 940278.26 | H24: =SUM(H8:H23) -> 940278.26 | I24: =SUM(I8:I23) -> 0 | J24: =SUM(J8:J23) -> 0 | K24: =SUM(K8:K23) -> 0 | L24: =SUM(L8:L23) -> 0 | M24: =SUM(M8:M23) -> 0 | ... R24: =SUM(R8:R23) -> 2826099
B26: ✅ CONSUNTIVO INCENTIVI GSE — OWNER × TARIFF
B27: ID | C27: CODE | D27: Impianto / SPV | E27: Tariffa (€/kWh) | F27: Gen | G27: Feb | H27: Mar | I27: Apr | J27: Mag | K27: Giu | L27: Lug | M27: Ago | N27: Set | O27: Ott | P27: Nov | Q27: Dic | R27: Totale Anno (€)
B28: 1 | C28: MONC1A01_01 | D28: FV-Batia S.Francesco Sez. 01 | E28: =IFERROR(AVERAGE(SRC_Incentivi!E44:P44),0) -> 0.217 | F28: =IFERROR(SRC_Incentivi!E25*SRC_Incentivi!E44,0) -> 50249.214 | G28: =IFERROR(SRC_Incentivi!F25*SRC_Incentivi!F44,0) -> 88825.489 | H28: =IFERROR(SRC_Incentivi!G25*SRC_Incentivi!G44,0) -> 0 | I28: =IFERROR(SRC_Incentivi!H25*SRC_Incentivi!H44,0) -> 0 | J28: =IFERROR(SRC_Incentivi!I25*SRC_Incentivi!I44,0) -> 0 | K28: =IFERROR(SRC_Incentivi!J25*SRC_Incentivi!J44,0) -> 0 | L28: =IFERROR(SRC_Incentivi!K25*SRC_Incentivi!K44,0) -> 0 | M28: =IFERROR(SRC_Incentivi!L25*SRC_Incentivi!L44,0) -> 0 | ... Q28: =IFERROR(SRC_Incentivi!P25*SRC_Incentivi!P44,0) -> 0 | R28: =SUM(F28:Q28) -> 139074.7
B29: 2 | C29: MONC1A01_03 | D29: FV-Batia S.Francesco Sez. 02 | E29: =IFERROR(AVERAGE(SRC_Incentivi!E45:P45),0) -> 0 | F29: =IFERROR(SRC_Incentivi!E26*SRC_Incentivi!E45,0) -> 0 | G29: =IFERROR(SRC_Incentivi!F26*SRC_Incentivi!F45,0) -> 0 | H29: =IFERROR(SRC_Incentivi!G26*SRC_Incentivi!G45,0) -> 0 | I29: =IFERROR(SRC_Incentivi!H26*SRC_Incentivi!H45,0) -> 0 | J29: =IFERROR(SRC_Incentivi!I26*SRC_Incentivi!I45,0) -> 0 | K29: =IFERROR(SRC_Incentivi!J26*SRC_Incentivi!J45,0) -> 0 | L29: =IFERROR(SRC_Incentivi!K26*SRC_Incentivi!K45,0) -> 0 | M29: =IFERROR(SRC_Incentivi!L26*SRC_Incentivi!L45,0) -> 0 | ... Q29: =IFERROR(SRC_Incentivi!P26*SRC_Incentivi!P45,0) -> 0 | R29: =SUM(F29:Q29) -> 0
B30: 3 | C30: MONC1A01_04 | D30: FV-Batia S.Francesco Sez. 03 | E30: =IFERROR(AVERAGE(SRC_Incentivi!E46:P46),0) -> 0 | F30: =IFERROR(SRC_Incentivi!E27*SRC_Incentivi!E46,0) -> 0 | G30: =IFERROR(SRC_Incentivi!F27*SRC_Incentivi!F46,0) -> 0 | H30: =IFERROR(SRC_Incentivi!G27*SRC_Incentivi!G46,0) -> 0 | I30: =IFERROR(SRC_Incentivi!H27*SRC_Incentivi!H46,0) -> 0 | J30: =IFERROR(SRC_Incentivi!I27*SRC_Incentivi!I46,0) -> 0 | K30: =IFERROR(SRC_Incentivi!J27*SRC_Incentivi!J46,0) -> 0 | L30: =IFERROR(SRC_Incentivi!K27*SRC_Incentivi!K46,0) -> 0 | M30: =IFERROR(SRC_Incentivi!L27*SRC_Incentivi!L46,0) -> 0 | ... Q30: =IFERROR(SRC_Incentivi!P27*SRC_Incentivi!P46,0) -> 0 | R30: =SUM(F30:Q30) -> 0
B31: 4 | C31: MONC2A03 | D31: FV-Campofranco Tetto | E31: =IFERROR(AVERAGE(SRC_Incentivi!E47:P47),0) -> 0.488 | F31: =IFERROR(SRC_Incentivi!E28*SRC_Incentivi!E47,0) -> 14054.254 | G31: =IFERROR(SRC_Incentivi!F28*SRC_Incentivi!F47,0) -> 25307.046 | H31: =IFERROR(SRC_Incentivi!G28*SRC_Incentivi!G47,0) -> 0 | I31: =IFERROR(SRC_Incentivi!H28*SRC_Incentivi!H47,0) -> 0 | J31: =IFERROR(SRC_Incentivi!I28*SRC_Incentivi!I47,0) -> 0 | K31: =IFERROR(SRC_Incentivi!J28*SRC_Incentivi!J47,0) -> 0 | L31: =IFERROR(SRC_Incentivi!K28*SRC_Incentivi!K47,0) -> 0 | M31: =IFERROR(SRC_Incentivi!L28*SRC_Incentivi!L47,0) -> 0 | ... Q31: =IFERROR(SRC_Incentivi!P28*SRC_Incentivi!P47,0) -> 0 | R31: =SUM(F31:Q31) -> 39361.299
B32: 5 | C32: MONC2A06 | D32: FV-Kronion Tetto | E32: =IFERROR(AVERAGE(SRC_Incentivi!E48:P48),0) -> 0 | F32: =IFERROR(SRC_Incentivi!E29*SRC_Incentivi!E48,0) -> 0 | G32: =IFERROR(SRC_Incentivi!F29*SRC_Incentivi!F48,0) -> 0 | H32: =IFERROR(SRC_Incentivi!G29*SRC_Incentivi!G48,0) -> 0 | I32: =IFERROR(SRC_Incentivi!H29*SRC_Incentivi!H48,0) -> 0 | J32: =IFERROR(SRC_Incentivi!I29*SRC_Incentivi!I48,0) -> 0 | K32: =IFERROR(SRC_Incentivi!J29*SRC_Incentivi!J48,0) -> 0 | L32: =IFERROR(SRC_Incentivi!K29*SRC_Incentivi!K48,0) -> 0 | M32: =IFERROR(SRC_Incentivi!L29*SRC_Incentivi!L48,0) -> 0 | ... Q32: =IFERROR(SRC_Incentivi!P29*SRC_Incentivi!P48,0) -> 0 | R32: =SUM(F32:Q32) -> 0
B33: 6 | C33: MONC2A07 | D33: FV-Malvizzo a Terra | E33: =IFERROR(AVERAGE(SRC_Incentivi!E49:P49),0) -> 0.251 | F33: =IFERROR(SRC_Incentivi!E30*SRC_Incentivi!E49,0) -> 28936.51 | G33: =IFERROR(SRC_Incentivi!F30*SRC_Incentivi!F49,0) -> 53601.075 | H33: =IFERROR(SRC_Incentivi!G30*SRC_Incentivi!G49,0) -> 0 | I33: =IFERROR(SRC_Incentivi!H30*SRC_Incentivi!H49,0) -> 0 | J33: =IFERROR(SRC_Incentivi!I30*SRC_Incentivi!I49,0) -> 0 | K33: =IFERROR(SRC_Incentivi!J30*SRC_Incentivi!J49,0) -> 0 | L33: =IFERROR(SRC_Incentivi!K30*SRC_Incentivi!K49,0) -> 0 | M33: =IFERROR(SRC_Incentivi!L30*SRC_Incentivi!L49,0) -> 0 | ... Q33: =IFERROR(SRC_Incentivi!P30*SRC_Incentivi!P49,0) -> 0 | R33: =SUM(F33:Q33) -> 82537.585
B34: 7 | C34: MONC2A09 | D34: FV-Melilli | E34: =IFERROR(AVERAGE(SRC_Incentivi!E50:P50),0) -> 0.207 | F34: =IFERROR(SRC_Incentivi!E31*SRC_Incentivi!E50,0) -> 7728.345 | G34: =IFERROR(SRC_Incentivi!F31*SRC_Incentivi!F50,0) -> 12396.932 | H34: =IFERROR(SRC_Incentivi!G31*SRC_Incentivi!G50,0) -> 0 | I34: =IFERROR(SRC_Incentivi!H31*SRC_Incentivi!H50,0) -> 0 | J34: =IFERROR(SRC_Incentivi!I31*SRC_Incentivi!I50,0) -> 0 | K34: =IFERROR(SRC_Incentivi!J31*SRC_Incentivi!J50,0) -> 0 | L34: =IFERROR(SRC_Incentivi!K31*SRC_Incentivi!K50,0) -> 0 | M34: =IFERROR(SRC_Incentivi!L31*SRC_Incentivi!L50,0) -> 0 | ... Q34: =IFERROR(SRC_Incentivi!P31*SRC_Incentivi!P50,0) -> 0 | R34: =SUM(F34:Q34) -> 20125.277
B35: 8 | C35: MONC2A10 | D35: FV-Narbone a Terra Grande | E35: =IFERROR(AVERAGE(SRC_Incentivi!E51:P51),0) -> 0.314 | F35: =IFERROR(SRC_Incentivi!E32*SRC_Incentivi!E51,0) -> 24935.823 | G35: =IFERROR(SRC_Incentivi!F32*SRC_Incentivi!F51,0) -> 0 | H35: =IFERROR(SRC_Incentivi!G32*SRC_Incentivi!G51,0) -> 0 | I35: =IFERROR(SRC_Incentivi!H32*SRC_Incentivi!H51,0) -> 0 | J35: =IFERROR(SRC_Incentivi!I32*SRC_Incentivi!I51,0) -> 0 | K35: =IFERROR(SRC_Incentivi!J32*SRC_Incentivi!J51,0) -> 0 | L35: =IFERROR(SRC_Incentivi!K32*SRC_Incentivi!K51,0) -> 0 | M35: =IFERROR(SRC_Incentivi!L32*SRC_Incentivi!L51,0) -> 0 | ... Q35: =IFERROR(SRC_Incentivi!P32*SRC_Incentivi!P51,0) -> 0 | R35: =SUM(F35:Q35) -> 24935.823
B36: 9 | C36: MONC2A13 | D36: FV-Palazzetto | E36: =IFERROR(AVERAGE(SRC_Incentivi!E52:P52),0) -> 0.384 | F36: =IFERROR(SRC_Incentivi!E33*SRC_Incentivi!E52,0) -> 2524.631 | G36: =IFERROR(SRC_Incentivi!F33*SRC_Incentivi!F52,0) -> 3880.6618 | H36: =IFERROR(SRC_Incentivi!G33*SRC_Incentivi!G52,0) -> 0 | I36: =IFERROR(SRC_Incentivi!H33*SRC_Incentivi!H52,0) -> 0 | J36: =IFERROR(SRC_Incentivi!I33*SRC_Incentivi!I52,0) -> 0 | K36: =IFERROR(SRC_Incentivi!J33*SRC_Incentivi!J52,0) -> 0 | L36: =IFERROR(SRC_Incentivi!K33*SRC_Incentivi!K52,0) -> 0 | M36: =IFERROR(SRC_Incentivi!L33*SRC_Incentivi!L52,0) -> 0 | ... Q36: =IFERROR(SRC_Incentivi!P33*SRC_Incentivi!P52,0) -> 0 | R36: =SUM(F36:Q36) -> 6405.2928
B37: 10 | C37: MONC2A15 | D37: FV-Serre Gela | E37: =IFERROR(AVERAGE(SRC_Incentivi!E53:P53),0) -> 0.285 | F37: =IFERROR(SRC_Incentivi!E34*SRC_Incentivi!E53,0) -> 58189.505 | G37: =IFERROR(SRC_Incentivi!F34*SRC_Incentivi!F53,0) -> 80688.886 | H37: =IFERROR(SRC_Incentivi!G34*SRC_Incentivi!G53,0) -> 0 | I37: =IFERROR(SRC_Incentivi!H34*SRC_Incentivi!H53,0) -> 0 | J37: =IFERROR(SRC_Incentivi!I34*SRC_Incentivi!I53,0) -> 0 | K37: =IFERROR(SRC_Incentivi!J34*SRC_Incentivi!J53,0) -> 0 | L37: =IFERROR(SRC_Incentivi!K34*SRC_Incentivi!K53,0) -> 0 | M37: =IFERROR(SRC_Incentivi!L34*SRC_Incentivi!L53,0) -> 0 | ... Q37: =IFERROR(SRC_Incentivi!P34*SRC_Incentivi!P53,0) -> 0 | R37: =SUM(F37:Q37) -> 138878.39
B38: 11 | C38: MONC2A16_01 | D38: FV-Serre Narbone Sez. 01 | E38: =IFERROR(AVERAGE(SRC_Incentivi!E54:P54),0) -> 0.491 | F38: =IFERROR(SRC_Incentivi!E35*SRC_Incentivi!E54,0) -> 65630.556 | G38: =IFERROR(SRC_Incentivi!F35*SRC_Incentivi!F54,0) -> 80517.298 | H38: =IFERROR(SRC_Incentivi!G35*SRC_Incentivi!G54,0) -> 0 | I38: =IFERROR(SRC_Incentivi!H35*SRC_Incentivi!H54,0) -> 0 | J38: =IFERROR(SRC_Incentivi!I35*SRC_Incentivi!I54,0) -> 0 | K38: =IFERROR(SRC_Incentivi!J35*SRC_Incentivi!J54,0) -> 0 | L38: =IFERROR(SRC_Incentivi!K35*SRC_Incentivi!K54,0) -> 0 | M38: =IFERROR(SRC_Incentivi!L35*SRC_Incentivi!L54,0) -> 0 | ... Q38: =IFERROR(SRC_Incentivi!P35*SRC_Incentivi!P54,0) -> 0 | R38: =SUM(F38:Q38) -> 146147.85
B39: 12 | C39: MONC2A16_02 | D39: FV-Serre Narbone Sez. 02 | E39: =IFERROR(AVERAGE(SRC_Incentivi!E55:P55),0) -> 0.49 | F39: =IFERROR(SRC_Incentivi!E36*SRC_Incentivi!E55,0) -> 55244.389 | G39: =IFERROR(SRC_Incentivi!F36*SRC_Incentivi!F55,0) -> 70988.505 | H39: =IFERROR(SRC_Incentivi!G36*SRC_Incentivi!G55,0) -> 0 | I39: =IFERROR(SRC_Incentivi!H36*SRC_Incentivi!H55,0) -> 0 | J39: =IFERROR(SRC_Incentivi!I36*SRC_Incentivi!I55,0) -> 0 | K39: =IFERROR(SRC_Incentivi!J36*SRC_Incentivi!J55,0) -> 0 | L39: =IFERROR(SRC_Incentivi!K36*SRC_Incentivi!K55,0) -> 0 | M39: =IFERROR(SRC_Incentivi!L36*SRC_Incentivi!L55,0) -> 0 | ... Q39: =IFERROR(SRC_Incentivi!P36*SRC_Incentivi!P55,0) -> 0 | R39: =SUM(F39:Q39) -> 126232.89
... B43: 16 | C43: MONC2A18 | D43: FV-Tumarrano Partner | E43: =IFERROR(AVERAGE(SRC_Incentivi!E59:P59),0) -> 0.13462 | F43: =IFERROR(SRC_Incentivi!E40*SRC_Incentivi!E59,0) -> 9292.1038 | G43: =IFERROR(SRC_Incentivi!F40*SRC_Incentivi!F59,0) -> 12341.809 | H43: =IFERROR(SRC_Incentivi!G40*SRC_Incentivi!G59,0) -> 0 | I43: =IFERROR(SRC_Incentivi!H40*SRC_Incentivi!H59,0) -> 0 | J43: =IFERROR(SRC_Incentivi!I40*SRC_Incentivi!I59,0) -> 0 | K43: =IFERROR(SRC_Incentivi!J40*SRC_Incentivi!J59,0) -> 0 | L43: =IFERROR(SRC_Incentivi!K40*SRC_Incentivi!K59,0) -> 0 | M43: =IFERROR(SRC_Incentivi!L40*SRC_Incentivi!L59,0) -> 0 | ... Q43: =IFERROR(SRC_Incentivi!P40*SRC_Incentivi!P59,0) -> 0 | R43: =SUM(F43:Q43) -> 21633.913
B44: TOTALE ✅ CONSUNTIVO INCENTIVI GSE | F44: =SUM(F28:F43) -> 485932.75 | G44: =SUM(G28:G43) -> 637264.92 | H44: =SUM(H28:H43) -> 0 | I44: =SUM(I28:I43) -> 0 | J44: =SUM(J28:J43) -> 0 | K44: =SUM(K28:K43) -> 0 | L44: =SUM(L28:L43) -> 0 | M44: =SUM(M28:M43) -> 0 | ... R44: =SUM(R28:R43) -> 1123197.7
B46: 📐 DELTA INCENTIVI (Consuntivo − Acconto)
B47: ID | C47: CODE | D47: Impianto | F47: Gen | G47: Feb | H47: Mar | I47: Apr | J47: Mag | K47: Giu | L47: Lug | M47: Ago | N47: Set | O47: Ott | P47: Nov | Q47: Dic | R47: Totale (€)
B48: 1 | C48: MONC1A01_01 | D48: FV-Batia S.Francesco Sez. 01 | F48: =F28-F8 -> -59364.864 | G48: =G28-G8 -> -20788.589 | H48: =H28-H8 -> -109614.08 | I48: =I28-I8 -> 0 | J48: =J28-J8 -> 0 | K48: =K28-K8 -> 0 | L48: =L28-L8 -> 0 | M48: =M28-M8 -> 0 | ... Q48: =Q28-Q8 -> 0 | R48: =SUM(F48:Q48) -> -189767.53
B49: 2 | C49: MONC1A01_03 | D49: FV-Batia S.Francesco Sez. 02 | F49: =F29-F9 -> 0 | G49: =G29-G9 -> 0 | H49: =H29-H9 -> 0 | I49: =I29-I9 -> 0 | J49: =J29-J9 -> 0 | K49: =K29-K9 -> 0 | L49: =L29-L9 -> 0 | M49: =M29-M9 -> 0 | ... Q49: =Q29-Q9 -> 0 | R49: =SUM(F49:Q49) -> 0
B50: 3 | C50: MONC1A01_04 | D50: FV-Batia S.Francesco Sez. 03 | F50: =F30-F10 -> 0 | G50: =G30-G10 -> 0 | H50: =H30-H10 -> 0 | I50: =I30-I10 -> 0 | J50: =J30-J10 -> 0 | K50: =K30-K10 -> 0 | L50: =L30-L10 -> 0 | M50: =M30-M10 -> 0 | ... Q50: =Q30-Q10 -> 0 | R50: =SUM(F50:Q50) -> 0
B51: 4 | C51: MONC2A03 | D51: FV-Campofranco Tetto | F51: =F31-F11 -> -19230.762 | G51: =G31-G11 -> -7977.9704 | H51: =H31-H11 -> -33285.016 | I51: =I31-I11 -> 0 | J51: =J31-J11 -> 0 | K51: =K31-K11 -> 0 | L51: =L31-L11 -> 0 | M51: =M31-M11 -> 0 | ... Q51: =Q31-Q11 -> 0 | R51: =SUM(F51:Q51) -> -60493.749
B52: 5 | C52: MONC2A06 | D52: FV-Kronion Tetto | F52: =F32-F12 -> 0 | G52: =G32-G12 -> 0 | H52: =H32-H12 -> 0 | I52: =I32-I12 -> 0 | J52: =J32-J12 -> 0 | K52: =K32-K12 -> 0 | L52: =L32-L12 -> 0 | M52: =M32-M12 -> 0 | ... Q52: =Q32-Q12 -> 0 | R52: =SUM(F52:Q52) -> 0
B53: 6 | C53: MONC2A07 | D53: FV-Malvizzo a Terra | F53: =F33-F13 -> -52264.5 | G53: =G33-G13 -> -27599.935 | H53: =H33-H13 -> -81201.01 | I53: =I33-I13 -> 0 | J53: =J33-J13 -> 0 | K53: =K33-K13 -> 0 | L53: =L33-L13 -> 0 | M53: =M33-M13 -> 0 | ... Q53: =Q33-Q13 -> 0 | R53: =SUM(F53:Q53) -> -161065.45
B54: 7 | C54: MONC2A09 | D54: FV-Melilli | F54: =F34-F14 -> 2192.751 | G54: =G34-G14 -> 6861.3379 | H54: =H34-H14 -> -5535.594 | I54: =I34-I14 -> 0 | J54: =J34-J14 -> 0 | K54: =K34-K14 -> 0 | L54: =L34-L14 -> 0 | M54: =M34-M14 -> 0 | ... Q54: =Q34-Q14 -> 0 | R54: =SUM(F54:Q54) -> 3518.4949
B55: 8 | C55: MONC2A10 | D55: FV-Narbone a Terra Grande | F55: =F35-F15 -> -31299.065 | G55: =G35-G15 -> -56234.888 | H55: =H35-H15 -> -56234.888 | I55: =I35-I15 -> 0 | J55: =J35-J15 -> 0 | K55: =K35-K15 -> 0 | L55: =L35-L15 -> 0 | M55: =M35-M15 -> 0 | ... Q55: =Q35-Q15 -> 0 | R55: =SUM(F55:Q55) -> -143768.84
B56: 9 | C56: MONC2A13 | D56: FV-Palazzetto | F56: =F36-F16 -> -2409.769 | G56: =G36-G16 -> -1053.7382 | H56: =H36-H16 -> -4934.4 | I56: =I36-I16 -> 0 | J56: =J36-J16 -> 0 | K56: =K36-K16 -> 0 | L56: =L36-L16 -> 0 | M56: =M36-M16 -> 0 | ... Q56: =Q36-Q16 -> 0 | R56: =SUM(F56:Q56) -> -8397.9072
B57: 10 | C57: MONC2A15 | D57: FV-Serre Gela | F57: =F37-F17 -> -56418.685 | G57: =G37-G17 -> -33919.304 | H57: =H37-H17 -> -114608.19 | I57: =I37-I17 -> 0 | J57: =J37-J17 -> 0 | K57: =K37-K17 -> 0 | L57: =L37-L17 -> 0 | M57: =M37-M17 -> 0 | ... Q57: =Q37-Q17 -> 0 | R57: =SUM(F57:Q57) -> -204946.18
B58: 11 | C58: MONC2A16_01 | D58: FV-Serre Narbone Sez. 01 | F58: =F38-F18 -> -57071.326 | G58: =G38-G18 -> -42184.584 | H58: =H38-H18 -> -122701.88 | I58: =I38-I18 -> 0 | J58: =J38-J18 -> 0 | K58: =K38-K18 -> 0 | L58: =L38-L18 -> 0 | M58: =M38-M18 -> 0 | ... Q58: =Q38-Q18 -> 0 | R58: =SUM(F58:Q58) -> -221957.79
B59: 12 | C59: MONC2A16_02 | D59: FV-Serre Narbone Sez. 02 | F59: =F39-F19 -> -48975.181 | G59: =G39-G19 -> -33231.065 | H59: =H39-H19 -> -104219.57 | I59: =I39-I19 -> 0 | J59: =J39-J19 -> 0 | K59: =K39-K19 -> 0 | L59: =L39-L19 -> 0 | M59: =M39-M19 -> 0 | ... Q59: =Q39-Q19 -> 0 | R59: =SUM(F59:Q59) -> -186425.82
... B63: 16 | C63: MONC2A18 | D63: FV-Tumarrano Partner | F63: =F43-F23 -> 4027.9233 | G63: =G43-G23 -> 12341.809 | H63: =H43-H23 -> 0 | I63: =I43-I23 -> 0 | J63: =J43-J23 -> 0 | K63: =K43-K23 -> 0 | L63: =L43-L23 -> 0 | M63: =M43-M23 -> 0 | ... Q63: =Q43-Q23 -> 0 | R63: =SUM(F63:Q63) -> 16369.733
B64: TOTALE DELTA | F64: =SUM(F48:F63) -> -459609.69 | G64: =SUM(G48:G63) -> -303013.34 | H64: =SUM(H48:H63) -> -940278.26 | I64: =SUM(I48:I63) -> 0 | J64: =SUM(J48:J63) -> 0 | K64: =SUM(K48:K63) -> 0 | L64: =SUM(L48:L63) -> 0 | M64: =SUM(M48:M63) -> 0 | ... R64: =SUM(R48:R63) -> -1702901.3

Sheet Analisi_Perdite
B1: ⚡ ANALISI PERDITE ENERGETICHE — POTENZA TEORICA vs REALE
B4: FV: E_teorica = H(i) × kWp_DC × PR_target / 1000 | Eolico: E_teorica = P_curve(v_55m) × N_turbine × ore / 1000 | ΔE = E_teorica − E_reale | 850kW/turbina @ ρ=1.15kg/m³
B7: POWER CURVE (Vestas 850kW)
B8: m/s | C8: kW | D8: Ct
B9: 3 | C9: 8.2 | D9: 0.879
B10: 4 | C10: 28.7 | D10: 0.844
B11: 5 | C11: 74.2 | D11: 0.828
B12: 6 | C12: 140.2 | D12: 0.822
B13: 7 | C13: 230.3 | D13: 0.82
B14: 8 | C14: 351 | D14: 0.819
B15: 9 | C15: 499.6 | D15: 0.795
B16: 10 | C16: 660.2 | D16: 0.703
B17: 11 | C17: 758.3 | D17: 0.563
B18: 12 | C18: 811.7 | D18: 0.432
B19: 13 | C19: 837.6 | D19: 0.328
B20: 14 | C20: 843 | D20: 0.256
... B29: 23 | C29: 791.1 | D29: 0.077
B30: Cut-in: 3m/s | Rated: 850kW/turbina | Cut-out: 25m/s
B31: N° TURBINE PER IMPIANTO
B32: Wind - Monte Narbone | C32: 24
B33: Wind - Monte Durrà | C33: 29
B34: Wind - Monte Malvizzo | C34: 19
B36: CONFIG FV
B37: PR Target: | C37: 0.8 | D37: ← modifica
B39: DETTAGLIO PER IMPIANTO E MESE — Q1 2026
B40: ID | C40: Impianto | D40: Tipo | E40: Mese | F40: Gg | G40: Vento m/s (Eo.) o H(i) (FV) | H40: N°Turb. (Eo.) o kWp (FV) | I40: E Teorica (MWh) | J40: E Reale (MWh) | K40: ΔE (MWh) | L40: ΔE % | M40: Status
B41: 1 | C41: Wind - Monte Narbone | D41: Eolico | E41: Gennaio | F41: 31 | G41: =IFERROR(Irraggiamento_PVGIS!E45,0) -> 0 | H41: 24 | I41: =IFERROR(IF(G41<3,0,IF(G41>=23,791.1*H41*744/1000,let(v,G41,vlo,aggregate(14,6,IF($B$9:$B$29<=v,$B$9:$B$29),1),vhi,aggregate(15,6,IF($B$9:$B$29>v,$B$9:$B$29),1),plo,INDEX($C$9:$C$29,MATCH(vlo,$B$9:$B$29,0)),phi,INDEX($C$9:$C$29,MATCH(vhi,$B$9:$B$29,0)),(plo+(v-vlo)/(vhi-vlo)*(phi-plo))*H41*744/1000))),0) -> 0 | J41: =IFERROR(SUMIFS(Fonte_Dati!E:E,Fonte_Dati!D:D,C41,Fonte_Dati!C:C,"Gennaio")/1000,0) -> 4716.6952 | K41: =IFERROR(I41-J41,"") -> -4716.6952 | L41: =IFERROR(K41/I41,"") | M41: =IFERROR(IF(ABS(L41)>0.2,"⚠ Alto",IF(ABS(L41)>0.08,"⚡ Medio","✅ OK")),"—") -> —
B42: 1 | C42: Wind - Monte Narbone | D42: Eolico | E42: Febbraio | F42: 28 | G42: =IFERROR(Irraggiamento_PVGIS!F45,0) -> 0 | H42: 24 | I42: =IFERROR(IF(G42<3,0,IF(G42>=23,791.1*H42*672/1000,let(v,G42,vlo,aggregate(14,6,IF($B$9:$B$29<=v,$B$9:$B$29),1),vhi,aggregate(15,6,IF($B$9:$B$29>v,$B$9:$B$29),1),plo,INDEX($C$9:$C$29,MATCH(vlo,$B$9:$B$29,0)),phi,INDEX($C$9:$C$29,MATCH(vhi,$B$9:$B$29,0)),(plo+(v-vlo)/(vhi-vlo)*(phi-plo))*H42*672/1000))),0) -> 0 | J42: =IFERROR(SUMIFS(Fonte_Dati!E:E,Fonte_Dati!D:D,C42,Fonte_Dati!C:C,"Febbraio")/1000,0) -> 4379.1799 | K42: =IFERROR(I42-J42,"") -> -4379.1799 | L42: =IFERROR(K42/I42,"") | M42: =IFERROR(IF(ABS(L42)>0.2,"⚠ Alto",IF(ABS(L42)>0.08,"⚡ Medio","✅ OK")),"—") -> —
B43: 1 | C43: Wind - Monte Narbone | D43: Eolico | E43: Marzo | F43: 31 | G43: =IFERROR(Irraggiamento_PVGIS!G45,0) -> 0 | H43: 24 | I43: =IFERROR(IF(G43<3,0,IF(G43>=23,791.1*H43*744/1000,let(v,G43,vlo,aggregate(14,6,IF($B$9:$B$29<=v,$B$9:$B$29),1),vhi,aggregate(15,6,IF($B$9:$B$29>v,$B$9:$B$29),1),plo,INDEX($C$9:$C$29,MATCH(vlo,$B$9:$B$29,0)),phi,INDEX($C$9:$C$29,MATCH(vhi,$B$9:$B$29,0)),(plo+(v-vlo)/(vhi-vlo)*(phi-plo))*H43*744/1000))),0) -> 0 | J43: =IFERROR(SUMIFS(Fonte_Dati!E:E,Fonte_Dati!D:D,C43,Fonte_Dati!C:C,"Marzo")/1000,0) -> 0.34854082 | K43: =IFERROR(I43-J43,"") -> -0.34854082 | L43: =IFERROR(K43/I43,"") | M43: =IFERROR(IF(ABS(L43)>0.2,"⚠ Alto",IF(ABS(L43)>0.08,"⚡ Medio","✅ OK")),"—") -> —
B44: Σ 💨 Wind - Monte Narbone (24 turbine) | I44: =SUM(I41:I43) -> 0 | J44: =SUM(J41:J43) -> 9096.2236 | K44: =SUM(K41:K43) -> -9096.2236 | L44: =IFERROR(K44/I44,"")
B45: 2 | C45: Wind - Monte Durrà | D45: Eolico | E45: Gennaio | F45: 31 | G45: =IFERROR(Irraggiamento_PVGIS!E43,0) -> 0 | H45: 29 | I45: =IFERROR(IF(G45<3,0,IF(G45>=23,791.1*H45*744/1000,let(v,G45,vlo,aggregate(14,6,IF($B$9:$B$29<=v,$B$9:$B$29),1),vhi,aggregate(15,6,IF($B$9:$B$29>v,$B$9:$B$29),1),plo,INDEX($C$9:$C$29,MATCH(vlo,$B$9:$B$29,0)),phi,INDEX($C$9:$C$29,MATCH(vhi,$B$9:$B$29,0)),(plo+(v-vlo)/(vhi-vlo)*(phi-plo))*H45*744/1000))),0) -> 0 | J45: =IFERROR(SUMIFS(Fonte_Dati!E:E,Fonte_Dati!D:D,C45,Fonte_Dati!C:C,"Gennaio")/1000,0) -> 3977.1227 | K45: =IFERROR(I45-J45,"") -> -3977.1227 | L45: =IFERROR(K45/I45,"") | M45: =IFERROR(IF(ABS(L45)>0.2,"⚠ Alto",IF(ABS(L45)>0.08,"⚡ Medio","✅ OK")),"—") -> —
B46: 2 | C46: Wind - Monte Durrà | D46: Eolico | E46: Febbraio | F46: 28 | G46: =IFERROR(Irraggiamento_PVGIS!F43,0) -> 0 | H46: 29 | I46: =IFERROR(IF(G46<3,0,IF(G46>=23,791.1*H46*672/1000,let(v,G46,vlo,aggregate(14,6,IF($B$9:$B$29<=v,$B$9:$B$29),1),vhi,aggregate(15,6,IF($B$9:$B$29>v,$B$9:$B$29),1),plo,INDEX($C$9:$C$29,MATCH(vlo,$B$9:$B$29,0)),phi,INDEX($C$9:$C$29,MATCH(vhi,$B$9:$B$29,0)),(plo+(v-vlo)/(vhi-vlo)*(phi-plo))*H46*672/1000))),0) -> 0 | J46: =IFERROR(SUMIFS(Fonte_Dati!E:E,Fonte_Dati!D:D,C46,Fonte_Dati!C:C,"Febbraio")/1000,0) -> 4130.1921 | K46: =IFERROR(I46-J46,"") -> -4130.1921 | L46: =IFERROR(K46/I46,"") | M46: =IFERROR(IF(ABS(L46)>0.2,"⚠ Alto",IF(ABS(L46)>0.08,"⚡ Medio","✅ OK")),"—") -> —
B47: 2 | C47: Wind - Monte Durrà | D47: Eolico | E47: Marzo | F47: 31 | G47: =IFERROR(Irraggiamento_PVGIS!G43,0) -> 0 | H47: 29 | I47: =IFERROR(IF(G47<3,0,IF(G47>=23,791.1*H47*744/1000,let(v,G47,vlo,aggregate(14,6,IF($B$9:$B$29<=v,$B$9:$B$29),1),vhi,aggregate(15,6,IF($B$9:$B$29>v,$B$9:$B$29),1),plo,INDEX($C$9:$C$29,MATCH(vlo,$B$9:$B$29,0)),phi,INDEX($C$9:$C$29,MATCH(vhi,$B$9:$B$29,0)),(plo+(v-vlo)/(vhi-vlo)*(phi-plo))*H47*744/1000))),0) -> 0 | J47: =IFERROR(SUMIFS(Fonte_Dati!E:E,Fonte_Dati!D:D,C47,Fonte_Dati!C:C,"Marzo")/1000,0) -> 0 | K47: =IFERROR(I47-J47,"") -> 0 | L47: =IFERROR(K47/I47,"") | M47: =IFERROR(IF(ABS(L47)>0.2,"⚠ Alto",IF(ABS(L47)>0.08,"⚡ Medio","✅ OK")),"—") -> —
B48: Σ 💨 Wind - Monte Durrà (29 turbine) | I48: =SUM(I45:I47) -> 0 | J48: =SUM(J45:J47) -> 8107.3148 | K48: =SUM(K45:K47) -> -8107.3148 | L48: =IFERROR(K48/I48,"")
B49: 3 | C49: Wind - Monte Malvizzo | D49: Eolico | E49: Gennaio | F49: 31 | G49: =IFERROR(Irraggiamento_PVGIS!E44,0) -> 0 | H49: 19 | I49: =IFERROR(IF(G49<3,0,IF(G49>=23,791.1*H49*744/1000,let(v,G49,vlo,aggregate(14,6,IF($B$9:$B$29<=v,$B$9:$B$29),1),vhi,aggregate(15,6,IF($B$9:$B$29>v,$B$9:$B$29),1),plo,INDEX($C$9:$C$29,MATCH(vlo,$B$9:$B$29,0)),phi,INDEX($C$9:$C$29,MATCH(vhi,$B$9:$B$29,0)),(plo+(v-vlo)/(vhi-vlo)*(phi-plo))*H49*744/1000))),0) -> 0 | J49: =IFERROR(SUMIFS(Fonte_Dati!E:E,Fonte_Dati!D:D,C49,Fonte_Dati!C:C,"Gennaio")/1000,0) -> 1906.8542 | K49: =IFERROR(I49-J49,"") -> -1906.8542 | L49: =IFERROR(K49/I49,"") | M49: =IFERROR(IF(ABS(L49)>0.2,"⚠ Alto",IF(ABS(L49)>0.08,"⚡ Medio","✅ OK")),"—") -> —
B50: 3 | C50: Wind - Monte Malvizzo | D50: Eolico | E50: Febbraio | F50: 28 | G50: =IFERROR(Irraggiamento_PVGIS!F44,0) -> 0 | H50: 19 | I50: =IFERROR(IF(G50<3,0,IF(G50>=23,791.1*H50*672/1000,let(v,G50,vlo,aggregate(14,6,IF($B$9:$B$29<=v,$B$9:$B$29),1),vhi,aggregate(15,6,IF($B$9:$B$29>v,$B$9:$B$29),1),plo,INDEX($C$9:$C$29,MATCH(vlo,$B$9:$B$29,0)),phi,INDEX($C$9:$C$29,MATCH(vhi,$B$9:$B$29,0)),(plo+(v-vlo)/(vhi-vlo)*(phi-plo))*H50*672/1000))),0) -> 0 | J50: =IFERROR(SUMIFS(Fonte_Dati!E:E,Fonte_Dati!D:D,C50,Fonte_Dati!C:C,"Febbraio")/1000,0) -> 2037.2792 | K50: =IFERROR(I50-J50,"") -> -2037.2792 | L50: =IFERROR(K50/I50,"") | M50: =IFERROR(IF(ABS(L50)>0.2,"⚠ Alto",IF(ABS(L50)>0.08,"⚡ Medio","✅ OK")),"—") -> —
B51: 3 | C51: Wind - Monte Malvizzo | D51: Eolico | E51: Marzo | F51: 31 | G51: =IFERROR(Irraggiamento_PVGIS!G44,0) -> 0 | H51: 19 | I51: =IFERROR(IF(G51<3,0,IF(G51>=23,791.1*H51*744/1000,let(v,G51,vlo,aggregate(14,6,IF($B$9:$B$29<=v,$B$9:$B$29),1),vhi,aggregate(15,6,IF($B$9:$B$29>v,$B$9:$B$29),1),plo,INDEX($C$9:$C$29,MATCH(vlo,$B$9:$B$29,0)),phi,INDEX($C$9:$C$29,MATCH(vhi,$B$9:$B$29,0)),(plo+(v-vlo)/(vhi-vlo)*(phi-plo))*H51*744/1000))),0) -> 0 | J51: =IFERROR(SUMIFS(Fonte_Dati!E:E,Fonte_Dati!D:D,C51,Fonte_Dati!C:C,"Marzo")/1000,0) -> 0.9229494 | K51: =IFERROR(I51-J51,"") -> -0.9229494 | L51: =IFERROR(K51/I51,"") | M51: =IFERROR(IF(ABS(L51)>0.2,"⚠ Alto",IF(ABS(L51)>0.08,"⚡ Medio","✅ OK")),"—") -> —
B52: Σ 💨 Wind - Monte Malvizzo (19 turbine) | I52: =SUM(I49:I51) -> 0 | J52: =SUM(J49:J51) -> 3945.0563 | K52: =SUM(K49:K51) -> -3945.0563 | L52: =IFERROR(K52/I52,"")
B53: 4 | C53: FV-Favara Grande | D53: Fotovoltaico | E53: Gennaio | F53: 31 | G53: =IFERROR(Irraggiamento_PVGIS!E33,0) -> 0 | H53: =IFERROR(VLOOKUP(C53,DB_Impianti!C:K,9,0),"") -> 0 | I53: =IFERROR(G53*H53*Analisi_Perdite!C37/1000,"") -> 0 | J53: =IFERROR(SUMIFS(Fonte_Dati!E:E,Fonte_Dati!D:D,C53,Fonte_Dati!C:C,"Gennaio")/1000,0) -> 629.42576 | K53: =IFERROR(I53-J53,"") -> -629.42576 | L53: =IFERROR(K53/I53,"") | M53: =IFERROR(IF(ABS(L53)>0.2,"⚠ Alto",IF(ABS(L53)>0.08,"⚡ Medio","✅ OK")),"—") -> —
B54: 4 | C54: FV-Favara Grande | D54: Fotovoltaico | E54: Febbraio | F54: 28 | G54: =IFERROR(Irraggiamento_PVGIS!F33,0) -> 0 | H54: =IFERROR(VLOOKUP(C54,DB_Impianti!C:K,9,0),"") -> 0 | I54: =IFERROR(G54*H54*Analisi_Perdite!C37/1000,"") -> 0 | J54: =IFERROR(SUMIFS(Fonte_Dati!E:E,Fonte_Dati!D:D,C54,Fonte_Dati!C:C,"Febbraio")/1000,0) -> 914.78672 | K54: =IFERROR(I54-J54,"") -> -914.78672 | L54: =IFERROR(K54/I54,"") | M54: =IFERROR(IF(ABS(L54)>0.2,"⚠ Alto",IF(ABS(L54)>0.08,"⚡ Medio","✅ OK")),"—") -> —
B55: 4 | C55: FV-Favara Grande | D55: Fotovoltaico | E55: Marzo | F55: 31 | G55: =IFERROR(Irraggiamento_PVGIS!G33,0) -> 0 | H55: =IFERROR(VLOOKUP(C55,DB_Impianti!C:K,9,0),"") -> 0 | I55: =IFERROR(G55*H55*Analisi_Perdite!C37/1000,"") -> 0 | J55: =IFERROR(SUMIFS(Fonte_Dati!E:E,Fonte_Dati!D:D,C55,Fonte_Dati!C:C,"Marzo")/1000,0) -> 0 | K55: =IFERROR(I55-J55,"") -> 0 | L55: =IFERROR(K55/I55,"") | M55: =IFERROR(IF(ABS(L55)>0.2,"⚠ Alto",IF(ABS(L55)>0.08,"⚡ Medio","✅ OK")),"—") -> —
B56: Σ ☀ FV-Favara Grande | I56: =SUM(I53:I55) -> 0 | J56: =SUM(J53:J55) -> 1544.2125 | K56: =SUM(K53:K55) -> -1544.2125 | L56: =IFERROR(K56/I56,"")
B57: 5 | C57: FV-Fauma Tetto | D57: Fotovoltaico | E57: Gennaio | F57: 31 | G57: =IFERROR(Irraggiamento_PVGIS!E32,0) -> 0 | H57: =IFERROR(VLOOKUP(C57,DB_Impianti!C:K,9,0),"") -> 0 | I57: =IFERROR(G57*H57*Analisi_Perdite!C37/1000,"") -> 0 | J57: =IFERROR(SUMIFS(Fonte_Dati!E:E,Fonte_Dati!D:D,C57,Fonte_Dati!C:C,"Gennaio")/1000,0) -> 652.4864 | K57: =IFERROR(I57-J57,"") -> -652.4864 | L57: =IFERROR(K57/I57,"") | M57: =IFERROR(IF(ABS(L57)>0.2,"⚠ Alto",IF(ABS(L57)>0.08,"⚡ Medio","✅ OK")),"—") -> —
B58: 5 | C58: FV-Fauma Tetto | D58: Fotovoltaico | E58: Febbraio | F58: 28 | G58: =IFERROR(Irraggiamento_PVGIS!F32,0) -> 0 | H58: =IFERROR(VLOOKUP(C58,DB_Impianti!C:K,9,0),"") -> 0 | I58: =IFERROR(G58*H58*Analisi_Perdite!C37/1000,"") -> 0 | J58: =IFERROR(SUMIFS(Fonte_Dati!E:E,Fonte_Dati!D:D,C58,Fonte_Dati!C:C,"Febbraio")/1000,0) -> 851.4772 | K58: =IFERROR(I58-J58,"") -> -851.4772 | L58: =IFERROR(K58/I58,"") | M58: =IFERROR(IF(ABS(L58)>0.2,"⚠ Alto",IF(ABS(L58)>0.08,"⚡ Medio","✅ OK")),"—") -> —
B59: 5 | C59: FV-Fauma Tetto | D59: Fotovoltaico | E59: Marzo | F59: 31 | G59: =IFERROR(Irraggiamento_PVGIS!G32,0) -> 0 | H59: =IFERROR(VLOOKUP(C59,DB_Impianti!C:K,9,0),"") -> 0 | I59: =IFERROR(G59*H59*Analisi_Perdite!C37/1000,"") -> 0 | J59: =IFERROR(SUMIFS(Fonte_Dati!E:E,Fonte_Dati!D:D,C59,Fonte_Dati!C:C,"Marzo")/1000,0) -> 0 | K59: =IFERROR(I59-J59,"") -> 0 | L59: =IFERROR(K59/I59,"") | M59: =IFERROR(IF(ABS(L59)>0.2,"⚠ Alto",IF(ABS(L59)>0.08,"⚡ Medio","✅ OK")),"—") -> —
B60: Σ ☀ FV-Fauma Tetto | I60: =SUM(I57:I59) -> 0 | J60: =SUM(J57:J59) -> 1503.9636 | K60: =SUM(K57:K59) -> -1503.9636 | L60: =IFERROR(K60/I60,"")
B61: 6 | C61: FV-Batia S. Francesco | D61: Fotovoltaico | E61: Gennaio | F61: 31 | G61: =IFERROR(Irraggiamento_PVGIS!E30,0) -> 0 | H61: =IFERROR(VLOOKUP(C61,DB_Impianti!C:K,9,0),"") -> 0 | I61: =IFERROR(G61*H61*Analisi_Perdite!C37/1000,"") -> 0 | J61: =IFERROR(SUMIFS(Fonte_Dati!E:E,Fonte_Dati!D:D,C61,Fonte_Dati!C:C,"Gennaio")/1000,0) -> 425.76024 | K61: =IFERROR(I61-J61,"") -> -425.76024 | L61: =IFERROR(K61/I61,"") | M61: =IFERROR(IF(ABS(L61)>0.2,"⚠ Alto",IF(ABS(L61)>0.08,"⚡ Medio","✅ OK")),"—") -> —
B62: 6 | C62: FV-Batia S. Francesco | D62: Fotovoltaico | E62: Febbraio | F62: 28 | G62: =IFERROR(Irraggiamento_PVGIS!F30,0) -> 0 | H62: =IFERROR(VLOOKUP(C62,DB_Impianti!C:K,9,0),"") -> 0 | I62: =IFERROR(G62*H62*Analisi_Perdite!C37/1000,"") -> 0 | J62: =IFERROR(SUMIFS(Fonte_Dati!E:E,Fonte_Dati!D:D,C62,Fonte_Dati!C:C,"Febbraio")/1000,0) -> 721.12824 | K62: =IFERROR(I62-J62,"") -> -721.12824 | L62: =IFERROR(K62/I62,"") | M62: =IFERROR(IF(ABS(L62)>0.2,"⚠ Alto",IF(ABS(L62)>0.08,"⚡ Medio","✅ OK")),"—") -> —
B63: 6 | C63: FV-Batia S. Francesco | D63: Fotovoltaico | E63: Marzo | F63: 31 | G63: =IFERROR(Irraggiamento_PVGIS!G30,0) -> 0 | H63: =IFERROR(VLOOKUP(C63,DB_Impianti!C:K,9,0),"") -> 0 | I63: =IFERROR(G63*H63*Analisi_Perdite!C37/1000,"") -> 0 | J63: =IFERROR(SUMIFS(Fonte_Dati!E:E,Fonte_Dati!D:D,C63,Fonte_Dati!C:C,"Marzo")/1000,0) -> 0 | K63: =IFERROR(I63-J63,"") -> 0 | L63: =IFERROR(K63/I63,"") | M63: =IFERROR(IF(ABS(L63)>0.2,"⚠ Alto",IF(ABS(L63)>0.08,"⚡ Medio","✅ OK")),"—") -> —
B64: Σ ☀ FV-Batia S. Francesco | I64: =SUM(I61:I63) -> 0 | J64: =SUM(J61:J63) -> 1146.8885 | K64: =SUM(K61:K63) -> -1146.8885 | L64: =IFERROR(K64/I64,"")
B65: 7 | C65: FV-Serre S.Angelo Muxaro | D65: Fotovoltaico | E65: Gennaio | F65: 31 | G65: =IFERROR(Irraggiamento_PVGIS!E41,0) -> 0 | H65: =IFERROR(VLOOKUP(C65,DB_Impianti!C:K,9,0),"") -> 0 | I65: =IFERROR(G65*H65*Analisi_Perdite!C37/1000,"") -> 0 | J65: =IFERROR(SUMIFS(Fonte_Dati!E:E,Fonte_Dati!D:D,C65,Fonte_Dati!C:C,"Gennaio")/1000,0) -> 356.1996 | K65: =IFERROR(I65-J65,"") -> -356.1996 | L65: =IFERROR(K65/I65,"") | M65: =IFERROR(IF(ABS(L65)>0.2,"⚠ Alto",IF(ABS(L65)>0.08,"⚡ Medio","✅ OK")),"—") -> —
B66: 7 | C66: FV-Serre S.Angelo Muxaro | D66: Fotovoltaico | E66: Febbraio | F66: 28 | G66: =IFERROR(Irraggiamento_PVGIS!F41,0) -> 0 | H66: =IFERROR(VLOOKUP(C66,DB_Impianti!C:K,9,0),"") -> 0 | I66: =IFERROR(G66*H66*Analisi_Perdite!C37/1000,"") -> 0 | J66: =IFERROR(SUMIFS(Fonte_Dati!E:E,Fonte_Dati!D:D,C66,Fonte_Dati!C:C,"Febbraio")/1000,0) -> 430.9296 | K66: =IFERROR(I66-J66,"") -> -430.9296 | L66: =IFERROR(K66/I66,"") | M66: =IFERROR(IF(ABS(L66)>0.2,"⚠ Alto",IF(ABS(L66)>0.08,"⚡ Medio","✅ OK")),"—") -> —
B67: 7 | C67: FV-Serre S.Angelo Muxaro | D67: Fotovoltaico | E67: Marzo | F67: 31 | G67: =IFERROR(Irraggiamento_PVGIS!G41,0) -> 0 | H67: =IFERROR(VLOOKUP(C67,DB_Impianti!C:K,9,0),"") -> 0 | I67: =IFERROR(G67*H67*Analisi_Perdite!C37/1000,"") -> 0 | J67: =IFERROR(SUMIFS(Fonte_Dati!E:E,Fonte_Dati!D:D,C67,Fonte_Dati!C:C,"Marzo")/1000,0) -> 0 | K67: =IFERROR(I67-J67,"") -> 0 | L67: =IFERROR(K67/I67,"") | M67: =IFERROR(IF(ABS(L67)>0.2,"⚠ Alto",IF(ABS(L67)>0.08,"⚡ Medio","✅ OK")),"—") -> —
B68: Σ ☀ FV-Serre S.Angelo Muxaro | I68: =SUM(I65:I67) -> 0 | J68: =SUM(J65:J67) -> 787.1292 | K68: =SUM(K65:K67) -> -787.1292 | L68: =IFERROR(K68/I68,"")
B69: 8 | C69: FV-Serre Narbone | D69: Fotovoltaico | E69: Gennaio | F69: 31 | G69: =IFERROR(Irraggiamento_PVGIS!E40,0) -> 0 | H69: =IFERROR(VLOOKUP(C69,DB_Impianti!C:K,9,0),"") -> 0 | I69: =IFERROR(G69*H69*Analisi_Perdite!C37/1000,"") -> 0 | J69: =IFERROR(SUMIFS(Fonte_Dati!E:E,Fonte_Dati!D:D,C69,Fonte_Dati!C:C,"Gennaio")/1000,0) -> 353.3616 | K69: =IFERROR(I69-J69,"") -> -353.3616 | L69: =IFERROR(K69/I69,"") | M69: =IFERROR(IF(ABS(L69)>0.2,"⚠ Alto",IF(ABS(L69)>0.08,"⚡ Medio","✅ OK")),"—") -> —
B70: 8 | C70: FV-Serre Narbone | D70: Fotovoltaico | E70: Febbraio | F70: 28 | G70: =IFERROR(Irraggiamento_PVGIS!F40,0) -> 0 | H70: =IFERROR(VLOOKUP(C70,DB_Impianti!C:K,9,0),"") -> 0 | I70: =IFERROR(G70*H70*Analisi_Perdite!C37/1000,"") -> 0 | J70: =IFERROR(SUMIFS(Fonte_Dati!E:E,Fonte_Dati!D:D,C70,Fonte_Dati!C:C,"Febbraio")/1000,0) -> 448.146 | K70: =IFERROR(I70-J70,"") -> -448.146 | L70: =IFERROR(K70/I70,"") | M70: =IFERROR(IF(ABS(L70)>0.2,"⚠ Alto",IF(ABS(L70)>0.08,"⚡ Medio","✅ OK")),"—") -> —
B71: 8 | C71: FV-Serre Narbone | D71: Fotovoltaico | E71: Marzo | F71: 31 | G71: =IFERROR(Irraggiamento_PVGIS!G40,0) -> 0 | H71: =IFERROR(VLOOKUP(C71,DB_Impianti!C:K,9,0),"") -> 0 | I71: =IFERROR(G71*H71*Analisi_Perdite!C37/1000,"") -> 0 | J71: =IFERROR(SUMIFS(Fonte_Dati!E:E,Fonte_Dati!D:D,C71,Fonte_Dati!C:C,"Marzo")/1000,0) -> 0 | K71: =IFERROR(I71-J71,"") -> 0 | L71: =IFERROR(K71/I71,"") | M71: =IFERROR(IF(ABS(L71)>0.2,"⚠ Alto",IF(ABS(L71)>0.08,"⚡ Medio","✅ OK")),"—") -> —
B72: Σ ☀ FV-Serre Narbone | I72: =SUM(I69:I71) -> 0 | J72: =SUM(J69:J71) -> 801.5076 | K72: =SUM(K69:K71) -> -801.5076 | L72: =IFERROR(K72/I72,"")
B73: 9 | C73: FV-Perniciara | D73: Fotovoltaico | E73: Gennaio | F73: 31 | G73: =IFERROR(Irraggiamento_PVGIS!E38,0) -> 0 | H73: =IFERROR(VLOOKUP(C73,DB_Impianti!C:K,9,0),"") -> 0 | I73: =IFERROR(G73*H73*Analisi_Perdite!C37/1000,"") -> 0 | J73: =IFERROR(SUMIFS(Fonte_Dati!E:E,Fonte_Dati!D:D,C73,Fonte_Dati!C:C,"Gennaio")/1000,0) -> 209.75475 | K73: =IFERROR(I73-J73,"") -> -209.75475 | L73: =IFERROR(K73/I73,"") | M73: =IFERROR(IF(ABS(L73)>0.2,"⚠ Alto",IF(ABS(L73)>0.08,"⚡ Medio","✅ OK")),"—") -> —
B74: 9 | C74: FV-Perniciara | D74: Fotovoltaico | E74: Febbraio | F74: 28 | G74: =IFERROR(Irraggiamento_PVGIS!F38,0) -> 0 | H74: =IFERROR(VLOOKUP(C74,DB_Impianti!C:K,9,0),"") -> 0 | I74: =IFERROR(G74*H74*Analisi_Perdite!C37/1000,"") -> 0 | J74: =IFERROR(SUMIFS(Fonte_Dati!E:E,Fonte_Dati!D:D,C74,Fonte_Dati!C:C,"Febbraio")/1000,0) -> 311.66175 | K74: =IFERROR(I74-J74,"") -> -311.66175 | L74: =IFERROR(K74/I74,"") | M74: =IFERROR(IF(ABS(L74)>0.2,"⚠ Alto",IF(ABS(L74)>0.08,"⚡ Medio","✅ OK")),"—") -> —
B75: 9 | C75: FV-Perniciara | D75: Fotovoltaico | E75: Marzo | F75: 31 | G75: =IFERROR(Irraggiamento_PVGIS!G38,0) -> 0 | H75: =IFERROR(VLOOKUP(C75,DB_Impianti!C:K,9,0),"") -> 0 | I75: =IFERROR(G75*H75*Analisi_Perdite!C37/1000,"") -> 0 | J75: =IFERROR(SUMIFS(Fonte_Dati!E:E,Fonte_Dati!D:D,C75,Fonte_Dati!C:C,"Marzo")/1000,0) -> 0 | K75: =IFERROR(I75-J75,"") -> 0 | L75: =IFERROR(K75/I75,"") | M75: =IFERROR(IF(ABS(L75)>0.2,"⚠ Alto",IF(ABS(L75)>0.08,"⚡ Medio","✅ OK")),"—") -> —
B76: Σ ☀ FV-Perniciara | I76: =SUM(I73:I75) -> 0 | J76: =SUM(J73:J75) -> 521.4165 | K76: =SUM(K73:K75) -> -521.4165 | L76: =IFERROR(K76/I76,"")
B77: 10 | C77: FV-Serre Gela | D77: Fotovoltaico | E77: Gennaio | F77: 31 | G77: =IFERROR(Irraggiamento_PVGIS!E39,0) -> 0 | H77: =IFERROR(VLOOKUP(C77,DB_Impianti!C:K,9,0),"") -> 0 | I77: =IFERROR(G77*H77*Analisi_Perdite!C37/1000,"") -> 0 | J77: =IFERROR(SUMIFS(Fonte_Dati!E:E,Fonte_Dati!D:D,C77,Fonte_Dati!C:C,"Gennaio")/1000,0) -> 199.29456 | K77: =IFERROR(I77-J77,"") -> -199.29456 | L77: =IFERROR(K77/I77,"") | M77: =IFERROR(IF(ABS(L77)>0.2,"⚠ Alto",IF(ABS(L77)>0.08,"⚡ Medio","✅ OK")),"—") -> —
